Workbook

Sheet Sheet1
A1: ID_CLIENTE | B1: FECHA_ALTA | C1: FECHA_VENTA | D1: DIAS_DESDE_ALTA | E1: SKU | F1: DESCRIPCION | G1: PIEZAS
A2: 1001423 | B2: 46024 | C2: 46028 | D2: 4 | E2: 2398 | F2: AEROSOL NEGRO MATE | G2: 6
A3: 1001423 | B3: 46024 | C3: 46031 | D3: 7 | E3: 2399 | F3: AEROSOL NEGRO BRILLANTE | G3: 12
A4: 1001423 | B4: 46024 | C4: 46041 | D4: 17 | E4: 2451 | F4: AEROSOL SUPER ORO | G4: 6
A5: 1001423 | B5: 46024 | C5: 46051 | D5: 27 | E5: 2300 | F5: AEROSOL BLANCO BRILLANTE | G5: 3
A6: 1001423 | B6: 46024 | C6: 46051 | D6: 27 | E6: 2301 | F6: AEROSOL BLANCO MATE | G6: 6
A7: 1001423 | B7: 46024 | C7: 46051 | D7: 27 | E7: 2343 | F7: AEROSOL ROSA | G7: 3
A8: 1001423 | B8: 46024 | C8: 46051 | D8: 27 | E8: 2344 | F8: AEROSOL MORADO | G8: 3
A9: 1001423 | B9: 46024 | C9: 46051 | D9: 27 | E9: 2345 | F9: AEROSOL ROJO | G9: 3
A10: 1001423 | B10: 46024 | C10: 46051 | D10: 27 | E10: 2390 | F10: AEROSOL ALUMINIO | G10: 3
A11: 1001423 | B11: 46024 | C11: 46051 | D11: 27 | E11: 2397 | F11: AEROSOL NEGRO SEMI BRILLANTE | G11: 3
A12: 1001423 | B12: 46024 | C12: 46051 | D12: 27 | E12: 2398 | F12: AEROSOL NEGRO MATE | G12: 6
A13: 1001423 | B13: 46024 | C13: 46051 | D13: 27 | E13: 2454 | F13: AEROSOL PRISA SUPER CROMO | G13: 3
... A1278: 1002656 | B1278: 46248 | C1278: 46258 | D1278: 10 | E1278: VG-50014 | F1278: VINILICA GLOSI BLANCO ULTRA | G1278: 6

Sheet Hoja1
A3: 1001423
A4: 1001441
A5: 1001446
A6: 1001448
A7: 1001456
A8: 1001467
A9: 1001492
A10: 1001512
A11: 1001514
A12: 1001515
A13: 1001521
A14: 1001564
... A133: 1002656

Sheet TD
A3: Promedio de PIEZAS | B3: ID_CLIENTE
A4: SKU | B4: 1001423 | C4: 1001441 | D4: 1001446 | E4: 1001448 | F4: 1001456 | G4: 1001467 | H4: 1001492 | I4: 1001512 | J4: 1001514 | K4: 1001515 | L4: 1001521 | M4: 1001564 | N4: 1001569 | O4: 1001574 | P4: 1001578 | Q4: 1001582 | R4: 1001588 | S4: 1001594 | T4: 1001595 | U4: 1001599 | V4: 1001600 | W4: 1001608 | X4: 1001609 | Y4: 1001611 | Z4: 1001615 | AA4: 1001626 | AB4: 1001630 | AC4: 1001631 | AD4: 1001637 | AE4: 1001640 | AF4: 1001641 | AG4: 1001648 | AH4: 1001649 | AI4: 1001696 | AJ4: 1001703 | AK4: 1001706 | AL4: 1001709 | AM4: 1001714 | AN4: 1001717 | AO4: 1001720 | AP4: 1001734 | AQ4: 1001742 | AR4: 1001765 | AS4: 1001767 | AT4: 1001772 | AU4: 1001784 | AV4: 1001792 | AW4: 1001793 | AX4: 1001804 | AY4: 1001808 | AZ4: 1001818 | BA4: 1001843 | BB4: 1001844 | BC4: 1001848 | BD4: 1001849 | BE4: 1001852 | BF4: 1001858 | BG4: 1001859 | BH4: 1001871 | BI4: 1001883 | BJ4: 1001884 | BK4: 1001896 | BL4: 1001900 | BM4: 1001914 | BN4: 1001919 | BO4: 1001949 | BP4: 1001981 | BQ4: 1001983 | BR4: 1001999 | BS4: 1002001 | BT4: 1002005 | BU4: 1002010 | BV4: 1002048 | BW4: 1002058 | BX4: 1002063 | BY4: 1002093 | BZ4: 1002094 | CA4: 1002103 | CB4: 1002105 | CC4: 1002109 | CD4: 1002125 | CE4: 1002129 | CF4: 1002134 | CG4: 1002136 | CH4: 1002146 | CI4: 1002148 | CJ4: 1002150 | CK4: 1002154 | CL4: 1002159 | CM4: 1002161 | CN4: 1002162 | CO4: 1002170 | CP4: 1002189 | CQ4: 1002196 | CR4: 1002201 | CS4: 1002208 | CT4: 1002209 | CU4: 1002232 | CV4: 1002239 | CW4: 1002241 | CX4: 1002246 | CY4: 1002262 | CZ4: 1002283 | DA4: 1002309 | DB4: 1002321 | DC4: 1002348 | DD4: 1002356 | DE4: 1002372 | DF4: 1002385 | DG4: 1002399 | DH4: 1002400 | DI4: 1002421 | DJ4: 1002422 | DK4: 1002425 | DL4: 1002433 | DM4: 1002441 | DN4: 1002459 | DO4: 1002502 | DP4: 1002514 | DQ4: 1002521 | DR4: 1002542 | DS4: 1002549 | DT4: 1002551 | DU4: 1002559 | DV4: 1002562 | DW4: 1002575 | DX4: 1002581 | DY4: 1002583 | DZ4: 1002617 | EA4: 1002644 | EB4: 1002656 | EC4: Total general
A5: 360-N | P5: 100 | EC5: 100
A6: 9185 | AV6: 100 | EC6: 100
A7: 9184 | AV7: 50 | EC7: 50
A8: 38551 | BO8: 18 | EC8: 18
A9: SRG-10453 | AV9: 16 | EC9: 16
A10: 21986 | DT10: 12 | EC10: 12
A11: 2367 | DH11: 12 | EC11: 12
A12: 28266 | BR12: 12 | EC12: 12
A13: 22006 | BO13: 12 | EC13: 12
A14: 28136 | BR14: 12 | EC14: 12
A15: 28356 | BR15: 12 | EC15: 12
A16: 28646 | F16: 6 | BR16: 24 | DG16: 6 | DL16: 6 | EC16: 10.5
A17: 29004 | F17: 6 | M17: 12 | EC17: 9
A18: 28656 | BR18: 12 | CZ18: 6 | EC18: 9
A19: 22005 | BO19: 6 | DT19: 12 | EC19: 9
A20: 28936 | BJ20: 6 | BR20: 12 | DG20: 6 | EC20: 8
A21: SRG-10996 | U21: 6 | BC21: 12 | BQ21: 6 | CG21: 6 | EC21: 7.5
A22: SRG-10006 | BC22: 12 | BQ22: 6 | CG22: 6 | DX22: 6 | EC22: 7.5
A23: IG-40561 | AM23: 1 | BB23: 3 | BP23: 6 | BV23: 26 | DB23: 1 | EC23: 7.4
A24: IG-50001 | S24: 1 | AG24: 6 | BD24: 1 | BE24: 6 | BP24: 6 | CB24: 19 | CG24: 2 | DB24: 3 | DC24: 3 | EC24: 7
A25: 2300 | B25: 3 | E25: 6 | K25: 6 | L25: 7 | Q25: 12 | X25: 12 | Y25: 6 | AD25: 6 | AH25: 6 | AI25: 0 | AT25: 6 | AX25: 6 | BJ25: 6 | BO25: 24 | BP25: 12 | BQ25: 6 | BX25: 2 | CR25: 12 | CX25: 12 | DC25: 6 | DN25: 6 | DS25: 4.5 | DU25: 2 | EB25: 6 | EC25: 6.8846154
A26: 29012 | I26: 2 | AQ26: 2 | AU26: 2 | AV26: 40 | DI26: 3 | EC26: 6.4444444
A27: 2399 | B27: 12 | E27: 2 | G27: 6 | K27: 6 | X27: 12 | Y27: 6 | AD27: 2 | AH27: 6 | AI27: 0 | AL27: 12 | AT27: 6 | AX27: 6 | BA27: 12 | BJ27: 6 | BK27: 3 | BL27: 1 | CR27: 6 | CX27: 12 | DC27: 6 | DH27: 24 | DN27: 12 | DS27: 6 | DU27: 2 | EB27: 6 | EC27: 6.2
A28: 2380 | AT28: 6 | BA28: 6 | CX28: 6 | EC28: 6
A29: 28774 | AC29: 6 | BP29: 6 | EC29: 6
A30: 38061 | BO30: 6 | EC30: 6
A31: 15934 | AS31: 6 | EC31: 6
A32: 28106 | DG32: 6 | DL32: 6 | EC32: 6
A33: 28864 | DT33: 6 | EC33: 6
A34: 15994 | DV34: 6 | EC34: 6
A35: 33014 | DT35: 6 | EC35: 6
A36: 28154 | Z36: 6 | EC36: 6
A37: 22004 | DT37: 6 | EC37: 6
A38: 21584 | BO38: 6 | EC38: 6
A39: 28756 | DG39: 6 | EC39: 6
A40: 2375 | BO40: 6 | EC40: 6
A41: 28775 | BP41: 6 | EC41: 6
A42: SRG-11004 | BC42: 6 | EC42: 6
A43: 2335 | BP43: 6 | EC43: 6
A44: 2358 | AK44: 6 | BQ44: 6 | BY44: 6 | DN44: 6 | EC44: 6
A45: 29104 | X45: 6 | EC45: 6
A46: 28456 | BJ46: 6 | CZ46: 6 | DG46: 6 | EC46: 6
A47: 29284 | BP47: 6 | EC47: 6
A48: 2315 | X48: 6 | AL48: 6 | BP48: 6 | BQ48: 6 | DH48: 6 | EC48: 6
A49: 21644 | BO49: 6 | EC49: 6
A50: 2322 | BO50: 6 | EC50: 6
A51: 12774 | CK51: 6 | EC51: 6
A52: 15344 | CK52: 6 | EC52: 6
A53: 2364 | BQ53: 6 | DC53: 6 | EB53: 6 | EC53: 6
A54: SRG-10984 | BC54: 6 | EC54: 6
A55: 2324 | DN55: 6 | EC55: 6
A56: 28566 | DG56: 6 | EC56: 6
A57: SRG-10134 | CE57: 6 | EC57: 6
A58: 28574 | BP58: 6 | EC58: 6
A59: SRG-10584 | CE59: 6 | DM59: 6 | EC59: 6
A60: 28636 | DG60: 6 | EC60: 6
A61: 22995 | AS61: 6 | DT61: 6 | EC61: 6
A62: 22994 | AS62: 6 | DT62: 6 | EC62: 6
A63: 28446 | DG63: 6 | EC63: 6
A64: 28884 | DT64: 6 | EC64: 6
A65: 2451 | B65: 6 | C65: 6 | N65: 6 | Y65: 6 | BK65: 1 | BQ65: 6 | DC65: 6 | DH65: 6 | DS65: 6 | DX65: 6 | EC65: 5.5
A66: 2454 | B66: 3 | C66: 6 | Y66: 6 | AM66: 6 | BQ66: 6 | DS66: 6 | EC66: 5.5
A67: 2397 | B67: 3 | L67: 7 | Y67: 6 | AD67: 6 | AG67: 6 | AL67: 12 | BJ67: 0 | BO67: 12 | CX67: 6 | DU67: 2 | EC67: 5.4545455
A68: 28586 | F68: 6 | S68: 6 | AR68: 6 | BJ68: 6 | BR68: 12 | DG68: 6 | DW68: 2 | EC68: 5.3333333
A69: 2398 | B69: 6 | E69: 6 | L69: 7 | Y69: 6 | AL69: 0 | AX69: 6 | BA69: 12 | BK69: 3 | BQ69: 6 | BZ69: 6 | CR69: 6 | CX69: 6 | DN69: 6 | DS69: 6 | DU69: 2 | EB69: 6 | EC69: 5.3333333
A70: 28966 | DG70: 12 | DS70: 2 | EC70: 5.3333333
A71: 2393 | E71: 6 | Q71: 6 | X71: 6 | Z71: 0 | BO71: 12 | BQ71: 6 | DS71: 6 | EC71: 5.25
A72: 28006 | F72: 12 | N72: 6 | S72: 6 | U72: 6 | V72: 2 | AI72: 6 | AR72: 6 | BJ72: 6 | BP72: 12 | BX72: 6 | BY72: 6 | BZ72: 6 | CH72: 6 | CJ72: 4 | CZ72: 12 | DA72: 2 | DG72: 12 | DK72: 6 | DL72: 6 | DS72: 2 | DU72: 1 | DW72: 2 | EB72: 12 | EC72: 5.21875
A73: 28986 | S73: 6 | U73: 12 | V73: 6 | AI73: 2 | AR73: 6 | AX73: 6 | BC73: 6 | BJ73: 9 | BR73: 6 | BY73: 6 | BZ73: 6 | CH73: 6 | CJ73: 4 | CZ73: 12 | DA73: 2 | DG73: 6 | DK73: 6 | DS73: 2 | DU73: 1 | DV73: 12 | DW73: 2 | EB73: 12 | EC73: 5.21875
A74: IG-40001 | S74: 1 | BB74: 3 | BV74: 10 | DE74: 6 | EC74: 5.2
A75: 29014 | M75: 6 | P75: 12 | S75: 4 | Z75: 0 | AO75: 3 | AQ75: 3 | AR75: 1 | AS75: 12 | AW75: 2 | BG75: 18 | BH75: 6 | BJ75: 6 | BL75: 6 | BP75: 6 | CH75: 4 | CK75: 3 | DO75: 12 | DV75: 6 | EC75: 5.16
A76: BAG-10846 | Q76: 6 | AA76: 12 | BQ76: 6 | BZ76: 6 | DA76: 2 | EC76: 5.1428571
A77: 2301 | B77: 6 | E77: 6 | L77: 7 | AD77: 6 | BX77: 2 | DS77: 6 | DU77: 2 | EB77: 6 | EC77: 5.125
A78: SRG-10994 | U78: 6 | AG78: 2 | AN78: 12 | AW78: 1 | BP78: 6 | BV78: 9 | CE78: 6 | CG78: 3 | CK78: 6 | DM78: 3 | DR78: 6 | EC78: 5.0714286
A79: VG-30003 | D79: 1 | AB79: 3 | AJ79: 3 | BC79: 4 | BM79: 13 | BR79: 6 | EC79: 5
A80: 28575 | J80: 4 | BN80: 6 | EC80: 5
A81: 2345 | B81: 3 | L81: 6 | Q81: 6 | X81: 6 | Y81: 6 | AL81: 6 | BK81: 2 | DC81: 6 | DS81: 3.5 | EB81: 6 | EC81: 4.9090909
A82: 28934 | F82: 6 | BP82: 6 | CJ82: 6 | CR82: 3 | CS82: 3 | CZ82: 6 | DD82: 3 | EC82: 4.875
A83: 28454 | F83: 6 | BP83: 6 | CZ83: 3 | DC83: 3 | EC83: 4.8
A84: 79234 | H84: 12 | L84: 1 | O84: 1 | T84: 2 | Z84: 0 | AH84: 4 | AI84: 0.33333333 | AS84: 15 | AT84: 3 | BD84: 1 | BH84: 20 | BK84: 1 | BL84: 1 | CW84: 10 | CZ84: 10 | DS84: 20 | EC84: 4.7727273
A85: 28806 | N85: 6 | V85: 2 | BC85: 6 | BJ85: 6 | BQ85: 6 | CZ85: 6 | DG85: 6 | EC85: 4.6666667
A86: 2463 | B86: 3 | C86: 6 | L86: 6 | CV86: 6 | DS86: 2 | EC86: 4.6
A87: 28965 | T87: 3 | BC87: 6 | DG87: 6 | DL87: 3 | EC87: 4.5
A88: VG-50004 | D88: 3 | Q88: 6 | EC88: 4.5
A89: 28214 | T89: 6 | BJ89: 3 | EC89: 4.5
A90: 2396 | K90: 6 | AI90: 3 | EC90: 4.5
A91: VG-30014 | BZ91: 6 | CJ91: 6 | CR91: 3 | DG91: 12 | DP91: 0 | EC91: 4.5
A92: 2344 | B92: 3 | CX92: 6 | EC92: 4.5
A93: 2343 | B93: 3 | BQ93: 6 | EC93: 4.5
A94: VG-50614 | BP94: 4.5 | EC94: 4.5
A95: VG-30004 | U95: 12 | AA95: 6 | AB95: 6 | AP95: 1 | BK95: 4 | EC95: 4.4285714
A96: VG-50994 | Q96: 6 | AA96: 6 | AB96: 6 | AO96: 1 | CR96: 3 | EC96: 4.4
A97: 28015 | BC97: 6 | DG97: 6 | DS97: 1 | EC97: 4.3333333
A98: 28584 | D98: 3 | F98: 6 | S98: 3 | BR98: 6 | CF98: 3 | DC98: 6 | DG98: 3 | EC98: 4.2857143
A99: SRG-10004 | F99: 6 | U99: 6 | X99: 6 | AG99: 2 | AN99: 6 | AW99: 1 | BV99: 6 | CE99: 6 | CG99: 3 | CK99: 6 | DR99: 6 | DX99: 3 | EC99: 4.2142857
A100: SRG-10005 | C100: 3 | U100: 6 | BV100: 3 | CG100: 3 | CK100: 6 | EC100: 4.2
A101: 28985 | F101: 6 | O101: 3 | S101: 3 | T101: 6 | U101: 6 | V101: 3 | AA101: 12 | AB101: 6 | AE101: 3 | AI101: 1.5 | AR101: 3 | BC101: 6 | BJ101: 12 | BN101: 6 | BR101: 6 | BY101: 6 | BZ101: 3 | CF101: 3 | CV101: 3 | CZ101: 12 | DA101: 1 | DC101: 6 | DD101: 3 | DG101: 6 | DK101: 6 | DP101: 0 | DR101: 6 | DS101: 3 | DU101: 1 | DW101: 3 | EC101: 4.1944444
A102: 28004 | D102: 3 | F102: 12 | N102: 3 | P102: 9 | S102: 3 | T102: 6 | U102: 6 | V102: 3 | AB102: 6 | AP102: 1 | BJ102: 12 | BK102: 1 | BL102: 1 | BP102: 6 | BR102: 6 | BX102: 3 | BY102: 6 | BZ102: 3 | CF102: 3 | CH102: 6 | CJ102: 2 | CN102: 6 | CR102: 3 | CV102: 3 | CZ102: 6 | DA102: 1 | DC102: 6 | DG102: 12 | DK102: 3 | DL102: 3 | DP102: 0 | DR102: 6 | DS102: 2.5 | DU102: 1 | DV102: 6 | DW102: 3 | EB102: 6 | EC102: 4.1666667
...

Sheet POR PRODUCTO MAS COM
A1: PEDIDO SUGERIDO CLIENTES NUEVOS FELIPE PAIZ
A3: Cuenta de PIEZAS | D3: =SUM(D5:D24) -> 6064.64 | E3: =SUM(E5:E24) -> 4776.74 | H3: PRECIOS | L3: =SUM(L5:L27) -> 58 | M3: =SUM(M5:M27) -> 6872.37 | N3: =SUM(N5:N27) -> 5150.07
A4: SKU | B4: PRODUCTO | C4: CUANTOS CLIENTES COMPRARON POR PRIMERA VEZ / 149 CLIENTES NUEVOS | D4: TY | E4: TQ | F4: UNIDADES PROMEDIO DE COMPRA | G4: ENTERO | H4: TY | I4: TQ | K4: MARCA | L4: PROPUESTA | M4: TY | N4: TQ | O4: VECES QUE SE HIZO RECOMPRA (ENTRE 1RA COMP <90 DIAS) | P4: # CLIENTES QUE HICIERON LA RECOMPRA / 149 ALTAS / 131 HICIERON COMPRA EN <30 DÍAS DE SU ALTA | Q4: RKNG # CLIENTE | R4: % REC | S4: PIEZAS COMPRADAS | T4: # CLIENTES QUE HICIERON LA RECOMPRA / 149 ALTAS / 131 HICIERON COMPRA EN <30 DÍAS DE SU ALTA | U4: RKNG # CLIENTE
A5: IG-30001 | B5: =_xlfn.XLOOKUP(A:A,[1]Hoja1!$C:$C,[1]Hoja1!$D:$D,"",0,1) -> IMPERGLOSI AGUACERO BLANCO 3A | C5: 61 | D5: =_xlfn.XLOOKUP(A:A,[2]Hoja1!$C:$C,[2]Hoja1!$H:$H,"",0,1) -> 885.34 | E5: =_xlfn.XLOOKUP(A:A,[1]Hoja1!$C:$C,[1]Hoja1!$H:$H,"",0,1) -> 708.62 | F5: =_xlfn.XLOOKUP(A:A,TD!A:A,TD!EC:EC,"",0,1) -> 3.4590164 | G5: =INT(F5) -> 3 | H5: =D5*$G$5 -> 2656.02 | I5: =E5*$G$5 -> 2125.86 | J5: IG-30001 | K5: =_xlfn.XLOOKUP(J:J,'[3]FILTROS 2'!$A:$A,'[3]FILTROS 2'!$E:$E,"",0,1) -> IMPERGLOSI AGUACERO 3 AÑOS | M5: =$L$5*D5 -> 0 | N5: =$L5*E5 -> 0 | O5: =_xlfn.XLOOKUP(A:A,[4]TD90D!$A:$A,[4]TD90D!$CW:$CW,"",0,1) -> 65 | P5: =_xlfn.XLOOKUP(A:A,[4]TD90D!$A:$A,[4]TD90D!$CX:$CX,"",0,1) -> 25 | Q5: =_xlfn.XLOOKUP(A:A,[4]TD90D!$A:$A,[4]TD90D!$DA:$DA,"",0,1) -> 2 | R5: =P5/C5 -> 0.40983607 | S5: =_xlfn.XLOOKUP(A:A,'[4]TD90D PZAS'!$A:$A,'[4]TD90D PZAS'!$CW:$CW,"",0,1) -> 244 | T5: =_xlfn.XLOOKUP(A:A,'[4]TD90D PZAS'!$A:$A,'[4]TD90D PZAS'!$CX:$CX,"",0,1) -> 23 | U5: =_xlfn.XLOOKUP(A:A,'[4]TD90D PZAS'!$A:$A,'[4]TD90D PZAS'!$DA:$DA,"",0,1) -> 2
A6: IG-30561 | B6: =_xlfn.XLOOKUP(A:A,[1]Hoja1!$C:$C,[1]Hoja1!$D:$D,"",0,1) -> IMPERGLOSI AGUACERO TERRACOTA 3A | C6: 52 | D6: =_xlfn.XLOOKUP(A:A,[2]Hoja1!$C:$C,[2]Hoja1!$H:$H,"",0,1) -> 885.34 | E6: =_xlfn.XLOOKUP(A:A,[1]Hoja1!$C:$C,[1]Hoja1!$H:$H,"",0,1) -> 708.62 | F6: =_xlfn.XLOOKUP(A:A,TD!A:A,TD!EC:EC,"",0,1) -> 4.0769231 | G6: =INT(F6) -> 4 | H6: =D6*$G$5 -> 2656.02 | I6: =E6*$G$5 -> 2125.86 | J6: IG-30561 | K6: =_xlfn.XLOOKUP(J:J,'[3]FILTROS 2'!$A:$A,'[3]FILTROS 2'!$E:$E,"",0,1) -> IMPERGLOSI AGUACERO 3 AÑOS | M6: =L6*D6 -> 0 | N6: =$L6*E6 -> 0 | O6: =_xlfn.XLOOKUP(A:A,[4]TD90D!$A:$A,[4]TD90D!$CW:$CW,"",0,1) -> 81 | P6: =_xlfn.XLOOKUP(A:A,[4]TD90D!$A:$A,[4]TD90D!$CX:$CX,"",0,1) -> 25 | Q6: =_xlfn.XLOOKUP(A:A,[4]TD90D!$A:$A,[4]TD90D!$DA:$DA,"",0,1) -> 1 | R6: =P6/C6 -> 0.48076923 | S6: =_xlfn.XLOOKUP(A:A,'[4]TD90D PZAS'!$A:$A,'[4]TD90D PZAS'!$CW:$CW,"",0,1) -> 353 | T6: =_xlfn.XLOOKUP(A:A,'[4]TD90D PZAS'!$A:$A,'[4]TD90D PZAS'!$CX:$CX,"",0,1) -> 23 | U6: =_xlfn.XLOOKUP(A:A,'[4]TD90D PZAS'!$A:$A,'[4]TD90D PZAS'!$DA:$DA,"",0,1) -> 1
A7: 28984 | B7: =_xlfn.XLOOKUP(A:A,[1]Hoja1!$C:$C,[1]Hoja1!$D:$D,"",0,1) -> BRILLON NEGRO | C7: 52 | D7: =_xlfn.XLOOKUP(A:A,[2]Hoja1!$C:$C,[2]Hoja1!$H:$H,"",0,1) -> 150.86 | E7: =_xlfn.XLOOKUP(A:A,[1]Hoja1!$C:$C,[1]Hoja1!$H:$H,"",0,1) -> 112.93 | F7: =_xlfn.XLOOKUP(A:A,TD!A:A,TD!EC:EC,"",0,1) -> 3.9423077 | G7: =INT(F7) -> 3 | H7: =D7*$G$5 -> 452.58 | I7: =E7*$G$5 -> 338.79 | J7: 28984 | K7: =_xlfn.XLOOKUP(J:J,'[3]FILTROS 2'!$A:$A,'[3]FILTROS 2'!$E:$E,"",0,1) -> ESMALTE - BRILLON | L7: 4 | M7: =L7*D7 -> 603.44 | N7: =$L7*E7 -> 451.72 | O7: =_xlfn.XLOOKUP(A:A,[4]TD90D!$A:$A,[4]TD90D!$CW:$CW,"",0,1) -> 58 | P7: =_xlfn.XLOOKUP(A:A,[4]TD90D!$A:$A,[4]TD90D!$CX:$CX,"",0,1) -> 22 | Q7: =_xlfn.XLOOKUP(A:A,[4]TD90D!$A:$A,[4]TD90D!$DA:$DA,"",0,1) -> 3 | R7: =P7/C7 -> 0.42307692 | S7: =_xlfn.XLOOKUP(A:A,'[4]TD90D PZAS'!$A:$A,'[4]TD90D PZAS'!$CW:$CW,"",0,1) -> 293 | T7: =_xlfn.XLOOKUP(A:A,'[4]TD90D PZAS'!$A:$A,'[4]TD90D PZAS'!$CX:$CX,"",0,1) -> 21 | U7: =_xlfn.XLOOKUP(A:A,'[4]TD90D PZAS'!$A:$A,'[4]TD90D PZAS'!$DA:$DA,"",0,1) -> 3
A8: 28004 | B8: =_xlfn.XLOOKUP(A:A,[1]Hoja1!$C:$C,[1]Hoja1!$D:$D,"",0,1) -> ESMALTE BRILLON BLANCO | C8: 48 | D8: =_xlfn.XLOOKUP(A:A,[2]Hoja1!$C:$C,[2]Hoja1!$H:$H,"",0,1) -> 150.86 | E8: =_xlfn.XLOOKUP(A:A,[1]Hoja1!$C:$C,[1]Hoja1!$H:$H,"",0,1) -> 112.93 | F8: =_xlfn.XLOOKUP(A:A,TD!A:A,TD!EC:EC,"",0,1) -> 4.1666667 | G8: =INT(F8) -> 4 | H8: =D8*$G$5 -> 452.58 | I8: =E8*$G$5 -> 338.79 | J8: 28004 | K8: =_xlfn.XLOOKUP(J:J,'[3]FILTROS 2'!$A:$A,'[3]FILTROS 2'!$E:$E,"",0,1) -> ESMALTE - BRILLON | L8: 4 | M8: =L8*D8 -> 603.44 | N8: =$L8*E8 -> 451.72 | O8: =_xlfn.XLOOKUP(A:A,[4]TD90D!$A:$A,[4]TD90D!$CW:$CW,"",0,1) -> 57 | P8: =_xlfn.XLOOKUP(A:A,[4]TD90D!$A:$A,[4]TD90D!$CX:$CX,"",0,1) -> 21 | Q8: =_xlfn.XLOOKUP(A:A,[4]TD90D!$A:$A,[4]TD90D!$DA:$DA,"",0,1) -> 4 | R8: =P8/C8 -> 0.4375 | S8: =_xlfn.XLOOKUP(A:A,'[4]TD90D PZAS'!$A:$A,'[4]TD90D PZAS'!$CW:$CW,"",0,1) -> 308 | T8: =_xlfn.XLOOKUP(A:A,'[4]TD90D PZAS'!$A:$A,'[4]TD90D PZAS'!$CX:$CX,"",0,1) -> 20 | U8: =_xlfn.XLOOKUP(A:A,'[4]TD90D PZAS'!$A:$A,'[4]TD90D PZAS'!$DA:$DA,"",0,1) -> 4
A9: 28005 | B9: =_xlfn.XLOOKUP(A:A,[1]Hoja1!$C:$C,[1]Hoja1!$D:$D,"",0,1) -> BRILLON BLANCO | C9: 46 | D9: =_xlfn.XLOOKUP(A:A,[2]Hoja1!$C:$C,[2]Hoja1!$H:$H,"",0,1) -> 90.52 | E9: =_xlfn.XLOOKUP(A:A,[1]Hoja1!$C:$C,[1]Hoja1!$H:$H,"",0,1) -> 67.24 | F9: =_xlfn.XLOOKUP(A:A,TD!A:A,TD!EC:EC,"",0,1) -> 3.6956522 | G9: =INT(F9) -> 3 | H9: =D9*$G$5 -> 271.56 | I9: =E9*$G$5 -> 201.72 | J9: 28005 | K9: =_xlfn.XLOOKUP(J:J,'[3]FILTROS 2'!$A:$A,'[3]FILTROS 2'!$E:$E,"",0,1) -> ESMALTE - BRILLON | L9: 3 | M9: =L9*D9 -> 271.56 | N9: =$L9*E9 -> 201.72 | O9: =_xlfn.XLOOKUP(A:A,[4]TD90D!$A:$A,[4]TD90D!$CW:$CW,"",0,1) -> 46 | P9: =_xlfn.XLOOKUP(A:A,[4]TD90D!$A:$A,[4]TD90D!$CX:$CX,"",0,1) -> 16 | Q9: =_xlfn.XLOOKUP(A:A,[4]TD90D!$A:$A,[4]TD90D!$DA:$DA,"",0,1) -> 5 | R9: =P9/C9 -> 0.34782609 | S9: =_xlfn.XLOOKUP(A:A,'[4]TD90D PZAS'!$A:$A,'[4]TD90D PZAS'!$CW:$CW,"",0,1) -> 211 | T9: =_xlfn.XLOOKUP(A:A,'[4]TD90D PZAS'!$A:$A,'[4]TD90D PZAS'!$CX:$CX,"",0,1) -> 15 | U9: =_xlfn.XLOOKUP(A:A,'[4]TD90D PZAS'!$A:$A,'[4]TD90D PZAS'!$DA:$DA,"",0,1) -> 6
A10: 28985 | B10: =_xlfn.XLOOKUP(A:A,[1]Hoja1!$C:$C,[1]Hoja1!$D:$D,"",0,1) -> BRILLON NEGRO | C10: 36 | D10: =_xlfn.XLOOKUP(A:A,[2]Hoja1!$C:$C,[2]Hoja1!$H:$H,"",0,1) -> 90.52 | E10: =_xlfn.XLOOKUP(A:A,[1]Hoja1!$C:$C,[1]Hoja1!$H:$H,"",0,1) -> 67.24 | F10: =_xlfn.XLOOKUP(A:A,TD!A:A,TD!EC:EC,"",0,1) -> 4.1944444 | G10: =INT(F10) -> 4 | H10: =D10*$G$5 -> 271.56 | I10: =E10*$G$5 -> 201.72 | J10: 28985 | K10: =_xlfn.XLOOKUP(J:J,'[3]FILTROS 2'!$A:$A,'[3]FILTROS 2'!$E:$E,"",0,1) -> ESMALTE - BRILLON | L10: 4 | M10: =L10*D10 -> 362.08 | N10: =$L10*E10 -> 268.96 | O10: =_xlfn.XLOOKUP(A:A,[4]TD90D!$A:$A,[4]TD90D!$CW:$CW,"",0,1) -> 28 | P10: =_xlfn.XLOOKUP(A:A,[4]TD90D!$A:$A,[4]TD90D!$CX:$CX,"",0,1) -> 12 | Q10: =_xlfn.XLOOKUP(A:A,[4]TD90D!$A:$A,[4]TD90D!$DA:$DA,"",0,1) -> 8 | R10: =P10/C10 -> 0.33333333 | S10: =_xlfn.XLOOKUP(A:A,'[4]TD90D PZAS'!$A:$A,'[4]TD90D PZAS'!$CW:$CW,"",0,1) -> 105 | T10: =_xlfn.XLOOKUP(A:A,'[4]TD90D PZAS'!$A:$A,'[4]TD90D PZAS'!$CX:$CX,"",0,1) -> 11 | U10: =_xlfn.XLOOKUP(A:A,'[4]TD90D PZAS'!$A:$A,'[4]TD90D PZAS'!$DA:$DA,"",0,1) -> 11
A11: 28986 | B11: =_xlfn.XLOOKUP(A:A,[1]Hoja1!$C:$C,[1]Hoja1!$D:$D,"",0,1) -> BRILLON NEGRO | C11: 32 | D11: =_xlfn.XLOOKUP(A:A,[2]Hoja1!$C:$C,[2]Hoja1!$H:$H,"",0,1) -> 58.62 | E11: =_xlfn.XLOOKUP(A:A,[1]Hoja1!$C:$C,[1]Hoja1!$H:$H,"",0,1) -> 43.97 | F11: =_xlfn.XLOOKUP(A:A,TD!A:A,TD!EC:EC,"",0,1) -> 5.21875 | G11: =INT(F11) -> 5 | H11: =D11*$G$5 -> 175.86 | I11: =E11*$G$5 -> 131.91 | J11: 28986 | K11: =_xlfn.XLOOKUP(J:J,'[3]FILTROS 2'!$A:$A,'[3]FILTROS 2'!$E:$E,"",0,1) -> ESMALTE - BRILLON | L11: 4 | M11: =L11*D11 -> 234.48 | N11: =$L11*E11 -> 175.88 | O11: =_xlfn.XLOOKUP(A:A,[4]TD90D!$A:$A,[4]TD90D!$CW:$CW,"",0,1) -> 29 | P11: =_xlfn.XLOOKUP(A:A,[4]TD90D!$A:$A,[4]TD90D!$CX:$CX,"",0,1) -> 11 | Q11: =_xlfn.XLOOKUP(A:A,[4]TD90D!$A:$A,[4]TD90D!$DA:$DA,"",0,1) -> 10 | R11: =P11/C11 -> 0.34375 | S11: =_xlfn.XLOOKUP(A:A,'[4]TD90D PZAS'!$A:$A,'[4]TD90D PZAS'!$CW:$CW,"",0,1) -> 154 | T11: =_xlfn.XLOOKUP(A:A,'[4]TD90D PZAS'!$A:$A,'[4]TD90D PZAS'!$CX:$CX,"",0,1) -> 11 | U11: =_xlfn.XLOOKUP(A:A,'[4]TD90D PZAS'!$A:$A,'[4]TD90D PZAS'!$DA:$DA,"",0,1) -> 8
A12: 28006 | B12: =_xlfn.XLOOKUP(A:A,[1]Hoja1!$C:$C,[1]Hoja1!$D:$D,"",0,1) -> BRILLON BLANCO | C12: 32 | D12: =_xlfn.XLOOKUP(A:A,[2]Hoja1!$C:$C,[2]Hoja1!$H:$H,"",0,1) -> 58.62 | E12: =_xlfn.XLOOKUP(A:A,[1]Hoja1!$C:$C,[1]Hoja1!$H:$H,"",0,1) -> 43.97 | F12: =_xlfn.XLOOKUP(A:A,TD!A:A,TD!EC:EC,"",0,1) -> 5.21875 | G12: =INT(F12) -> 5 | H12: =D12*$G$5 -> 175.86 | I12: =E12*$G$5 -> 131.91 | J12: 28006 | K12: =_xlfn.XLOOKUP(J:J,'[3]FILTROS 2'!$A:$A,'[3]FILTROS 2'!$E:$E,"",0,1) -> ESMALTE - BRILLON | L12: 4 | M12: =L12*D12 -> 234.48 | N12: =$L12*E12 -> 175.88 | O12: =_xlfn.XLOOKUP(A:A,[4]TD90D!$A:$A,[4]TD90D!$CW:$CW,"",0,1) -> 26 | P12: =_xlfn.XLOOKUP(A:A,[4]TD90D!$A:$A,[4]TD90D!$CX:$CX,"",0,1) -> 11 | Q12: =_xlfn.XLOOKUP(A:A,[4]TD90D!$A:$A,[4]TD90D!$DA:$DA,"",0,1) -> 12 | R12: =P12/C12 -> 0.34375 | S12: =_xlfn.XLOOKUP(A:A,'[4]TD90D PZAS'!$A:$A,'[4]TD90D PZAS'!$CW:$CW,"",0,1) -> 130 | T12: =_xlfn.XLOOKUP(A:A,'[4]TD90D PZAS'!$A:$A,'[4]TD90D PZAS'!$CX:$CX,"",0,1) -> 11 | U12: =_xlfn.XLOOKUP(A:A,'[4]TD90D PZAS'!$A:$A,'[4]TD90D PZAS'!$DA:$DA,"",0,1) -> 10
A13: 2399 | B13: =_xlfn.XLOOKUP(A:A,[1]Hoja1!$C:$C,[1]Hoja1!$D:$D,"",0,1) -> AEROSOL NEGRO BRILLANTE | C13: 30 | D13: =_xlfn.XLOOKUP(A:A,[2]Hoja1!$C:$C,[2]Hoja1!$H:$H,"",0,1) -> 55.17 | E13: =_xlfn.XLOOKUP(A:A,[1]Hoja1!$C:$C,[1]Hoja1!$H:$H,"",0,1) -> 41.38 | F13: =_xlfn.XLOOKUP(A:A,TD!A:A,TD!EC:EC,"",0,1) -> 6.2 | G13: =INT(F13) -> 6 | H13: =D13*$G$5 -> 165.51 | I13: =E13*$G$5 -> 124.14 | J13: 2399 | K13: =_xlfn.XLOOKUP(J:J,'[3]FILTROS 2'!$A:$A,'[3]FILTROS 2'!$E:$E,"",0,1) -> AEROSOLES PRISA | L13: 6 | M13: =L13*D13 -> 331.02 | N13: =$L13*E13 -> 248.28 | O13: =_xlfn.XLOOKUP(A:A,[4]TD90D!$A:$A,[4]TD90D!$CW:$CW,"",0,1) -> 44 | P13: =_xlfn.XLOOKUP(A:A,[4]TD90D!$A:$A,[4]TD90D!$CX:$CX,"",0,1) -> 16 | Q13: =_xlfn.XLOOKUP(A:A,[4]TD90D!$A:$A,[4]TD90D!$DA:$DA,"",0,1) -> 6 | R13: =P13/C13 -> 0.53333333 | S13: =_xlfn.XLOOKUP(A:A,'[4]TD90D PZAS'!$A:$A,'[4]TD90D PZAS'!$CW:$CW,"",0,1) -> 502 | T13: =_xlfn.XLOOKUP(A:A,'[4]TD90D PZAS'!$A:$A,'[4]TD90D PZAS'!$CX:$CX,"",0,1) -> 15 | U13: =_xlfn.XLOOKUP(A:A,'[4]TD90D PZAS'!$A:$A,'[4]TD90D PZAS'!$DA:$DA,"",0,1) -> 5
A14: 2300 | B14: =_xlfn.XLOOKUP(A:A,[1]Hoja1!$C:$C,[1]Hoja1!$D:$D,"",0,1) -> AEROSOL BLANCO BRILLANTE | C14: 26 | D14: =_xlfn.XLOOKUP(A:A,[2]Hoja1!$C:$C,[2]Hoja1!$H:$H,"",0,1) -> 55.17 | E14: =_xlfn.XLOOKUP(A:A,[1]Hoja1!$C:$C,[1]Hoja1!$H:$H,"",0,1) -> 41.38 | F14: =_xlfn.XLOOKUP(A:A,TD!A:A,TD!EC:EC,"",0,1) -> 6.8846154 | G14: =INT(F14) -> 6 | H14: =D14*$G$5 -> 165.51 | I14: =E14*$G$5 -> 124.14 | J14: 2300 | K14: =_xlfn.XLOOKUP(J:J,'[3]FILTROS 2'!$A:$A,'[3]FILTROS 2'!$E:$E,"",0,1) -> AEROSOLES PRISA | L14: 6 | M14: =L14*D14 -> 331.02 | N14: =$L14*E14 -> 248.28 | O14: =_xlfn.XLOOKUP(A:A,[4]TD90D!$A:$A,[4]TD90D!$CW:$CW,"",0,1) -> 30 | P14: =_xlfn.XLOOKUP(A:A,[4]TD90D!$A:$A,[4]TD90D!$CX:$CX,"",0,1) -> 13 | Q14: =_xlfn.XLOOKUP(A:A,[4]TD90D!$A:$A,[4]TD90D!$DA:$DA,"",0,1) -> 7 | R14: =P14/C14 -> 0.5 | S14: =_xlfn.XLOOKUP(A:A,'[4]TD90D PZAS'!$A:$A,'[4]TD90D PZAS'!$CW:$CW,"",0,1) -> 229 | T14: =_xlfn.XLOOKUP(A:A,'[4]TD90D PZAS'!$A:$A,'[4]TD90D PZAS'!$CX:$CX,"",0,1) -> 13 | U14: =_xlfn.XLOOKUP(A:A,'[4]TD90D PZAS'!$A:$A,'[4]TD90D PZAS'!$DA:$DA,"",0,1) -> 7
A15: 29014 | B15: =_xlfn.XLOOKUP(A:A,[1]Hoja1!$C:$C,[1]Hoja1!$D:$D,"",0,1) -> RELLENADOR AUTOMOTRIZ C/CATAL. ROJO | C15: 25 | D15: =_xlfn.XLOOKUP(A:A,[2]Hoja1!$C:$C,[2]Hoja1!$H:$H,"",0,1) -> 137.07 | E15: =_xlfn.XLOOKUP(A:A,[1]Hoja1!$C:$C,[1]Hoja1!$H:$H,"",0,1) -> 103.45 | F15: =_xlfn.XLOOKUP(A:A,TD!A:A,TD!EC:EC,"",0,1) -> 5.16 | G15: =INT(F15) -> 5 | H15: =D15*$G$5 -> 411.21 | I15: =E15*$G$5 -> 310.35 | J15: 29014 | K15: =_xlfn.XLOOKUP(J:J,'[3]FILTROS 2'!$A:$A,'[3]FILTROS 2'!$E:$E,"",0,1) -> PASTA RELLENADORA | L15: 3 | M15: =L15*D15 -> 411.21 | N15: =$L15*E15 -> 310.35 | O15: =_xlfn.XLOOKUP(A:A,[4]TD90D!$A:$A,[4]TD90D!$CW:$CW,"",0,1) -> 27 | P15: =_xlfn.XLOOKUP(A:A,[4]TD90D!$A:$A,[4]TD90D!$CX:$CX,"",0,1) -> 11 | Q15: =_xlfn.XLOOKUP(A:A,[4]TD90D!$A:$A,[4]TD90D!$DA:$DA,"",0,1) -> 11 | R15: =P15/C15 -> 0.44 | S15: =_xlfn.XLOOKUP(A:A,'[4]TD90D PZAS'!$A:$A,'[4]TD90D PZAS'!$CW:$CW,"",0,1) -> 140 | T15: =_xlfn.XLOOKUP(A:A,'[4]TD90D PZAS'!$A:$A,'[4]TD90D PZAS'!$CX:$CX,"",0,1) -> 11 | U15: =_xlfn.XLOOKUP(A:A,'[4]TD90D PZAS'!$A:$A,'[4]TD90D PZAS'!$DA:$DA,"",0,1) -> 9
A16: 79234 | B16: =_xlfn.XLOOKUP(A:A,[1]Hoja1!$C:$C,[1]Hoja1!$D:$D,"",0,1) -> SIAMIL ECONOMICO MI FL 20 KG | C16: 22 | D16: =_xlfn.XLOOKUP(A:A,[2]Hoja1!$C:$C,[2]Hoja1!$H:$H,"",0,1) -> 163.79 | E16: =_xlfn.XLOOKUP(A:A,[1]Hoja1!$C:$C,[1]Hoja1!$H:$H,"",0,1) -> 123.28 | F16: =_xlfn.XLOOKUP(A:A,TD!A:A,TD!EC:EC,"",0,1) -> 4.7727273 | G16: =INT(F16) -> 4 | H16: =D16*$G$5 -> 491.37 | I16: =E16*$G$5 -> 369.84 | J16: 79234 | K16: =_xlfn.XLOOKUP(J:J,'[3]FILTROS 2'!$A:$A,'[3]FILTROS 2'!$E:$E,"",0,1) -> SIAMIL | L16: 4 | M16: =L16*D16 -> 655.16 | N16: =$L16*E16 -> 493.12 | O16: =_xlfn.XLOOKUP(A:A,[4]TD90D!$A:$A,[4]TD90D!$CW:$CW,"",0,1) -> 31 | P16: =_xlfn.XLOOKUP(A:A,[4]TD90D!$A:$A,[4]TD90D!$CX:$CX,"",0,1) -> 11 | Q16: =_xlfn.XLOOKUP(A:A,[4]TD90D!$A:$A,[4]TD90D!$DA:$DA,"",0,1) -> 9 | R16: =P16/C16 -> 0.5 | S16: =_xlfn.XLOOKUP(A:A,'[4]TD90D PZAS'!$A:$A,'[4]TD90D PZAS'!$CW:$CW,"",0,1) -> 211 | T16: =_xlfn.XLOOKUP(A:A,'[4]TD90D PZAS'!$A:$A,'[4]TD90D PZAS'!$CX:$CX,"",0,1) -> 10 | U16: =_xlfn.XLOOKUP(A:A,'[4]TD90D PZAS'!$A:$A,'[4]TD90D PZAS'!$DA:$DA,"",0,1) -> 12
A17: IG-50561 | B17: =_xlfn.XLOOKUP(A:A,[1]Hoja1!$C:$C,[1]Hoja1!$D:$D,"",0,1) -> IMPERGLOSI AGUACERO TERRACOTA 5A | C17: 18 | D17: =_xlfn.XLOOKUP(A:A,[2]Hoja1!$C:$C,[2]Hoja1!$H:$H,"",0,1) -> 1118.97 | E17: =_xlfn.XLOOKUP(A:A,[1]Hoja1!$C:$C,[1]Hoja1!$H:$H,"",0,1) -> 896.55 | F17: =_xlfn.XLOOKUP(A:A,TD!A:A,TD!EC:EC,"",0,1) -> 3.6111111 | G17: =INT(F17) -> 3 | H17: =D17*$G$5 -> 3356.91 | I17: =E17*$G$5 -> 2689.65 | J17: IG-50561 | K17: =_xlfn.XLOOKUP(J:J,'[3]FILTROS 2'!$A:$A,'[3]FILTROS 2'!$E:$E,"",0,1) -> IMPERGLOSI AGUACERO 5 AÑOS | M17: =L17*D17 -> 0 | N17: =$L17*E17 -> 0 | O17: =_xlfn.XLOOKUP(A:A,[4]TD90D!$A:$A,[4]TD90D!$CW:$CW,"",0,1) -> 20 | P17: =_xlfn.XLOOKUP(A:A,[4]TD90D!$A:$A,[4]TD90D!$CX:$CX,"",0,1) -> 7 | Q17: =_xlfn.XLOOKUP(A:A,[4]TD90D!$A:$A,[4]TD90D!$DA:$DA,"",0,1) -> 0 | R17: =P17/C17 -> 0.38888889 | S17: =_xlfn.XLOOKUP(A:A,'[4]TD90D PZAS'!$A:$A,'[4]TD90D PZAS'!$CW:$CW,"",0,1) -> 109 | T17: =_xlfn.XLOOKUP(A:A,'[4]TD90D PZAS'!$A:$A,'[4]TD90D PZAS'!$CX:$CX,"",0,1) -> 6 | U17: =_xlfn.XLOOKUP(A:A,'[4]TD90D PZAS'!$A:$A,'[4]TD90D PZAS'!$DA:$DA,"",0,1) -> 14
A18: 2398 | B18: =_xlfn.XLOOKUP(A:A,[1]Hoja1!$C:$C,[1]Hoja1!$D:$D,"",0,1) -> AEROSOL NEGRO MATE | C18: 18 | D18: =_xlfn.XLOOKUP(A:A,[2]Hoja1!$C:$C,[2]Hoja1!$H:$H,"",0,1) -> 55.17 | E18: =_xlfn.XLOOKUP(A:A,[1]Hoja1!$C:$C,[1]Hoja1!$H:$H,"",0,1) -> 41.38 | F18: =_xlfn.XLOOKUP(A:A,TD!A:A,TD!EC:EC,"",0,1) -> 5.3333333 | G18: =INT(F18) -> 5 | H18: =D18*$G$5 -> 165.51 | I18: =E18*$G$5 -> 124.14 | J18: 2398 | K18: =_xlfn.XLOOKUP(J:J,'[3]FILTROS 2'!$A:$A,'[3]FILTROS 2'!$E:$E,"",0,1) -> AEROSOLES PRISA | L18: 5 | M18: =L18*D18 -> 275.85 | N18: =$L18*E18 -> 206.9 | O18: =_xlfn.XLOOKUP(A:A,[4]TD90D!$A:$A,[4]TD90D!$CW:$CW,"",0,1) -> 26 | P18: =_xlfn.XLOOKUP(A:A,[4]TD90D!$A:$A,[4]TD90D!$CX:$CX,"",0,1) -> 10 | Q18: =_xlfn.XLOOKUP(A:A,[4]TD90D!$A:$A,[4]TD90D!$DA:$DA,"",0,1) -> 0 | R18: =P18/C18 -> 0.55555556 | S18: =_xlfn.XLOOKUP(A:A,'[4]TD90D PZAS'!$A:$A,'[4]TD90D PZAS'!$CW:$CW,"",0,1) -> 156 | T18: =_xlfn.XLOOKUP(A:A,'[4]TD90D PZAS'!$A:$A,'[4]TD90D PZAS'!$CX:$CX,"",0,1) -> 9 | U18: =_xlfn.XLOOKUP(A:A,'[4]TD90D PZAS'!$A:$A,'[4]TD90D PZAS'!$DA:$DA,"",0,1) -> 13
A19: IG-30563 | B19: =_xlfn.XLOOKUP(A:A,[1]Hoja1!$C:$C,[1]Hoja1!$D:$D,"",0,1) -> IMPERGLOSI AGUACERO TERRACOTA 3A | C19: 16 | D19: =_xlfn.XLOOKUP(A:A,[2]Hoja1!$C:$C,[2]Hoja1!$H:$H,"",0,1) -> 225 | E19: =_xlfn.XLOOKUP(A:A,[1]Hoja1!$C:$C,[1]Hoja1!$H:$H,"",0,1) -> 179.31 | F19: =_xlfn.XLOOKUP(A:A,TD!A:A,TD!EC:EC,"",0,1) -> 3.125 | G19: =INT(F19) -> 3 | H19: =D19*$G$5 -> 675 | I19: =E19*$G$5 -> 537.93 | J19: IG-30563 | K19: =_xlfn.XLOOKUP(J:J,'[3]FILTROS 2'!$A:$A,'[3]FILTROS 2'!$E:$E,"",0,1) -> IMPERGLOSI AGUACERO 3 AÑOS | M19: =L19*D19 -> 0 | N19: =$L19*E19 -> 0 | O19: =_xlfn.XLOOKUP(A:A,[4]TD90D!$A:$A,[4]TD90D!$CW:$CW,"",0,1) -> 11 | P19: =_xlfn.XLOOKUP(A:A,[4]TD90D!$A:$A,[4]TD90D!$CX:$CX,"",0,1) -> 5 | Q19: =_xlfn.XLOOKUP(A:A,[4]TD90D!$A:$A,[4]TD90D!$DA:$DA,"",0,1) -> 0 | R19: =P19/C19 -> 0.3125 | S19: =_xlfn.XLOOKUP(A:A,'[4]TD90D PZAS'!$A:$A,'[4]TD90D PZAS'!$CW:$CW,"",0,1) -> 25 | T19: =_xlfn.XLOOKUP(A:A,'[4]TD90D PZAS'!$A:$A,'[4]TD90D PZAS'!$CX:$CX,"",0,1) -> 3 | U19: =_xlfn.XLOOKUP(A:A,'[4]TD90D PZAS'!$A:$A,'[4]TD90D PZAS'!$DA:$DA,"",0,1) -> 0
A20: 2390 | B20: =_xlfn.XLOOKUP(A:A,[1]Hoja1!$C:$C,[1]Hoja1!$D:$D,"",0,1) -> AEROSOL ALUMINIO | C20: 14 | D20: =_xlfn.XLOOKUP(A:A,[2]Hoja1!$C:$C,[2]Hoja1!$H:$H,"",0,1) -> 55.17 | E20: =_xlfn.XLOOKUP(A:A,[1]Hoja1!$C:$C,[1]Hoja1!$H:$H,"",0,1) -> 41.38 | F20: =_xlfn.XLOOKUP(A:A,TD!A:A,TD!EC:EC,"",0,1) -> 3.5714286 | G20: =INT(F20) -> 3 | H20: =D20*$G$5 -> 165.51 | I20: =E20*$G$5 -> 124.14 | J20: 2390 | K20: =_xlfn.XLOOKUP(J:J,'[3]FILTROS 2'!$A:$A,'[3]FILTROS 2'!$E:$E,"",0,1) -> AEROSOLES PRISA | L20: 3 | M20: =L20*D20 -> 165.51 | N20: =$L20*E20 -> 124.14 | O20: =_xlfn.XLOOKUP(A:A,[4]TD90D!$A:$A,[4]TD90D!$CW:$CW,"",0,1) -> 16 | P20: =_xlfn.XLOOKUP(A:A,[4]TD90D!$A:$A,[4]TD90D!$CX:$CX,"",0,1) -> 6 | Q20: =_xlfn.XLOOKUP(A:A,[4]TD90D!$A:$A,[4]TD90D!$DA:$DA,"",0,1) -> 0 | R20: =P20/C20 -> 0.42857143 | S20: =_xlfn.XLOOKUP(A:A,'[4]TD90D PZAS'!$A:$A,'[4]TD90D PZAS'!$CW:$CW,"",0,1) -> 45 | T20: =_xlfn.XLOOKUP(A:A,'[4]TD90D PZAS'!$A:$A,'[4]TD90D PZAS'!$CX:$CX,"",0,1) -> 4 | U20: =_xlfn.XLOOKUP(A:A,'[4]TD90D PZAS'!$A:$A,'[4]TD90D PZAS'!$DA:$DA,"",0,1) -> 0
A21: SRG-10994 | B21: =_xlfn.XLOOKUP(A:A,[1]Hoja1!$C:$C,[1]Hoja1!$D:$D,"",0,1) -> ESMALTE GLOSI SR NEGRO BRILLANTE | C21: 14 | D21: =_xlfn.XLOOKUP(A:A,[2]Hoja1!$C:$C,[2]Hoja1!$H:$H,"",0,1) -> 205.17 | E21: =_xlfn.XLOOKUP(A:A,[1]Hoja1!$C:$C,[1]Hoja1!$H:$H,"",0,1) -> 161.21 | F21: =_xlfn.XLOOKUP(A:A,TD!A:A,TD!EC:EC,"",0,1) -> 5.0714286 | G21: =INT(F21) -> 5 | H21: =D21*$G$5 -> 615.51 | I21: =E21*$G$5 -> 483.63 | J21: SRG-10994 | K21: =_xlfn.XLOOKUP(J:J,'[3]FILTROS 2'!$A:$A,'[3]FILTROS 2'!$E:$E,"",0,1) -> ESMALTE - GLOSI SECADO RAPIDO | M21: =L21*D21 -> 0 | N21: =$L21*E21 -> 0 | O21: =_xlfn.XLOOKUP(A:A,[4]TD90D!$A:$A,[4]TD90D!$CW:$CW,"",0,1) -> 10 | P21: =_xlfn.XLOOKUP(A:A,[4]TD90D!$A:$A,[4]TD90D!$CX:$CX,"",0,1) -> 5 | Q21: =_xlfn.XLOOKUP(A:A,[4]TD90D!$A:$A,[4]TD90D!$DA:$DA,"",0,1) -> 0 | R21: =P21/C21 -> 0.35714286 | S21: =_xlfn.XLOOKUP(A:A,'[4]TD90D PZAS'!$A:$A,'[4]TD90D PZAS'!$CW:$CW,"",0,1) -> 66 | T21: =_xlfn.XLOOKUP(A:A,'[4]TD90D PZAS'!$A:$A,'[4]TD90D PZAS'!$CX:$CX,"",0,1) -> 5 | U21: =_xlfn.XLOOKUP(A:A,'[4]TD90D PZAS'!$A:$A,'[4]TD90D PZAS'!$DA:$DA,"",0,1) -> 0
A22: VG-50013 | B22: =_xlfn.XLOOKUP(A:A,[1]Hoja1!$C:$C,[1]Hoja1!$D:$D,"",0,1) -> VINILICA GLOSI BLANCO ULTRA | C22: 14 | D22: =_xlfn.XLOOKUP(A:A,[2]Hoja1!$C:$C,[2]Hoja1!$H:$H,"",0,1) -> 299.14 | E22: =_xlfn.XLOOKUP(A:A,[1]Hoja1!$C:$C,[1]Hoja1!$H:$H,"",0,1) -> 224.14 | F22: =_xlfn.XLOOKUP(A:A,TD!A:A,TD!EC:EC,"",0,1) -> 2.4285714 | G22: =INT(F22) -> 2 | H22: =D22*$G$5 -> 897.42 | I22: =E22*$G$5 -> 672.42 | J22: VG-50013 | K22: =_xlfn.XLOOKUP(J:J,'[3]FILTROS 2'!$A:$A,'[3]FILTROS 2'!$E:$E,"",0,1) -> VINILICA - GLOSI 3 AÑOS | L22: 8 | M22: =L22*D22 -> 2393.12 | N22: =$L22*E22 -> 1793.12 | O22: =_xlfn.XLOOKUP(A:A,[4]TD90D!$A:$A,[4]TD90D!$CW:$CW,"",0,1) -> 13 | P22: =_xlfn.XLOOKUP(A:A,[4]TD90D!$A:$A,[4]TD90D!$CX:$CX,"",0,1) -> 6 | Q22: =_xlfn.XLOOKUP(A:A,[4]TD90D!$A:$A,[4]TD90D!$DA:$DA,"",0,1) -> 0 | R22: =P22/C22 -> 0.42857143 | S22: =_xlfn.XLOOKUP(A:A,'[4]TD90D PZAS'!$A:$A,'[4]TD90D PZAS'!$CW:$CW,"",0,1) -> 39 | T22: =_xlfn.XLOOKUP(A:A,'[4]TD90D PZAS'!$A:$A,'[4]TD90D PZAS'!$CX:$CX,"",0,1) -> 5 | U22: =_xlfn.XLOOKUP(A:A,'[4]TD90D PZAS'!$A:$A,'[4]TD90D PZAS'!$DA:$DA,"",0,1) -> 0
A23: SRG-10004 | B23: =_xlfn.XLOOKUP(A:A,[1]Hoja1!$C:$C,[1]Hoja1!$D:$D,"",0,1) -> ESMALTE GLOSI SR BLANCO | C23: 14 | D23: =_xlfn.XLOOKUP(A:A,[2]Hoja1!$C:$C,[2]Hoja1!$H:$H,"",0,1) -> 205.17 | E23: =_xlfn.XLOOKUP(A:A,[1]Hoja1!$C:$C,[1]Hoja1!$H:$H,"",0,1) -> 161.21 | F23: =_xlfn.XLOOKUP(A:A,TD!A:A,TD!EC:EC,"",0,1) -> 4.2142857 | G23: =INT(F23) -> 4 | H23: =D23*$G$5 -> 615.51 | I23: =E23*$G$5 -> 483.63 | J23: SRG-10004 | K23: =_xlfn.XLOOKUP(J:J,'[3]FILTROS 2'!$A:$A,'[3]FILTROS 2'!$E:$E,"",0,1) -> ESMALTE - GLOSI SECADO RAPIDO | O23: =_xlfn.XLOOKUP(A:A,[4]TD90D!$A:$A,[4]TD90D!$CW:$CW,"",0,1) -> 6 | P23: =_xlfn.XLOOKUP(A:A,[4]TD90D!$A:$A,[4]TD90D!$CX:$CX,"",0,1) -> 3 | Q23: =_xlfn.XLOOKUP(A:A,[4]TD90D!$A:$A,[4]TD90D!$DA:$DA,"",0,1) -> 0 | R23: =P23/C23 -> 0.21428571 | S23: =_xlfn.XLOOKUP(A:A,'[4]TD90D PZAS'!$A:$A,'[4]TD90D PZAS'!$CW:$CW,"",0,1) -> 28 | T23: =_xlfn.XLOOKUP(A:A,'[4]TD90D PZAS'!$A:$A,'[4]TD90D PZAS'!$CX:$CX,"",0,1) -> 3 | U23: =_xlfn.XLOOKUP(A:A,'[4]TD90D PZAS'!$A:$A,'[4]TD90D PZAS'!$DA:$DA,"",0,1) -> 0
A24: IG-50001 | B24: =_xlfn.XLOOKUP(A:A,[1]Hoja1!$C:$C,[1]Hoja1!$D:$D,"",0,1) -> IMPERGLOSI AGUACERO BLANCO 5A | C24: 13 | D24: =_xlfn.XLOOKUP(A:A,[2]Hoja1!$C:$C,[2]Hoja1!$H:$H,"",0,1) -> 1118.97 | E24: =_xlfn.XLOOKUP(A:A,[1]Hoja1!$C:$C,[1]Hoja1!$H:$H,"",0,1) -> 896.55 | F24: =_xlfn.XLOOKUP(A:A,TD!A:A,TD!EC:EC,"",0,1) -> 7 | G24: =INT(F24) -> 7 | H24: =D24*$G$5 -> 3356.91 | I24: =E24*$G$5 -> 2689.65 | J24: IG-50001 | K24: =_xlfn.XLOOKUP(J:J,'[3]FILTROS 2'!$A:$A,'[3]FILTROS 2'!$E:$E,"",0,1) -> IMPERGLOSI AGUACERO 5 AÑOS | O24: =_xlfn.XLOOKUP(A:A,[4]TD90D!$A:$A,[4]TD90D!$CW:$CW,"",0,1) -> 4 | P24: =_xlfn.XLOOKUP(A:A,[4]TD90D!$A:$A,[4]TD90D!$CX:$CX,"",0,1) -> 2 | Q24: =_xlfn.XLOOKUP(A:A,[4]TD90D!$A:$A,[4]TD90D!$DA:$DA,"",0,1) -> 0 | R24: =P24/C24 -> 0.15384615 | S24: =_xlfn.XLOOKUP(A:A,'[4]TD90D PZAS'!$A:$A,'[4]TD90D PZAS'!$CW:$CW,"",0,1) -> 63 | T24: =_xlfn.XLOOKUP(A:A,'[4]TD90D PZAS'!$A:$A,'[4]TD90D PZAS'!$CX:$CX,"",0,1) -> 2 | U24: =_xlfn.XLOOKUP(A:A,'[4]TD90D PZAS'!$A:$A,'[4]TD90D PZAS'!$DA:$DA,"",0,1) -> 0
A25: VG-50011 | B25: =_xlfn.XLOOKUP(A:A,[1]Hoja1!$C:$C,[1]Hoja1!$D:$D,"",0,1) -> VINILICA GLOSI BLANCO ULTRA | C25: 13 | D25: =_xlfn.XLOOKUP(A:A,[2]Hoja1!$C:$C,[2]Hoja1!$H:$H,"",0,1) -> 1213.79 | E25: =_xlfn.XLOOKUP(A:A,[1]Hoja1!$C:$C,[1]Hoja1!$H:$H,"",0,1) -> 909.48 | F25: =_xlfn.XLOOKUP(A:A,TD!A:A,TD!EC:EC,"",0,1) -> 1.8461538 | G25: =INT(F25) -> 1 | H25: =D25*$G$5 -> 3641.37 | I25: =E25*$G$5 -> 2728.44 | J25: VG-50011 | K25: =_xlfn.XLOOKUP(J:J,'[3]FILTROS 2'!$A:$A,'[3]FILTROS 2'!$E:$E,"",0,1) -> VINILICA - GLOSI 3 AÑOS | O25: =_xlfn.XLOOKUP(A:A,[4]TD90D!$A:$A,[4]TD90D!$CW:$CW,"",0,1) -> 10 | P25: =_xlfn.XLOOKUP(A:A,[4]TD90D!$A:$A,[4]TD90D!$CX:$CX,"",0,1) -> 5 | Q25: =_xlfn.XLOOKUP(A:A,[4]TD90D!$A:$A,[4]TD90D!$DA:$DA,"",0,1) -> 0 | R25: =P25/C25 -> 0.38461538 | S25: =_xlfn.XLOOKUP(A:A,'[4]TD90D PZAS'!$A:$A,'[4]TD90D PZAS'!$CW:$CW,"",0,1) -> 36 | T25: =_xlfn.XLOOKUP(A:A,'[4]TD90D PZAS'!$A:$A,'[4]TD90D PZAS'!$CX:$CX,"",0,1) -> 5 | U25: =_xlfn.XLOOKUP(A:A,'[4]TD90D PZAS'!$A:$A,'[4]TD90D PZAS'!$DA:$DA,"",0,1) -> 0
A26: IG-30003 | B26: =_xlfn.XLOOKUP(A:A,[1]Hoja1!$C:$C,[1]Hoja1!$D:$D,"",0,1) -> IMPERGLOSI AGUACERO BLANCO 3A | C26: 12 | D26: =_xlfn.XLOOKUP(A:A,[2]Hoja1!$C:$C,[2]Hoja1!$H:$H,"",0,1) -> 225 | E26: =_xlfn.XLOOKUP(A:A,[1]Hoja1!$C:$C,[1]Hoja1!$H:$H,"",0,1) -> 179.31 | F26: =_xlfn.XLOOKUP(A:A,TD!A:A,TD!EC:EC,"",0,1) -> 2.75 | G26: =INT(F26) -> 2 | H26: =D26*$G$5 -> 675 | I26: =E26*$G$5 -> 537.93 | J26: IG-30003 | K26: =_xlfn.XLOOKUP(J:J,'[3]FILTROS 2'!$A:$A,'[3]FILTROS 2'!$E:$E,"",0,1) -> IMPERGLOSI AGUACERO 3 AÑOS | O26: =_xlfn.XLOOKUP(A:A,[4]TD90D!$A:$A,[4]TD90D!$CW:$CW,"",0,1) -> 2 | P26: =_xlfn.XLOOKUP(A:A,[4]TD90D!$A:$A,[4]TD90D!$CX:$CX,"",0,1) -> 1 | Q26: =_xlfn.XLOOKUP(A:A,[4]TD90D!$A:$A,[4]TD90D!$DA:$DA,"",0,1) -> 0 | R26: =P26/C26 -> 0.083333333 | S26: =_xlfn.XLOOKUP(A:A,'[4]TD90D PZAS'!$A:$A,'[4]TD90D PZAS'!$CW:$CW,"",0,1) -> 0 | T26: =_xlfn.XLOOKUP(A:A,'[4]TD90D PZAS'!$A:$A,'[4]TD90D PZAS'!$CX:$CX,"",0,1) -> 0 | U26: =_xlfn.XLOOKUP(A:A,'[4]TD90D PZAS'!$A:$A,'[4]TD90D PZAS'!$DA:$DA,"",0,1) -> 0
A27: 2345 | B27: =_xlfn.XLOOKUP(A:A,[1]Hoja1!$C:$C,[1]Hoja1!$D:$D,"",0,1) -> AEROSOL ROJO | C27: 11 | D27: =_xlfn.XLOOKUP(A:A,[2]Hoja1!$C:$C,[2]Hoja1!$H:$H,"",0,1) -> 55.17 | E27: =_xlfn.XLOOKUP(A:A,[1]Hoja1!$C:$C,[1]Hoja1!$H:$H,"",0,1) -> 41.38 | F27: =_xlfn.XLOOKUP(A:A,TD!A:A,TD!EC:EC,"",0,1) -> 4.9090909 | G27: =INT(F27) -> 4 | H27: =D27*$G$5 -> 165.51 | I27: =E27*$G$5 -> 124.14 | J27: 2345 | K27: =_xlfn.XLOOKUP(J:J,'[3]FILTROS 2'!$A:$A,'[3]FILTROS 2'!$E:$E,"",0,1) -> AEROSOLES PRISA | O27: =_xlfn.XLOOKUP(A:A,[4]TD90D!$A:$A,[4]TD90D!$CW:$CW,"",0,1) -> 16 | P27: =_xlfn.XLOOKUP(A:A,[4]TD90D!$A:$A,[4]TD90D!$CX:$CX,"",0,1) -> 6 | Q27: =_xlfn.XLOOKUP(A:A,[4]TD90D!$A:$A,[4]TD90D!$DA:$DA,"",0,1) -> 0 | R27: =P27/C27 -> 0.54545455 | S27: =_xlfn.XLOOKUP(A:A,'[4]TD90D PZAS'!$A:$A,'[4]TD90D PZAS'!$CW:$CW,"",0,1) -> 61 | T27: =_xlfn.XLOOKUP(A:A,'[4]TD90D PZAS'!$A:$A,'[4]TD90D PZAS'!$CX:$CX,"",0,1) -> 4 | U27: =_xlfn.XLOOKUP(A:A,'[4]TD90D PZAS'!$A:$A,'[4]TD90D PZAS'!$DA:$DA,"",0,1) -> 0
A28: SRG-10003 | B28: =_xlfn.XLOOKUP(A:A,[1]Hoja1!$C:$C,[1]Hoja1!$D:$D,"",0,1) -> ESMALTE GLOSI SR BLANCO | C28: 11 | D28: =_xlfn.XLOOKUP(A:A,[2]Hoja1!$C:$C,[2]Hoja1!$H:$H,"",0,1) -> 730.17 | E28: =_xlfn.XLOOKUP(A:A,[1]Hoja1!$C:$C,[1]Hoja1!$H:$H,"",0,1) -> 584.48 | F28: =_xlfn.XLOOKUP(A:A,TD!A:A,TD!EC:EC,"",0,1) -> 1.7272727 | G28: =INT(F28) -> 1 | H28: =D28*$G$5 -> 2190.51 | I28: =E28*$G$5 -> 1753.44 | J28: SRG-10003 | K28: =_xlfn.XLOOKUP(J:J,'[3]FILTROS 2'!$A:$A,'[3]FILTROS 2'!$E:$E,"",0,1) -> ESMALTE - GLOSI SECADO RAPIDO | O28: =_xlfn.XLOOKUP(A:A,[4]TD90D!$A:$A,[4]TD90D!$CW:$CW,"",0,1) -> 8 | P28: =_xlfn.XLOOKUP(A:A,[4]TD90D!$A:$A,[4]TD90D!$CX:$CX,"",0,1) -> 3 | Q28: =_xlfn.XLOOKUP(A:A,[4]TD90D!$A:$A,[4]TD90D!$DA:$DA,"",0,1) -> 0 | R28: =P28/C28 -> 0.27272727 | S28: =_xlfn.XLOOKUP(A:A,'[4]TD90D PZAS'!$A:$A,'[4]TD90D PZAS'!$CW:$CW,"",0,1) -> 19 | T28: =_xlfn.XLOOKUP(A:A,'[4]TD90D PZAS'!$A:$A,'[4]TD90D PZAS'!$CX:$CX,"",0,1) -> 3 | U28: =_xlfn.XLOOKUP(A:A,'[4]TD90D PZAS'!$A:$A,'[4]TD90D PZAS'!$DA:$DA,"",0,1) -> 0
A29: PRG-10934 | B29: =_xlfn.XLOOKUP(A:A,[1]Hoja1!$C:$C,[1]Hoja1!$D:$D,"",0,1) -> PRIMARIO GLOSI ESTRUCTURAS GRIS | C29: 11 | D29: =_xlfn.XLOOKUP(A:A,[2]Hoja1!$C:$C,[2]Hoja1!$H:$H,"",0,1) -> 138.79 | E29: =_xlfn.XLOOKUP(A:A,[1]Hoja1!$C:$C,[1]Hoja1!$H:$H,"",0,1) -> 105.17 | F29: =_xlfn.XLOOKUP(A:A,TD!A:A,TD!EC:EC,"",0,1) -> 3 | G29: =INT(F29) -> 3 | H29: =D29*$G$5 -> 416.37 | I29: =E29*$G$5 -> 315.51 | J29: PRG-10934 | K29: =_xlfn.XLOOKUP(J:J,'[3]FILTROS 2'!$A:$A,'[3]FILTROS 2'!$E:$E,"",0,1) -> ESMALTE - ESTRUCTURAS GLOSI | O29: =_xlfn.XLOOKUP(A:A,[4]TD90D!$A:$A,[4]TD90D!$CW:$CW,"",0,1) -> 2 | P29: =_xlfn.XLOOKUP(A:A,[4]TD90D!$A:$A,[4]TD90D!$CX:$CX,"",0,1) -> 1 | Q29: =_xlfn.XLOOKUP(A:A,[4]TD90D!$A:$A,[4]TD90D!$DA:$DA,"",0,1) -> 0 | R29: =P29/C29 -> 0.090909091 | S29: =_xlfn.XLOOKUP(A:A,'[4]TD90D PZAS'!$A:$A,'[4]TD90D PZAS'!$CW:$CW,"",0,1) -> 3 | T29: =_xlfn.XLOOKUP(A:A,'[4]TD90D PZAS'!$A:$A,'[4]TD90D PZAS'!$CX:$CX,"",0,1) -> 1 | U29: =_xlfn.XLOOKUP(A:A,'[4]TD90D PZAS'!$A:$A,'[4]TD90D PZAS'!$DA:$DA,"",0,1) -> 0
A30: 2397 | B30: =_xlfn.XLOOKUP(A:A,[1]Hoja1!$C:$C,[1]Hoja1!$D:$D,"",0,1) -> AEROSOL NEGRO SEMI BRILLANTE | C30: 11 | D30: =_xlfn.XLOOKUP(A:A,[2]Hoja1!$C:$C,[2]Hoja1!$H:$H,"",0,1) -> 55.17 | E30: =_xlfn.XLOOKUP(A:A,[1]Hoja1!$C:$C,[1]Hoja1!$H:$H,"",0,1) -> 41.38 | F30: =_xlfn.XLOOKUP(A:A,TD!A:A,TD!EC:EC,"",0,1) -> 5.4545455 | G30: =INT(F30) -> 5 | H30: =D30*$G$5 -> 165.51 | I30: =E30*$G$5 -> 124.14 | J30: 2397 | K30: =_xlfn.XLOOKUP(J:J,'[3]FILTROS 2'!$A:$A,'[3]FILTROS 2'!$E:$E,"",0,1) -> AEROSOLES PRISA | O30: =_xlfn.XLOOKUP(A:A,[4]TD90D!$A:$A,[4]TD90D!$CW:$CW,"",0,1) -> 11 | P30: =_xlfn.XLOOKUP(A:A,[4]TD90D!$A:$A,[4]TD90D!$CX:$CX,"",0,1) -> 5 | Q30: =_xlfn.XLOOKUP(A:A,[4]TD90D!$A:$A,[4]TD90D!$DA:$DA,"",0,1) -> 0 | R30: =P30/C30 -> 0.45454545 | S30: =_xlfn.XLOOKUP(A:A,'[4]TD90D PZAS'!$A:$A,'[4]TD90D PZAS'!$CW:$CW,"",0,1) -> 97 | T30: =_xlfn.XLOOKUP(A:A,'[4]TD90D PZAS'!$A:$A,'[4]TD90D PZAS'!$CX:$CX,"",0,1) -> 4 | U30: =_xlfn.XLOOKUP(A:A,'[4]TD90D PZAS'!$A:$A,'[4]TD90D PZAS'!$DA:$DA,"",0,1) -> 0
A31: 2451 | B31: =_xlfn.XLOOKUP(A:A,[1]Hoja1!$C:$C,[1]Hoja1!$D:$D,"",0,1) -> AEROSOL SUPER ORO | C31: 10 | D31: =_xlfn.XLOOKUP(A:A,[2]Hoja1!$C:$C,[2]Hoja1!$H:$H,"",0,1) -> 73.28 | E31: =_xlfn.XLOOKUP(A:A,[1]Hoja1!$C:$C,[1]Hoja1!$H:$H,"",0,1) -> 55.17 | F31: =_xlfn.XLOOKUP(A:A,TD!A:A,TD!EC:EC,"",0,1) -> 5.5 | G31: =INT(F31) -> 5 | H31: =D31*$G$5 -> 219.84 | I31: =E31*$G$5 -> 165.51 | J31: 2451 | K31: =_xlfn.XLOOKUP(J:J,'[3]FILTROS 2'!$A:$A,'[3]FILTROS 2'!$E:$E,"",0,1) -> AEROSOLES PRISA | O31: =_xlfn.XLOOKUP(A:A,[4]TD90D!$A:$A,[4]TD90D!$CW:$CW,"",0,1) -> 6 | P31: =_xlfn.XLOOKUP(A:A,[4]TD90D!$A:$A,[4]TD90D!$CX:$CX,"",0,1) -> 2 | Q31: =_xlfn.XLOOKUP(A:A,[4]TD90D!$A:$A,[4]TD90D!$DA:$DA,"",0,1) -> 0 | R31: =P31/C31 -> 0.2 | S31: =_xlfn.XLOOKUP(A:A,'[4]TD90D PZAS'!$A:$A,'[4]TD90D PZAS'!$CW:$CW,"",0,1) -> 12 | T31: =_xlfn.XLOOKUP(A:A,'[4]TD90D PZAS'!$A:$A,'[4]TD90D PZAS'!$CX:$CX,"",0,1) -> 1 | U31: =_xlfn.XLOOKUP(A:A,'[4]TD90D PZAS'!$A:$A,'[4]TD90D PZAS'!$DA:$DA,"",0,1) -> 0
A32: 28014 | B32: =_xlfn.XLOOKUP(A:A,[1]Hoja1!$C:$C,[1]Hoja1!$D:$D,"",0,1) -> BRILLON BLANCO MATE | C32: 10 | D32: =_xlfn.XLOOKUP(A:A,[2]Hoja1!$C:$C,[2]Hoja1!$H:$H,"",0,1) -> 150.86 | E32: =_xlfn.XLOOKUP(A:A,[1]Hoja1!$C:$C,[1]Hoja1!$H:$H,"",0,1) -> 112.93 | F32: =_xlfn.XLOOKUP(A:A,TD!A:A,TD!EC:EC,"",0,1) -> 3.7 | G32: =INT(F32) -> 3 | H32: =D32*$G$5 -> 452.58 | I32: =E32*$G$5 -> 338.79 | J32: 28014 | K32: =_xlfn.XLOOKUP(J:J,'[3]FILTROS 2'!$A:$A,'[3]FILTROS 2'!$E:$E,"",0,1) -> ESMALTE - BRILLON | O32: =_xlfn.XLOOKUP(A:A,[4]TD90D!$A:$A,[4]TD90D!$CW:$CW,"",0,1) -> 8 | P32: =_xlfn.XLOOKUP(A:A,[4]TD90D!$A:$A,[4]TD90D!$CX:$CX,"",0,1) -> 4 | Q32: =_xlfn.XLOOKUP(A:A,[4]TD90D!$A:$A,[4]TD90D!$DA:$DA,"",0,1) -> 0 | R32: =P32/C32 -> 0.4 | S32: =_xlfn.XLOOKUP(A:A,'[4]TD90D PZAS'!$A:$A,'[4]TD90D PZAS'!$CW:$CW,"",0,1) -> 28 | T32: =_xlfn.XLOOKUP(A:A,'[4]TD90D PZAS'!$A:$A,'[4]TD90D PZAS'!$CX:$CX,"",0,1) -> 3 | U32: =_xlfn.XLOOKUP(A:A,'[4]TD90D PZAS'!$A:$A,'[4]TD90D PZAS'!$DA:$DA,"",0,1) -> 0
A33: VG-50014 | B33: =_xlfn.XLOOKUP(A:A,[1]Hoja1!$C:$C,[1]Hoja1!$D:$D,"",0,1) -> VINILICA GLOSI BLANCO ULTRA | C33: 10 | D33: =_xlfn.XLOOKUP(A:A,[2]Hoja1!$C:$C,[2]Hoja1!$H:$H,"",0,1) -> 107.76 | E33: =_xlfn.XLOOKUP(A:A,[1]Hoja1!$C:$C,[1]Hoja1!$H:$H,"",0,1) -> 78.45 | F33: =_xlfn.XLOOKUP(A:A,TD!A:A,TD!EC:EC,"",0,1) -> 3.9 | G33: =INT(F33) -> 3 | H33: =D33*$G$5 -> 323.28 | I33: =E33*$G$5 -> 235.35 | J33: VG-50014 | K33: =_xlfn.XLOOKUP(J:J,'[3]FILTROS 2'!$A:$A,'[3]FILTROS 2'!$E:$E,"",0,1) -> VINILICA - GLOSI 3 AÑOS | O33: =_xlfn.XLOOKUP(A:A,[4]TD90D!$A:$A,[4]TD90D!$CW:$CW,"",0,1) -> 9 | P33: =_xlfn.XLOOKUP(A:A,[4]TD90D!$A:$A,[4]TD90D!$CX:$CX,"",0,1) -> 4 | Q33: =_xlfn.XLOOKUP(A:A,[4]TD90D!$A:$A,[4]TD90D!$DA:$DA,"",0,1) -> 0 | R33: =P33/C33 -> 0.4 | S33: =_xlfn.XLOOKUP(A:A,'[4]TD90D PZAS'!$A:$A,'[4]TD90D PZAS'!$CW:$CW,"",0,1) -> 45 | T33: =_xlfn.XLOOKUP(A:A,'[4]TD90D PZAS'!$A:$A,'[4]TD90D PZAS'!$CX:$CX,"",0,1) -> 4 | U33: =_xlfn.XLOOKUP(A:A,'[4]TD90D PZAS'!$A:$A,'[4]TD90D PZAS'!$DA:$DA,"",0,1) -> 0
A34: 28916 | B34: =_xlfn.XLOOKUP(A:A,[1]Hoja1!$C:$C,[1]Hoja1!$D:$D,"",0,1) -> BRILLON DORADO | C34: 9 | D34: =_xlfn.XLOOKUP(A:A,[2]Hoja1!$C:$C,[2]Hoja1!$H:$H,"",0,1) -> 58.62 | E34: =_xlfn.XLOOKUP(A:A,[1]Hoja1!$C:$C,[1]Hoja1!$H:$H,"",0,1) -> 43.97 | F34: =_xlfn.XLOOKUP(A:A,TD!A:A,TD!EC:EC,"",0,1) -> 4.1111111 | G34: =INT(F34) -> 4 | H34: =D34*$G$5 -> 175.86 | I34: =E34*$G$5 -> 131.91 | J34: 28916 | K34: =_xlfn.XLOOKUP(J:J,'[3]FILTROS 2'!$A:$A,'[3]FILTROS 2'!$E:$E,"",0,1) -> ESMALTE - BRILLON | O34: =_xlfn.XLOOKUP(A:A,[4]TD90D!$A:$A,[4]TD90D!$CW:$CW,"",0,1) -> 5 | P34: =_xlfn.XLOOKUP(A:A,[4]TD90D!$A:$A,[4]TD90D!$CX:$CX,"",0,1) -> 2 | Q34: =_xlfn.XLOOKUP(A:A,[4]TD90D!$A:$A,[4]TD90D!$DA:$DA,"",0,1) -> 0 | R34: =P34/C34 -> 0.22222222 | S34: =_xlfn.XLOOKUP(A:A,'[4]TD90D PZAS'!$A:$A,'[4]TD90D PZAS'!$CW:$CW,"",0,1) -> 18 | T34: =_xlfn.XLOOKUP(A:A,'[4]TD90D PZAS'!$A:$A,'[4]TD90D PZAS'!$CX:$CX,"",0,1) -> 2 | U34: =_xlfn.XLOOKUP(A:A,'[4]TD90D PZAS'!$A:$A,'[4]TD90D PZAS'!$DA:$DA,"",0,1) -> 0
A35: 28586 | B35: =_xlfn.XLOOKUP(A:A,[1]Hoja1!$C:$C,[1]Hoja1!$D:$D,"",0,1) -> BRILLON CACAO | C35: 9 | D35: =_xlfn.XLOOKUP(A:A,[2]Hoja1!$C:$C,[2]Hoja1!$H:$H,"",0,1) -> 58.62 | E35: =_xlfn.XLOOKUP(A:A,[1]Hoja1!$C:$C,[1]Hoja1!$H:$H,"",0,1) -> 43.97 | F35: =_xlfn.XLOOKUP(A:A,TD!A:A,TD!EC:EC,"",0,1) -> 5.3333333 | G35: =INT(F35) -> 5 | H35: =D35*$G$5 -> 175.86 | I35: =E35*$G$5 -> 131.91 | J35: 28586 | K35: =_xlfn.XLOOKUP(J:J,'[3]FILTROS 2'!$A:$A,'[3]FILTROS 2'!$E:$E,"",0,1) -> ESMALTE - BRILLON | O35: =_xlfn.XLOOKUP(A:A,[4]TD90D!$A:$A,[4]TD90D!$CW:$CW,"",0,1) -> 6 | P35: =_xlfn.XLOOKUP(A:A,[4]TD90D!$A:$A,[4]TD90D!$CX:$CX,"",0,1) -> 2 | Q35: =_xlfn.XLOOKUP(A:A,[4]TD90D!$A:$A,[4]TD90D!$DA:$DA,"",0,1) -> 0 | R35: =P35/C35 -> 0.22222222 | S35: =_xlfn.XLOOKUP(A:A,'[4]TD90D PZAS'!$A:$A,'[4]TD90D PZAS'!$CW:$CW,"",0,1) -> 12 | T35: =_xlfn.XLOOKUP(A:A,'[4]TD90D PZAS'!$A:$A,'[4]TD90D PZAS'!$CX:$CX,"",0,1) -> 2 | U35: =_xlfn.XLOOKUP(A:A,'[4]TD90D PZAS'!$A:$A,'[4]TD90D PZAS'!$DA:$DA,"",0,1) -> 0
A36: VG-30011 | B36: =_xlfn.XLOOKUP(A:A,[1]Hoja1!$C:$C,[1]Hoja1!$D:$D,"",0,1) -> VINILICA GLOSI BLANCO BASIC | C36: 9 | D36: =_xlfn.XLOOKUP(A:A,[2]Hoja1!$C:$C,[2]Hoja1!$H:$H,"",0,1) -> 874.14 | E36: =_xlfn.XLOOKUP(A:A,[1]Hoja1!$C:$C,[1]Hoja1!$H:$H,"",0,1) -> 656.03 | F36: =_xlfn.XLOOKUP(A:A,TD!A:A,TD!EC:EC,"",0,1) -> 2.2222222 | G36: =INT(F36) -> 2 | H36: =D36*$G$5 -> 2622.42 | I36: =E36*$G$5 -> 1968.09 | J36: VG-30011 | K36: =_xlfn.XLOOKUP(J:J,'[3]FILTROS 2'!$A:$A,'[3]FILTROS 2'!$E:$E,"",0,1) -> VINILICA - GLOSI 3 AÑOS | O36: =_xlfn.XLOOKUP(A:A,[4]TD90D!$A:$A,[4]TD90D!$CW:$CW,"",0,1) -> 10 | P36: =_xlfn.XLOOKUP(A:A,[4]TD90D!$A:$A,[4]TD90D!$CX:$CX,"",0,1) -> 5 | Q36: =_xlfn.XLOOKUP(A:A,[4]TD90D!$A:$A,[4]TD90D!$DA:$DA,"",0,1) -> 0 | R36: =P36/C36 -> 0.55555556 | S36: =_xlfn.XLOOKUP(A:A,'[4]TD90D PZAS'!$A:$A,'[4]TD90D PZAS'!$CW:$CW,"",0,1) -> 24 | T36: =_xlfn.XLOOKUP(A:A,'[4]TD90D PZAS'!$A:$A,'[4]TD90D PZAS'!$CX:$CX,"",0,1) -> 5 | U36: =_xlfn.XLOOKUP(A:A,'[4]TD90D PZAS'!$A:$A,'[4]TD90D PZAS'!$DA:$DA,"",0,1) -> 0
A37: 28806 | B37: =_xlfn.XLOOKUP(A:A,[1]Hoja1!$C:$C,[1]Hoja1!$D:$D,"",0,1) -> BARNIZ ALQ. TRANSP. NATURAL | C37: 9 | D37: =_xlfn.XLOOKUP(A:A,[2]Hoja1!$C:$C,[2]Hoja1!$H:$H,"",0,1) -> 78.45 | E37: =_xlfn.XLOOKUP(A:A,[1]Hoja1!$C:$C,[1]Hoja1!$H:$H,"",0,1) -> 56.03 | F37: =_xlfn.XLOOKUP(A:A,TD!A:A,TD!EC:EC,"",0,1) -> 4.6666667 | G37: =INT(F37) -> 4 | H37: =D37*$G$5 -> 235.35 | I37: =E37*$G$5 -> 168.09 | J37: 28806 | K37: =_xlfn.XLOOKUP(J:J,'[3]FILTROS 2'!$A:$A,'[3]FILTROS 2'!$E:$E,"",0,1) -> BARNIZ ALQUIDALICO SIGLO | O37: =_xlfn.XLOOKUP(A:A,[4]TD90D!$A:$A,[4]TD90D!$CW:$CW,"",0,1) -> 8 | P37: =_xlfn.XLOOKUP(A:A,[4]TD90D!$A:$A,[4]TD90D!$CX:$CX,"",0,1) -> 3 | Q37: =_xlfn.XLOOKUP(A:A,[4]TD90D!$A:$A,[4]TD90D!$DA:$DA,"",0,1) -> 0 | R37: =P37/C37 -> 0.33333333 | S37: =_xlfn.XLOOKUP(A:A,'[4]TD90D PZAS'!$A:$A,'[4]TD90D PZAS'!$CW:$CW,"",0,1) -> 36 | T37: =_xlfn.XLOOKUP(A:A,'[4]TD90D PZAS'!$A:$A,'[4]TD90D PZAS'!$CX:$CX,"",0,1) -> 3 | U37: =_xlfn.XLOOKUP(A:A,'[4]TD90D PZAS'!$A:$A,'[4]TD90D PZAS'!$DA:$DA,"",0,1) -> 0
A38: 29012 | B38: =_xlfn.XLOOKUP(A:A,[1]Hoja1!$C:$C,[1]Hoja1!$D:$D,"",0,1) -> RELLENADOR AUTOMOTRIZ C/CATAL. ROJO | C38: 9 | D38: =_xlfn.XLOOKUP(A:A,[2]Hoja1!$C:$C,[2]Hoja1!$H:$H,"",0,1) -> 408.62 | E38: =_xlfn.XLOOKUP(A:A,[1]Hoja1!$C:$C,[1]Hoja1!$H:$H,"",0,1) -> 305.17 | F38: =_xlfn.XLOOKUP(A:A,TD!A:A,TD!EC:EC,"",0,1) -> 6.4444444 | G38: =INT(F38) -> 6 | H38: =D38*$G$5 -> 1225.86 | I38: =E38*$G$5 -> 915.51 | J38: 29012 | K38: =_xlfn.XLOOKUP(J:J,'[3]FILTROS 2'!$A:$A,'[3]FILTROS 2'!$E:$E,"",0,1) -> PASTA RELLENADORA | O38: =_xlfn.XLOOKUP(A:A,[4]TD90D!$A:$A,[4]TD90D!$CW:$CW,"",0,1) -> 11 | P38: =_xlfn.XLOOKUP(A:A,[4]TD90D!$A:$A,[4]TD90D!$CX:$CX,"",0,1) -> 3 | Q38: =_xlfn.XLOOKUP(A:A,[4]TD90D!$A:$A,[4]TD90D!$DA:$DA,"",0,1) -> 0 | R38: =P38/C38 -> 0.33333333 | S38: =_xlfn.XLOOKUP(A:A,'[4]TD90D PZAS'!$A:$A,'[4]TD90D PZAS'!$CW:$CW,"",0,1) -> 100 | T38: =_xlfn.XLOOKUP(A:A,'[4]TD90D PZAS'!$A:$A,'[4]TD90D PZAS'!$CX:$CX,"",0,1) -> 3 | U38: =_xlfn.XLOOKUP(A:A,'[4]TD90D PZAS'!$A:$A,'[4]TD90D PZAS'!$DA:$DA,"",0,1) -> 0
A39: BAG-10886 | B39: =_xlfn.XLOOKUP(A:A,[1]Hoja1!$C:$C,[1]Hoja1!$D:$D,"",0,1) -> BARNIZ GLOSI ALQUI CAOBA | C39: 9 | D39: =_xlfn.XLOOKUP(A:A,[2]Hoja1!$C:$C,[2]Hoja1!$H:$H,"",0,1) -> 68.97 | E39: =_xlfn.XLOOKUP(A:A,[1]Hoja1!$C:$C,[1]Hoja1!$H:$H,"",0,1) -> 52.59 | F39: =_xlfn.XLOOKUP(A:A,TD!A:A,TD!EC:EC,"",0,1) -> 3.3333333 | G39: =INT(F39) -> 3 | H39: =D39*$G$5 -> 206.91 | I39: =E39*$G$5 -> 157.77 | J39: BAG-10886 | K39: =_xlfn.XLOOKUP(J:J,'[3]FILTROS 2'!$A:$A,'[3]FILTROS 2'!$E:$E,"",0,1) -> BARNIZ ALQUIDALICO GLOSI 3-1 | O39: =_xlfn.XLOOKUP(A:A,[4]TD90D!$A:$A,[4]TD90D!$CW:$CW,"",0,1) -> 4 | P39: =_xlfn.XLOOKUP(A:A,[4]TD90D!$A:$A,[4]TD90D!$CX:$CX,"",0,1) -> 1 | Q39: =_xlfn.XLOOKUP(A:A,[4]TD90D!$A:$A,[4]TD90D!$DA:$DA,"",0,1) -> 0 | R39: =P39/C39 -> 0.11111111 | S39: =_xlfn.XLOOKUP(A:A,'[4]TD90D PZAS'!$A:$A,'[4]TD90D PZAS'!$CW:$CW,"",0,1) -> 6 | T39: =_xlfn.XLOOKUP(A:A,'[4]TD90D PZAS'!$A:$A,'[4]TD90D PZAS'!$CX:$CX,"",0,1) -> 1 | U39: =_xlfn.XLOOKUP(A:A,'[4]TD90D PZAS'!$A:$A,'[4]TD90D PZAS'!$DA:$DA,"",0,1) -> 0
A40: 2393 | B40: =_xlfn.XLOOKUP(A:A,[1]Hoja1!$C:$C,[1]Hoja1!$D:$D,"",0,1) -> AEROSOL GRIS CLARO | C40: 8 | D40: =_xlfn.XLOOKUP(A:A,[2]Hoja1!$C:$C,[2]Hoja1!$H:$H,"",0,1) -> 55.17 | E40: =_xlfn.XLOOKUP(A:A,[1]Hoja1!$C:$C,[1]Hoja1!$H:$H,"",0,1) -> 41.38 | F40: =_xlfn.XLOOKUP(A:A,TD!A:A,TD!EC:EC,"",0,1) -> 5.25 | G40: =INT(F40) -> 5 | H40: =D40*$G$5 -> 165.51 | I40: =E40*$G$5 -> 124.14 | J40: 2393 | K40: =_xlfn.XLOOKUP(J:J,'[3]FILTROS 2'!$A:$A,'[3]FILTROS 2'!$E:$E,"",0,1) -> AEROSOLES PRISA | O40: =_xlfn.XLOOKUP(A:A,[4]TD90D!$A:$A,[4]TD90D!$CW:$CW,"",0,1) -> 6 | P40: =_xlfn.XLOOKUP(A:A,[4]TD90D!$A:$A,[4]TD90D!$CX:$CX,"",0,1) -> 3 | Q40: =_xlfn.XLOOKUP(A:A,[4]TD90D!$A:$A,[4]TD90D!$DA:$DA,"",0,1) -> 0 | R40: =P40/C40 -> 0.375 | S40: =_xlfn.XLOOKUP(A:A,'[4]TD90D PZAS'!$A:$A,'[4]TD90D PZAS'!$CW:$CW,"",0,1) -> 36 | T40: =_xlfn.XLOOKUP(A:A,'[4]TD90D PZAS'!$A:$A,'[4]TD90D PZAS'!$CX:$CX,"",0,1) -> 2 | U40: =_xlfn.XLOOKUP(A:A,'[4]TD90D PZAS'!$A:$A,'[4]TD90D PZAS'!$DA:$DA,"",0,1) -> 0
A41: VG-30013 | B41: =_xlfn.XLOOKUP(A:A,[1]Hoja1!$C:$C,[1]Hoja1!$D:$D,"",0,1) -> VINILICA GLOSI BLANCO BASIC | C41: 8 | D41: =_xlfn.XLOOKUP(A:A,[2]Hoja1!$C:$C,[2]Hoja1!$H:$H,"",0,1) -> 219.83 | E41: =_xlfn.XLOOKUP(A:A,[1]Hoja1!$C:$C,[1]Hoja1!$H:$H,"",0,1) -> 163.79 | F41: =_xlfn.XLOOKUP(A:A,TD!A:A,TD!EC:EC,"",0,1) -> 3.5 | G41: =INT(F41) -> 3 | H41: =D41*$G$5 -> 659.49 | I41: =E41*$G$5 -> 491.37 | J41: VG-30013 | K41: =_xlfn.XLOOKUP(J:J,'[3]FILTROS 2'!$A:$A,'[3]FILTROS 2'!$E:$E,"",0,1) -> VINILICA - GLOSI BASIC | O41: =_xlfn.XLOOKUP(A:A,[4]TD90D!$A:$A,[4]TD90D!$CW:$CW,"",0,1) -> 9 | P41: =_xlfn.XLOOKUP(A:A,[4]TD90D!$A:$A,[4]TD90D!$CX:$CX,"",0,1) -> 4 | Q41: =_xlfn.XLOOKUP(A:A,[4]TD90D!$A:$A,[4]TD90D!$DA:$DA,"",0,1) -> 0 | R41: =P41/C41 -> 0.5 | S41: =_xlfn.XLOOKUP(A:A,'[4]TD90D PZAS'!$A:$A,'[4]TD90D PZAS'!$CW:$CW,"",0,1) -> 38 | T41: =_xlfn.XLOOKUP(A:A,'[4]TD90D PZAS'!$A:$A,'[4]TD90D PZAS'!$CX:$CX,"",0,1) -> 4 | U41: =_xlfn.XLOOKUP(A:A,'[4]TD90D PZAS'!$A:$A,'[4]TD90D PZAS'!$DA:$DA,"",0,1) -> 0
A42: BAG-10896 | B42: =_xlfn.XLOOKUP(A:A,[1]Hoja1!$C:$C,[1]Hoja1!$D:$D,"",0,1) -> BARNIZ GLOSI ALQUI NOGAL | C42: 8 | D42: =_xlfn.XLOOKUP(A:A,[2]Hoja1!$C:$C,[2]Hoja1!$H:$H,"",0,1) -> 68.97 | E42: =_xlfn.XLOOKUP(A:A,[1]Hoja1!$C:$C,[1]Hoja1!$H:$H,"",0,1) -> 52.59 | F42: =_xlfn.XLOOKUP(A:A,TD!A:A,TD!EC:EC,"",0,1) -> 2.25 | G42: =INT(F42) -> 2 | H42: =D42*$G$5 -> 206.91 | I42: =E42*$G$5 -> 157.77 | J42: BAG-10896 | K42: =_xlfn.XLOOKUP(J:J,'[3]FILTROS 2'!$A:$A,'[3]FILTROS 2'!$E:$E,"",0,1) -> BARNIZ ALQUIDALICO GLOSI 3-1 | O42: =_xlfn.XLOOKUP(A:A,[4]TD90D!$A:$A,[4]TD90D!$CW:$CW,"",0,1) -> 5 | P42: =_xlfn.XLOOKUP(A:A,[4]TD90D!$A:$A,[4]TD90D!$CX:$CX,"",0,1) -> 2 | Q42: =_xlfn.XLOOKUP(A:A,[4]TD90D!$A:$A,[4]TD90D!$DA:$DA,"",0,1) -> 0 | R42: =P42/C42 -> 0.25 | S42: =_xlfn.XLOOKUP(A:A,'[4]TD90D PZAS'!$A:$A,'[4]TD90D PZAS'!$CW:$CW,"",0,1) -> 12 | T42: =_xlfn.XLOOKUP(A:A,'[4]TD90D PZAS'!$A:$A,'[4]TD90D PZAS'!$CX:$CX,"",0,1) -> 2 | U42: =_xlfn.XLOOKUP(A:A,'[4]TD90D PZAS'!$A:$A,'[4]TD90D PZAS'!$DA:$DA,"",0,1) -> 0
A43: 28934 | B43: =_xlfn.XLOOKUP(A:A,[1]Hoja1!$C:$C,[1]Hoja1!$D:$D,"",0,1) -> BRILLON GRIS | C43: 8 | D43: =_xlfn.XLOOKUP(A:A,[2]Hoja1!$C:$C,[2]Hoja1!$H:$H,"",0,1) -> 150.86 | E43: =_xlfn.XLOOKUP(A:A,[1]Hoja1!$C:$C,[1]Hoja1!$H:$H,"",0,1) -> 112.93 | F43: =_xlfn.XLOOKUP(A:A,TD!A:A,TD!EC:EC,"",0,1) -> 4.875 | G43: =INT(F43) -> 4 | H43: =D43*$G$5 -> 452.58 | I43: =E43*$G$5 -> 338.79 | J43: 28934 | K43: =_xlfn.XLOOKUP(J:J,'[3]FILTROS 2'!$A:$A,'[3]FILTROS 2'!$E:$E,"",0,1) -> ESMALTE - BRILLON | O43: =_xlfn.XLOOKUP(A:A,[4]TD90D!$A:$A,[4]TD90D!$CW:$CW,"",0,1) -> 2 | P43: =_xlfn.XLOOKUP(A:A,[4]TD90D!$A:$A,[4]TD90D!$CX:$CX,"",0,1) -> 1 | Q43: =_xlfn.XLOOKUP(A:A,[4]TD90D!$A:$A,[4]TD90D!$DA:$DA,"",0,1) -> 0 | R43: =P43/C43 -> 0.125 | S43: =_xlfn.XLOOKUP(A:A,'[4]TD90D PZAS'!$A:$A,'[4]TD90D PZAS'!$CW:$CW,"",0,1) -> 12 | T43: =_xlfn.XLOOKUP(A:A,'[4]TD90D PZAS'!$A:$A,'[4]TD90D PZAS'!$CX:$CX,"",0,1) -> 1 | U43: =_xlfn.XLOOKUP(A:A,'[4]TD90D PZAS'!$A:$A,'[4]TD90D PZAS'!$DA:$DA,"",0,1) -> 0
A44: 2301 | B44: =_xlfn.XLOOKUP(A:A,[1]Hoja1!$C:$C,[1]Hoja1!$D:$D,"",0,1) -> AEROSOL BLANCO MATE | C44: 8 | D44: =_xlfn.XLOOKUP(A:A,[2]Hoja1!$C:$C,[2]Hoja1!$H:$H,"",0,1) -> 55.17 | E44: =_xlfn.XLOOKUP(A:A,[1]Hoja1!$C:$C,[1]Hoja1!$H:$H,"",0,1) -> 41.38 | F44: =_xlfn.XLOOKUP(A:A,TD!A:A,TD!EC:EC,"",0,1) -> 5.125 | G44: =INT(F44) -> 5 | H44: =D44*$G$5 -> 165.51 | I44: =E44*$G$5 -> 124.14 | J44: 2301 | K44: =_xlfn.XLOOKUP(J:J,'[3]FILTROS 2'!$A:$A,'[3]FILTROS 2'!$E:$E,"",0,1) -> AEROSOLES PRISA | O44: =_xlfn.XLOOKUP(A:A,[4]TD90D!$A:$A,[4]TD90D!$CW:$CW,"",0,1) -> 5 | P44: =_xlfn.XLOOKUP(A:A,[4]TD90D!$A:$A,[4]TD90D!$CX:$CX,"",0,1) -> 2 | Q44: =_xlfn.XLOOKUP(A:A,[4]TD90D!$A:$A,[4]TD90D!$DA:$DA,"",0,1) -> 0 | R44: =P44/C44 -> 0.25 | S44: =_xlfn.XLOOKUP(A:A,'[4]TD90D PZAS'!$A:$A,'[4]TD90D PZAS'!$CW:$CW,"",0,1) -> 18 | T44: =_xlfn.XLOOKUP(A:A,'[4]TD90D PZAS'!$A:$A,'[4]TD90D PZAS'!$CX:$CX,"",0,1) -> 2 | U44: =_xlfn.XLOOKUP(A:A,'[4]TD90D PZAS'!$A:$A,'[4]TD90D PZAS'!$DA:$DA,"",0,1) -> 0
A45: SRG-10983 | B45: =_xlfn.XLOOKUP(A:A,[1]Hoja1!$C:$C,[1]Hoja1!$D:$D,"",0,1) -> ESMALTE GLOSI SR NEGRO MATE | C45: 8 | D45: =_xlfn.XLOOKUP(A:A,[2]Hoja1!$C:$C,[2]Hoja1!$H:$H,"",0,1) -> 730.17 | E45: =_xlfn.XLOOKUP(A:A,[1]Hoja1!$C:$C,[1]Hoja1!$H:$H,"",0,1) -> 584.48 | F45: =_xlfn.XLOOKUP(A:A,TD!A:A,TD!EC:EC,"",0,1) -> 1.25 | G45: =INT(F45) -> 1 | H45: =D45*$G$5 -> 2190.51 | I45: =E45*$G$5 -> 1753.44 | J45: SRG-10983 | K45: =_xlfn.XLOOKUP(J:J,'[3]FILTROS 2'!$A:$A,'[3]FILTROS 2'!$E:$E,"",0,1) -> ESMALTE - GLOSI SECADO RAPIDO | O45: =_xlfn.XLOOKUP(A:A,[4]TD90D!$A:$A,[4]TD90D!$CW:$CW,"",0,1) -> 11 | P45: =_xlfn.XLOOKUP(A:A,[4]TD90D!$A:$A,[4]TD90D!$CX:$CX,"",0,1) -> 2 | Q45: =_xlfn.XLOOKUP(A:A,[4]TD90D!$A:$A,[4]TD90D!$DA:$DA,"",0,1) -> 0 | R45: =P45/C45 -> 0.25 | S45: =_xlfn.XLOOKUP(A:A,'[4]TD90D PZAS'!$A:$A,'[4]TD90D PZAS'!$CW:$CW,"",0,1) -> 48 | T45: =_xlfn.XLOOKUP(A:A,'[4]TD90D PZAS'!$A:$A,'[4]TD90D PZAS'!$CX:$CX,"",0,1) -> 2 | U45: =_xlfn.XLOOKUP(A:A,'[4]TD90D PZAS'!$A:$A,'[4]TD90D PZAS'!$DA:$DA,"",0,1) -> 0
A46: 28584 | B46: =_xlfn.XLOOKUP(A:A,[1]Hoja1!$C:$C,[1]Hoja1!$D:$D,"",0,1) -> BRILLON CACAO | C46: 7 | D46: =_xlfn.XLOOKUP(A:A,[2]Hoja1!$C:$C,[2]Hoja1!$H:$H,"",0,1) -> 150.86 | E46: =_xlfn.XLOOKUP(A:A,[1]Hoja1!$C:$C,[1]Hoja1!$H:$H,"",0,1) -> 112.93 | F46: =_xlfn.XLOOKUP(A:A,TD!A:A,TD!EC:EC,"",0,1) -> 4.2857143 | G46: =INT(F46) -> 4 | H46: =D46*$G$5 -> 452.58 | I46: =E46*$G$5 -> 338.79 | J46: 28584 | K46: =_xlfn.XLOOKUP(J:J,'[3]FILTROS 2'!$A:$A,'[3]FILTROS 2'!$E:$E,"",0,1) -> ESMALTE - BRILLON | O46: =_xlfn.XLOOKUP(A:A,[4]TD90D!$A:$A,[4]TD90D!$CW:$CW,"",0,1) -> 2 | P46: =_xlfn.XLOOKUP(A:A,[4]TD90D!$A:$A,[4]TD90D!$CX:$CX,"",0,1) -> 1 | Q46: =_xlfn.XLOOKUP(A:A,[4]TD90D!$A:$A,[4]TD90D!$DA:$DA,"",0,1) -> 0 | R46: =P46/C46 -> 0.14285714 | S46: =_xlfn.XLOOKUP(A:A,'[4]TD90D PZAS'!$A:$A,'[4]TD90D PZAS'!$CW:$CW,"",0,1) -> 12 | T46: =_xlfn.XLOOKUP(A:A,'[4]TD90D PZAS'!$A:$A,'[4]TD90D PZAS'!$CX:$CX,"",0,1) -> 1 | U46: =_xlfn.XLOOKUP(A:A,'[4]TD90D PZAS'!$A:$A,'[4]TD90D PZAS'!$DA:$DA,"",0,1) -> 0
A47: VG-50001 | B47: =_xlfn.XLOOKUP(A:A,[1]Hoja1!$C:$C,[1]Hoja1!$D:$D,"",0,1) -> VINILICA GLOSI BLANCO 5A | C47: 7 | D47: =_xlfn.XLOOKUP(A:A,[2]Hoja1!$C:$C,[2]Hoja1!$H:$H,"",0,1) -> 1213.79 | E47: =_xlfn.XLOOKUP(A:A,[1]Hoja1!$C:$C,[1]Hoja1!$H:$H,"",0,1) -> 909.48 | F47: =_xlfn.XLOOKUP(A:A,TD!A:A,TD!EC:EC,"",0,1) -> 3.8571429 | G47: =INT(F47) -> 3 | H47: =D47*$G$5 -> 3641.37 | I47: =E47*$G$5 -> 2728.44 | J47: VG-50001 | K47: =_xlfn.XLOOKUP(J:J,'[3]FILTROS 2'!$A:$A,'[3]FILTROS 2'!$E:$E,"",0,1) -> VINILICA - GLOSI 5 AÑOS | O47: =_xlfn.XLOOKUP(A:A,[4]TD90D!$A:$A,[4]TD90D!$CW:$CW,"",0,1) -> 6 | P47: =_xlfn.XLOOKUP(A:A,[4]TD90D!$A:$A,[4]TD90D!$CX:$CX,"",0,1) -> 3 | Q47: =_xlfn.XLOOKUP(A:A,[4]TD90D!$A:$A,[4]TD90D!$DA:$DA,"",0,1) -> 0 | R47: =P47/C47 -> 0.42857143 | S47: =_xlfn.XLOOKUP(A:A,'[4]TD90D PZAS'!$A:$A,'[4]TD90D PZAS'!$CW:$CW,"",0,1) -> 19 | T47: =_xlfn.XLOOKUP(A:A,'[4]TD90D PZAS'!$A:$A,'[4]TD90D PZAS'!$CX:$CX,"",0,1) -> 3 | U47: =_xlfn.XLOOKUP(A:A,'[4]TD90D PZAS'!$A:$A,'[4]TD90D PZAS'!$DA:$DA,"",0,1) -> 0
A48: 28964 | B48: =_xlfn.XLOOKUP(A:A,[1]Hoja1!$C:$C,[1]Hoja1!$D:$D,"",0,1) -> BRILLON NEGRO MATE | C48: 7 | D48: =_xlfn.XLOOKUP(A:A,[2]Hoja1!$C:$C,[2]Hoja1!$H:$H,"",0,1) -> 150.86 | E48: =_xlfn.XLOOKUP(A:A,[1]Hoja1!$C:$C,[1]Hoja1!$H:$H,"",0,1) -> 112.93 | F48: =_xlfn.XLOOKUP(A:A,TD!A:A,TD!EC:EC,"",0,1) -> 3.5714286 | G48: =INT(F48) -> 3 | H48: =D48*$G$5 -> 452.58 | I48: =E48*$G$5 -> 338.79 | J48: 28964 | K48: =_xlfn.XLOOKUP(J:J,'[3]FILTROS 2'!$A:$A,'[3]FILTROS 2'!$E:$E,"",0,1) -> ESMALTE - BRILLON | O48: =_xlfn.XLOOKUP(A:A,[4]TD90D!$A:$A,[4]TD90D!$CW:$CW,"",0,1) -> 6 | P48: =_xlfn.XLOOKUP(A:A,[4]TD90D!$A:$A,[4]TD90D!$CX:$CX,"",0,1) -> 2 | Q48: =_xlfn.XLOOKUP(A:A,[4]TD90D!$A:$A,[4]TD90D!$DA:$DA,"",0,1) -> 0 | R48: =P48/C48 -> 0.28571429 | S48: =_xlfn.XLOOKUP(A:A,'[4]TD90D PZAS'!$A:$A,'[4]TD90D PZAS'!$CW:$CW,"",0,1) -> 19 | T48: =_xlfn.XLOOKUP(A:A,'[4]TD90D PZAS'!$A:$A,'[4]TD90D PZAS'!$CX:$CX,"",0,1) -> 2 | U48: =_xlfn.XLOOKUP(A:A,'[4]TD90D PZAS'!$A:$A,'[4]TD90D PZAS'!$DA:$DA,"",0,1) -> 0
A49: 28003 | B49: =_xlfn.XLOOKUP(A:A,[1]Hoja1!$C:$C,[1]Hoja1!$D:$D,"",0,1) -> ESMALTE BRILLON BLANCO. | C49: 7 | D49: =_xlfn.XLOOKUP(A:A,[2]Hoja1!$C:$C,[2]Hoja1!$H:$H,"",0,1) -> 533.62 | E49: =_xlfn.XLOOKUP(A:A,[1]Hoja1!$C:$C,[1]Hoja1!$H:$H,"",0,1) -> 401.72 | F49: =_xlfn.XLOOKUP(A:A,TD!A:A,TD!EC:EC,"",0,1) -> 2.4285714 | G49: =INT(F49) -> 2 | H49: =D49*$G$5 -> 1600.86 | I49: =E49*$G$5 -> 1205.16 | J49: 28003 | K49: =_xlfn.XLOOKUP(J:J,'[3]FILTROS 2'!$A:$A,'[3]FILTROS 2'!$E:$E,"",0,1) -> ESMALTE - BRILLON | O49: =_xlfn.XLOOKUP(A:A,[4]TD90D!$A:$A,[4]TD90D!$CW:$CW,"",0,1) -> 6 | P49: =_xlfn.XLOOKUP(A:A,[4]TD90D!$A:$A,[4]TD90D!$CX:$CX,"",0,1) -> 2 | Q49: =_xlfn.XLOOKUP(A:A,[4]TD90D!$A:$A,[4]TD90D!$DA:$DA,"",0,1) -> 0 | R49: =P49/C49 -> 0.28571429 | S49: =_xlfn.XLOOKUP(A:A,'[4]TD90D PZAS'!$A:$A,'[4]TD90D PZAS'!$CW:$CW,"",0,1) -> 18 | T49: =_xlfn.XLOOKUP(A:A,'[4]TD90D PZAS'!$A:$A,'[4]TD90D PZAS'!$CX:$CX,"",0,1) -> 2 | U49: =_xlfn.XLOOKUP(A:A,'[4]TD90D PZAS'!$A:$A,'[4]TD90D PZAS'!$DA:$DA,"",0,1) -> 0
A50: BAG-10846 | B50: =_xlfn.XLOOKUP(A:A,[1]Hoja1!$C:$C,[1]Hoja1!$D:$D,"",0,1) -> BARNIZ GLOSI ALQUI CEDRO | C50: 7 | D50: =_xlfn.XLOOKUP(A:A,[2]Hoja1!$C:$C,[2]Hoja1!$H:$H,"",0,1) -> 68.97 | E50: =_xlfn.XLOOKUP(A:A,[1]Hoja1!$C:$C,[1]Hoja1!$H:$H,"",0,1) -> 52.59 | F50: =_xlfn.XLOOKUP(A:A,TD!A:A,TD!EC:EC,"",0,1) -> 5.1428571 | G50: =INT(F50) -> 5 | H50: =D50*$G$5 -> 206.91 | I50: =E50*$G$5 -> 157.77 | J50: BAG-10846 | K50: =_xlfn.XLOOKUP(J:J,'[3]FILTROS 2'!$A:$A,'[3]FILTROS 2'!$E:$E,"",0,1) -> BARNIZ ALQUIDALICO GLOSI 3-1 | O50: =_xlfn.XLOOKUP(A:A,[4]TD90D!$A:$A,[4]TD90D!$CW:$CW,"",0,1) -> 2 | P50: =_xlfn.XLOOKUP(A:A,[4]TD90D!$A:$A,[4]TD90D!$CX:$CX,"",0,1) -> 1 | Q50: =_xlfn.XLOOKUP(A:A,[4]TD90D!$A:$A,[4]TD90D!$DA:$DA,"",0,1) -> 0 | R50: =P50/C50 -> 0.14285714 | S50: =_xlfn.XLOOKUP(A:A,'[4]TD90D PZAS'!$A:$A,'[4]TD90D PZAS'!$CW:$CW,"",0,1) -> 6 | T50: =_xlfn.XLOOKUP(A:A,'[4]TD90D PZAS'!$A:$A,'[4]TD90D PZAS'!$CX:$CX,"",0,1) -> 1 | U50: =_xlfn.XLOOKUP(A:A,'[4]TD90D PZAS'!$A:$A,'[4]TD90D PZAS'!$DA:$DA,"",0,1) -> 0
A51: VG-30004 | B51: =_xlfn.XLOOKUP(A:A,[1]Hoja1!$C:$C,[1]Hoja1!$D:$D,"",0,1) -> VINILICA GLOSI BLANCO 3A | C51: 7 | D51: =_xlfn.XLOOKUP(A:A,[2]Hoja1!$C:$C,[2]Hoja1!$H:$H,"",0,1) -> 80.17 | E51: =_xlfn.XLOOKUP(A:A,[1]Hoja1!$C:$C,[1]Hoja1!$H:$H,"",0,1) -> 56.9 | F51: =_xlfn.XLOOKUP(A:A,TD!A:A,TD!EC:EC,"",0,1) -> 4.4285714 | G51: =INT(F51) -> 4 | H51: =D51*$G$5 -> 240.51 | I51: =E51*$G$5 -> 170.7 | J51: VG-30004 | K51: =_xlfn.XLOOKUP(J:J,'[3]FILTROS 2'!$A:$A,'[3]FILTROS 2'!$E:$E,"",0,1) -> VINILICA - GLOSI 3 AÑOS | O51: =_xlfn.XLOOKUP(A:A,[4]TD90D!$A:$A,[4]TD90D!$CW:$CW,"",0,1) -> 10 | P51: =_xlfn.XLOOKUP(A:A,[4]TD90D!$A:$A,[4]TD90D!$CX:$CX,"",0,1) -> 4 | Q51: =_xlfn.XLOOKUP(A:A,[4]TD90D!$A:$A,[4]TD90D!$DA:$DA,"",0,1) -> 0 | R51: =P51/C51 -> 0.57142857 | S51: =_xlfn.XLOOKUP(A:A,'[4]TD90D PZAS'!$A:$A,'[4]TD90D PZAS'!$CW:$CW,"",0,1) -> 36 | T51: =_xlfn.XLOOKUP(A:A,'[4]TD90D PZAS'!$A:$A,'[4]TD90D PZAS'!$CX:$CX,"",0,1) -> 3 | U51: =_xlfn.XLOOKUP(A:A,'[4]TD90D PZAS'!$A:$A,'[4]TD90D PZAS'!$DA:$DA,"",0,1) -> 0
A52: SRG-10993 | B52: =_xlfn.XLOOKUP(A:A,[1]Hoja1!$C:$C,[1]Hoja1!$D:$D,"",0,1) -> ESMALTE GLOSI SR NEGRO BRILLANTE | C52: 7 | D52: =_xlfn.XLOOKUP(A:A,[2]Hoja1!$C:$C,[2]Hoja1!$H:$H,"",0,1) -> 730.17 | E52: =_xlfn.XLOOKUP(A:A,[1]Hoja1!$C:$C,[1]Hoja1!$H:$H,"",0,1) -> 584.48 | F52: =_xlfn.XLOOKUP(A:A,TD!A:A,TD!EC:EC,"",0,1) -> 3.2857143 | G52: =INT(F52) -> 3 | H52: =D52*$G$5 -> 2190.51 | I52: =E52*$G$5 -> 1753.44 | J52: SRG-10993 | K52: =_xlfn.XLOOKUP(J:J,'[3]FILTROS 2'!$A:$A,'[3]FILTROS 2'!$E:$E,"",0,1) -> ESMALTE - GLOSI SECADO RAPIDO | O52: =_xlfn.XLOOKUP(A:A,[4]TD90D!$A:$A,[4]TD90D!$CW:$CW,"",0,1) | P52: =_xlfn.XLOOKUP(A:A,[4]TD90D!$A:$A,[4]TD90D!$CX:$CX,"",0,1) | Q52: =_xlfn.XLOOKUP(A:A,[4]TD90D!$A:$A,[4]TD90D!$DA:$DA,"",0,1) | R52: =P52/C52 -> #VALUE! | S52: =_xlfn.XLOOKUP(A:A,'[4]TD90D PZAS'!$A:$A,'[4]TD90D PZAS'!$CW:$CW,"",0,1) | T52: =_xlfn.XLOOKUP(A:A,'[4]TD90D PZAS'!$A:$A,'[4]TD90D PZAS'!$CX:$CX,"",0,1) | U52: =_xlfn.XLOOKUP(A:A,'[4]TD90D PZAS'!$A:$A,'[4]TD90D PZAS'!$DA:$DA,"",0,1)
A53: VG-30014 | B53: =_xlfn.XLOOKUP(A:A,[1]Hoja1!$C:$C,[1]Hoja1!$D:$D,"",0,1) -> VINILICA GLOSI BLANCO BASIC | C53: 6 | D53: =_xlfn.XLOOKUP(A:A,[2]Hoja1!$C:$C,[2]Hoja1!$H:$H,"",0,1) -> 80.17 | E53: =_xlfn.XLOOKUP(A:A,[1]Hoja1!$C:$C,[1]Hoja1!$H:$H,"",0,1) -> 56.9 | F53: =_xlfn.XLOOKUP(A:A,TD!A:A,TD!EC:EC,"",0,1) -> 4.5 | G53: =INT(F53) -> 4 | H53: =D53*$G$5 -> 240.51 | I53: =E53*$G$5 -> 170.7 | J53: VG-30014 | K53: =_xlfn.XLOOKUP(J:J,'[3]FILTROS 2'!$A:$A,'[3]FILTROS 2'!$E:$E,"",0,1) -> VINILICA - GLOSI BASIC | O53: =_xlfn.XLOOKUP(A:A,[4]TD90D!$A:$A,[4]TD90D!$CW:$CW,"",0,1) -> 8 | P53: =_xlfn.XLOOKUP(A:A,[4]TD90D!$A:$A,[4]TD90D!$CX:$CX,"",0,1) -> 4 | Q53: =_xlfn.XLOOKUP(A:A,[4]TD90D!$A:$A,[4]TD90D!$DA:$DA,"",0,1) -> 0 | R53: =P53/C53 -> 0.66666667 | S53: =_xlfn.XLOOKUP(A:A,'[4]TD90D PZAS'!$A:$A,'[4]TD90D PZAS'!$CW:$CW,"",0,1) -> 42 | T53: =_xlfn.XLOOKUP(A:A,'[4]TD90D PZAS'!$A:$A,'[4]TD90D PZAS'!$CX:$CX,"",0,1) -> 2 | U53: =_xlfn.XLOOKUP(A:A,'[4]TD90D PZAS'!$A:$A,'[4]TD90D PZAS'!$DA:$DA,"",0,1) -> 0
A54: VG-30003 | B54: =_xlfn.XLOOKUP(A:A,[1]Hoja1!$C:$C,[1]Hoja1!$D:$D,"",0,1) -> VINILICA GLOSI BLANCO 3A | C54: 6 | D54: =_xlfn.XLOOKUP(A:A,[2]Hoja1!$C:$C,[2]Hoja1!$H:$H,"",0,1) -> 219.83 | E54: =_xlfn.XLOOKUP(A:A,[1]Hoja1!$C:$C,[1]Hoja1!$H:$H,"",0,1) -> 163.79 | F54: =_xlfn.XLOOKUP(A:A,TD!A:A,TD!EC:EC,"",0,1) -> 5 | G54: =INT(F54) -> 5 | H54: =D54*$G$5 -> 659.49 | I54: =E54*$G$5 -> 491.37 | J54: VG-30003 | K54: =_xlfn.XLOOKUP(J:J,'[3]FILTROS 2'!$A:$A,'[3]FILTROS 2'!$E:$E,"",0,1) -> VINILICA - GLOSI 3 AÑOS | O54: =_xlfn.XLOOKUP(A:A,[4]TD90D!$A:$A,[4]TD90D!$CW:$CW,"",0,1) -> 6 | P54: =_xlfn.XLOOKUP(A:A,[4]TD90D!$A:$A,[4]TD90D!$CX:$CX,"",0,1) -> 3 | Q54: =_xlfn.XLOOKUP(A:A,[4]TD90D!$A:$A,[4]TD90D!$DA:$DA,"",0,1) -> 0 | R54: =P54/C54 -> 0.5 | S54: =_xlfn.XLOOKUP(A:A,'[4]TD90D PZAS'!$A:$A,'[4]TD90D PZAS'!$CW:$CW,"",0,1) -> 23 | T54: =_xlfn.XLOOKUP(A:A,'[4]TD90D PZAS'!$A:$A,'[4]TD90D PZAS'!$CX:$CX,"",0,1) -> 3 | U54: =_xlfn.XLOOKUP(A:A,'[4]TD90D PZAS'!$A:$A,'[4]TD90D PZAS'!$DA:$DA,"",0,1) -> 0
A55: SRG-10995 | B55: =_xlfn.XLOOKUP(A:A,[1]Hoja1!$C:$C,[1]Hoja1!$D:$D,"",0,1) -> ESMALTE GLOSI SR NEGRO BRILLANTE | C55: 6 | D55: =_xlfn.XLOOKUP(A:A,[2]Hoja1!$C:$C,[2]Hoja1!$H:$H,"",0,1) -> 121.55 | E55: =_xlfn.XLOOKUP(A:A,[1]Hoja1!$C:$C,[1]Hoja1!$H:$H,"",0,1) -> 100 | F55: =_xlfn.XLOOKUP(A:A,TD!A:A,TD!EC:EC,"",0,1) -> 3.6666667 | G55: =INT(F55) -> 3 | H55: =D55*$G$5 -> 364.65 | I55: =E55*$G$5 -> 300 | J55: SRG-10995 | K55: =_xlfn.XLOOKUP(J:J,'[3]FILTROS 2'!$A:$A,'[3]FILTROS 2'!$E:$E,"",0,1) -> ESMALTE - GLOSI SECADO RAPIDO | O55: =_xlfn.XLOOKUP(A:A,[4]TD90D!$A:$A,[4]TD90D!$CW:$CW,"",0,1) | P55: =_xlfn.XLOOKUP(A:A,[4]TD90D!$A:$A,[4]TD90D!$CX:$CX,"",0,1) | Q55: =_xlfn.XLOOKUP(A:A,[4]TD90D!$A:$A,[4]TD90D!$DA:$DA,"",0,1) | R55: =P55/C55 -> #VALUE! | S55: =_xlfn.XLOOKUP(A:A,'[4]TD90D PZAS'!$A:$A,'[4]TD90D PZAS'!$CW:$CW,"",0,1) | T55: =_xlfn.XLOOKUP(A:A,'[4]TD90D PZAS'!$A:$A,'[4]TD90D PZAS'!$CX:$CX,"",0,1) | U55: =_xlfn.XLOOKUP(A:A,'[4]TD90D PZAS'!$A:$A,'[4]TD90D PZAS'!$DA:$DA,"",0,1)
A56: 2454 | B56: =_xlfn.XLOOKUP(A:A,[1]Hoja1!$C:$C,[1]Hoja1!$D:$D,"",0,1) -> AEROSOL PRISA SUPER CROMO | C56: 6 | D56: =_xlfn.XLOOKUP(A:A,[2]Hoja1!$C:$C,[2]Hoja1!$H:$H,"",0,1) -> 71.55 | E56: =_xlfn.XLOOKUP(A:A,[1]Hoja1!$C:$C,[1]Hoja1!$H:$H,"",0,1) -> 53.45 | F56: =_xlfn.XLOOKUP(A:A,TD!A:A,TD!EC:EC,"",0,1) -> 5.5 | G56: =INT(F56) -> 5 | H56: =D56*$G$5 -> 214.65 | I56: =E56*$G$5 -> 160.35 | J56: 2454 | K56: =_xlfn.XLOOKUP(J:J,'[3]FILTROS 2'!$A:$A,'[3]FILTROS 2'!$E:$E,"",0,1) -> AEROSOLES PRISA | O56: =_xlfn.XLOOKUP(A:A,[4]TD90D!$A:$A,[4]TD90D!$CW:$CW,"",0,1) -> 5 | P56: =_xlfn.XLOOKUP(A:A,[4]TD90D!$A:$A,[4]TD90D!$CX:$CX,"",0,1) -> 2 | Q56: =_xlfn.XLOOKUP(A:A,[4]TD90D!$A:$A,[4]TD90D!$DA:$DA,"",0,1) -> 0 | R56: =P56/C56 -> 0.33333333 | S56: =_xlfn.XLOOKUP(A:A,'[4]TD90D PZAS'!$A:$A,'[4]TD90D PZAS'!$CW:$CW,"",0,1) -> 42 | T56: =_xlfn.XLOOKUP(A:A,'[4]TD90D PZAS'!$A:$A,'[4]TD90D PZAS'!$CX:$CX,"",0,1) -> 2 | U56: =_xlfn.XLOOKUP(A:A,'[4]TD90D PZAS'!$A:$A,'[4]TD90D PZAS'!$DA:$DA,"",0,1) -> 0
A57: BAG-10845 | B57: =_xlfn.XLOOKUP(A:A,[1]Hoja1!$C:$C,[1]Hoja1!$D:$D,"",0,1) -> BARNIZ GLOSI ALQUI CEDRO | C57: 6 | D57: =_xlfn.XLOOKUP(A:A,[2]Hoja1!$C:$C,[2]Hoja1!$H:$H,"",0,1) -> 106.03 | E57: =_xlfn.XLOOKUP(A:A,[1]Hoja1!$C:$C,[1]Hoja1!$H:$H,"",0,1) -> 83.62 | F57: =_xlfn.XLOOKUP(A:A,TD!A:A,TD!EC:EC,"",0,1) -> 1.5 | G57: =INT(F57) -> 1 | H57: =D57*$G$5 -> 318.09 | I57: =E57*$G$5 -> 250.86 | J57: BAG-10845 | K57: =_xlfn.XLOOKUP(J:J,'[3]FILTROS 2'!$A:$A,'[3]FILTROS 2'!$E:$E,"",0,1) -> BARNIZ ALQUIDALICO GLOSI 3-1 | O57: =_xlfn.XLOOKUP(A:A,[4]TD90D!$A:$A,[4]TD90D!$CW:$CW,"",0,1) -> 4 | P57: =_xlfn.XLOOKUP(A:A,[4]TD90D!$A:$A,[4]TD90D!$CX:$CX,"",0,1) -> 1 | Q57: =_xlfn.XLOOKUP(A:A,[4]TD90D!$A:$A,[4]TD90D!$DA:$DA,"",0,1) -> 0 | R57: =P57/C57 -> 0.16666667 | S57: =_xlfn.XLOOKUP(A:A,'[4]TD90D PZAS'!$A:$A,'[4]TD90D PZAS'!$CW:$CW,"",0,1) -> 6 | T57: =_xlfn.XLOOKUP(A:A,'[4]TD90D PZAS'!$A:$A,'[4]TD90D PZAS'!$CX:$CX,"",0,1) -> 1 | U57: =_xlfn.XLOOKUP(A:A,'[4]TD90D PZAS'!$A:$A,'[4]TD90D PZAS'!$DA:$DA,"",0,1) -> 0
A58: 28804 | B58: =_xlfn.XLOOKUP(A:A,[1]Hoja1!$C:$C,[1]Hoja1!$D:$D,"",0,1) -> BARNIZ ALQ. TRANSP. NATURAL | C58: 6 | D58: =_xlfn.XLOOKUP(A:A,[2]Hoja1!$C:$C,[2]Hoja1!$H:$H,"",0,1) -> 232.76 | E58: =_xlfn.XLOOKUP(A:A,[1]Hoja1!$C:$C,[1]Hoja1!$H:$H,"",0,1) -> 138.79 | F58: =_xlfn.XLOOKUP(A:A,TD!A:A,TD!EC:EC,"",0,1) -> 3.8333333 | G58: =INT(F58) -> 3 | H58: =D58*$G$5 -> 698.28 | I58: =E58*$G$5 -> 416.37 | J58: 28804 | K58: =_xlfn.XLOOKUP(J:J,'[3]FILTROS 2'!$A:$A,'[3]FILTROS 2'!$E:$E,"",0,1) -> BARNIZ ALQUIDALICO SIGLO | O58: =_xlfn.XLOOKUP(A:A,[4]TD90D!$A:$A,[4]TD90D!$CW:$CW,"",0,1) -> 2 | P58: =_xlfn.XLOOKUP(A:A,[4]TD90D!$A:$A,[4]TD90D!$CX:$CX,"",0,1) -> 1 | Q58: =_xlfn.XLOOKUP(A:A,[4]TD90D!$A:$A,[4]TD90D!$DA:$DA,"",0,1) -> 0 | R58: =P58/C58 -> 0.16666667 | S58: =_xlfn.XLOOKUP(A:A,'[4]TD90D PZAS'!$A:$A,'[4]TD90D PZAS'!$CW:$CW,"",0,1) -> 6 | T58: =_xlfn.XLOOKUP(A:A,'[4]TD90D PZAS'!$A:$A,'[4]TD90D PZAS'!$CX:$CX,"",0,1) -> 1 | U58: =_xlfn.XLOOKUP(A:A,'[4]TD90D PZAS'!$A:$A,'[4]TD90D PZAS'!$DA:$DA,"",0,1) -> 0
A59: 29384 | B59: =_xlfn.XLOOKUP(A:A,[1]Hoja1!$C:$C,[1]Hoja1!$D:$D,"",0,1) -> FONDO GRIS CLARO 3211 | C59: 6 | D59: =_xlfn.XLOOKUP(A:A,[2]Hoja1!$C:$C,[2]Hoja1!$H:$H,"",0,1) -> 243.97 | E59: =_xlfn.XLOOKUP(A:A,[1]Hoja1!$C:$C,[1]Hoja1!$H:$H,"",0,1) -> 171.55 | F59: =_xlfn.XLOOKUP(A:A,TD!A:A,TD!EC:EC,"",0,1) -> 0.16666667 | G59: =INT(F59) -> 0 | H59: =D59*$G$5 -> 731.91 | I59: =E59*$G$5 -> 514.65 | J59: 29384 | K59: =_xlfn.XLOOKUP(J:J,'[3]FILTROS 2'!$A:$A,'[3]FILTROS 2'!$E:$E,"",0,1) -> FONDO DE NITRO AUTOMOTRIZ | O59: =_xlfn.XLOOKUP(A:A,[4]TD90D!$A:$A,[4]TD90D!$CW:$CW,"",0,1) -> 3 | P59: =_xlfn.XLOOKUP(A:A,[4]TD90D!$A:$A,[4]TD90D!$CX:$CX,"",0,1) -> 1 | Q59: =_xlfn.XLOOKUP(A:A,[4]TD90D!$A:$A,[4]TD90D!$DA:$DA,"",0,1) -> 0 | R59: =P59/C59 -> 0.16666667 | S59: =_xlfn.XLOOKUP(A:A,'[4]TD90D PZAS'!$A:$A,'[4]TD90D PZAS'!$CW:$CW,"",0,1) -> -2 | T59: =_xlfn.XLOOKUP(A:A,'[4]TD90D PZAS'!$A:$A,'[4]TD90D PZAS'!$CX:$CX,"",0,1) -> 0 | U59: =_xlfn.XLOOKUP(A:A,'[4]TD90D PZAS'!$A:$A,'[4]TD90D PZAS'!$DA:$DA,"",0,1) -> 0
A60: 28454 | B60: =_xlfn.XLOOKUP(A:A,[1]Hoja1!$C:$C,[1]Hoja1!$D:$D,"",0,1) -> BRILLON SANDIA | C60: 5 | D60: =_xlfn.XLOOKUP(A:A,[2]Hoja1!$C:$C,[2]Hoja1!$H:$H,"",0,1) -> 150.86 | E60: =_xlfn.XLOOKUP(A:A,[1]Hoja1!$C:$C,[1]Hoja1!$H:$H,"",0,1) -> 112.93 | F60: =_xlfn.XLOOKUP(A:A,TD!A:A,TD!EC:EC,"",0,1) -> 4.8 | G60: =INT(F60) -> 4 | H60: =D60*$G$5 -> 452.58 | I60: =E60*$G$5 -> 338.79 | J60: 28454 | K60: =_xlfn.XLOOKUP(J:J,'[3]FILTROS 2'!$A:$A,'[3]FILTROS 2'!$E:$E,"",0,1) -> ESMALTE - BRILLON | O60: =_xlfn.XLOOKUP(A:A,[4]TD90D!$A:$A,[4]TD90D!$CW:$CW,"",0,1) -> 2 | P60: =_xlfn.XLOOKUP(A:A,[4]TD90D!$A:$A,[4]TD90D!$CX:$CX,"",0,1) -> 1 | Q60: =_xlfn.XLOOKUP(A:A,[4]TD90D!$A:$A,[4]TD90D!$DA:$DA,"",0,1) -> 0 | R60: =P60/C60 -> 0.2 | S60: =_xlfn.XLOOKUP(A:A,'[4]TD90D PZAS'!$A:$A,'[4]TD90D PZAS'!$CW:$CW,"",0,1) -> 12 | T60: =_xlfn.XLOOKUP(A:A,'[4]TD90D PZAS'!$A:$A,'[4]TD90D PZAS'!$CX:$CX,"",0,1) -> 1 | U60: =_xlfn.XLOOKUP(A:A,'[4]TD90D PZAS'!$A:$A,'[4]TD90D PZAS'!$DA:$DA,"",0,1) -> 0
A61: 28585 | B61: =_xlfn.XLOOKUP(A:A,[1]Hoja1!$C:$C,[1]Hoja1!$D:$D,"",0,1) -> BRILLON CACAO | C61: 5 | D61: =_xlfn.XLOOKUP(A:A,[2]Hoja1!$C:$C,[2]Hoja1!$H:$H,"",0,1) -> 90.52 | E61: =_xlfn.XLOOKUP(A:A,[1]Hoja1!$C:$C,[1]Hoja1!$H:$H,"",0,1) -> 67.24 | F61: =_xlfn.XLOOKUP(A:A,TD!A:A,TD!EC:EC,"",0,1) -> 3.6 | G61: =INT(F61) -> 3 | H61: =D61*$G$5 -> 271.56 | I61: =E61*$G$5 -> 201.72 | J61: 28585 | K61: =_xlfn.XLOOKUP(J:J,'[3]FILTROS 2'!$A:$A,'[3]FILTROS 2'!$E:$E,"",0,1) -> ESMALTE - BRILLON | O61: =_xlfn.XLOOKUP(A:A,[4]TD90D!$A:$A,[4]TD90D!$CW:$CW,"",0,1) -> 4 | P61: =_xlfn.XLOOKUP(A:A,[4]TD90D!$A:$A,[4]TD90D!$CX:$CX,"",0,1) -> 2 | Q61: =_xlfn.XLOOKUP(A:A,[4]TD90D!$A:$A,[4]TD90D!$DA:$DA,"",0,1) -> 0 | R61: =P61/C61 -> 0.4 | S61: =_xlfn.XLOOKUP(A:A,'[4]TD90D PZAS'!$A:$A,'[4]TD90D PZAS'!$CW:$CW,"",0,1) -> 12 | T61: =_xlfn.XLOOKUP(A:A,'[4]TD90D PZAS'!$A:$A,'[4]TD90D PZAS'!$CX:$CX,"",0,1) -> 2 | U61: =_xlfn.XLOOKUP(A:A,'[4]TD90D PZAS'!$A:$A,'[4]TD90D PZAS'!$DA:$DA,"",0,1) -> 0
A62: PRG-10564 | B62: =_xlfn.XLOOKUP(A:A,[1]Hoja1!$C:$C,[1]Hoja1!$D:$D,"",0,1) -> ESTRUCTURAS ROJO OXIDO | C62: 5 | D62: =_xlfn.XLOOKUP(A:A,[2]Hoja1!$C:$C,[2]Hoja1!$H:$H,"",0,1) -> 138.79 | E62: =_xlfn.XLOOKUP(A:A,[1]Hoja1!$C:$C,[1]Hoja1!$H:$H,"",0,1) -> 105.17 | F62: =_xlfn.XLOOKUP(A:A,TD!A:A,TD!EC:EC,"",0,1) -> 3 | G62: =INT(F62) -> 3 | H62: =D62*$G$5 -> 416.37 | I62: =E62*$G$5 -> 315.51 | J62: PRG-10564 | K62: =_xlfn.XLOOKUP(J:J,'[3]FILTROS 2'!$A:$A,'[3]FILTROS 2'!$E:$E,"",0,1) -> ESMALTE - ESTRUCTURAS GLOSI | O62: =_xlfn.XLOOKUP(A:A,[4]TD90D!$A:$A,[4]TD90D!$CW:$CW,"",0,1) -> 2 | P62: =_xlfn.XLOOKUP(A:A,[4]TD90D!$A:$A,[4]TD90D!$CX:$CX,"",0,1) -> 1 | Q62: =_xlfn.XLOOKUP(A:A,[4]TD90D!$A:$A,[4]TD90D!$DA:$DA,"",0,1) -> 0 | R62: =P62/C62 -> 0.2 | S62: =_xlfn.XLOOKUP(A:A,'[4]TD90D PZAS'!$A:$A,'[4]TD90D PZAS'!$CW:$CW,"",0,1) -> 3 | T62: =_xlfn.XLOOKUP(A:A,'[4]TD90D PZAS'!$A:$A,'[4]TD90D PZAS'!$CX:$CX,"",0,1) -> 1 | U62: =_xlfn.XLOOKUP(A:A,'[4]TD90D PZAS'!$A:$A,'[4]TD90D PZAS'!$DA:$DA,"",0,1) -> 0
A63: 2315 | B63: =_xlfn.XLOOKUP(A:A,[1]Hoja1!$C:$C,[1]Hoja1!$D:$D,"",0,1) -> AEROSOL AMARILLO | C63: 5 | D63: =_xlfn.XLOOKUP(A:A,[2]Hoja1!$C:$C,[2]Hoja1!$H:$H,"",0,1) -> 55.17 | E63: =_xlfn.XLOOKUP(A:A,[1]Hoja1!$C:$C,[1]Hoja1!$H:$H,"",0,1) -> 41.38 | F63: =_xlfn.XLOOKUP(A:A,TD!A:A,TD!EC:EC,"",0,1) -> 6 | G63: =INT(F63) -> 6 | H63: =D63*$G$5 -> 165.51 | I63: =E63*$G$5 -> 124.14 | J63: 2315 | K63: =_xlfn.XLOOKUP(J:J,'[3]FILTROS 2'!$A:$A,'[3]FILTROS 2'!$E:$E,"",0,1) -> AEROSOLES PRISA | O63: =_xlfn.XLOOKUP(A:A,[4]TD90D!$A:$A,[4]TD90D!$CW:$CW,"",0,1) -> 4 | P63: =_xlfn.XLOOKUP(A:A,[4]TD90D!$A:$A,[4]TD90D!$CX:$CX,"",0,1) -> 2 | Q63: =_xlfn.XLOOKUP(A:A,[4]TD90D!$A:$A,[4]TD90D!$DA:$DA,"",0,1) -> 0 | R63: =P63/C63 -> 0.4 | S63: =_xlfn.XLOOKUP(A:A,'[4]TD90D PZAS'!$A:$A,'[4]TD90D PZAS'!$CW:$CW,"",0,1) -> 24 | T63: =_xlfn.XLOOKUP(A:A,'[4]TD90D PZAS'!$A:$A,'[4]TD90D PZAS'!$CX:$CX,"",0,1) -> 2 | U63: =_xlfn.XLOOKUP(A:A,'[4]TD90D PZAS'!$A:$A,'[4]TD90D PZAS'!$DA:$DA,"",0,1) -> 0
A64: VG-50994 | B64: =_xlfn.XLOOKUP(A:A,[1]Hoja1!$C:$C,[1]Hoja1!$D:$D,"",0,1) -> VINILICA GLOSI NEGRO 5A | C64: 5 | D64: =_xlfn.XLOOKUP(A:A,[2]Hoja1!$C:$C,[2]Hoja1!$H:$H,"",0,1) -> 107.76 | E64: =_xlfn.XLOOKUP(A:A,[1]Hoja1!$C:$C,[1]Hoja1!$H:$H,"",0,1) -> 78.45 | F64: =_xlfn.XLOOKUP(A:A,TD!A:A,TD!EC:EC,"",0,1) -> 4.4 | G64: =INT(F64) -> 4 | H64: =D64*$G$5 -> 323.28 | I64: =E64*$G$5 -> 235.35 | J64: VG-50994 | K64: =_xlfn.XLOOKUP(J:J,'[3]FILTROS 2'!$A:$A,'[3]FILTROS 2'!$E:$E,"",0,1) -> VINILICA - GLOSI 5 AÑOS | O64: =_xlfn.XLOOKUP(A:A,[4]TD90D!$A:$A,[4]TD90D!$CW:$CW,"",0,1) -> 7 | P64: =_xlfn.XLOOKUP(A:A,[4]TD90D!$A:$A,[4]TD90D!$CX:$CX,"",0,1) -> 3 | Q64: =_xlfn.XLOOKUP(A:A,[4]TD90D!$A:$A,[4]TD90D!$DA:$DA,"",0,1) -> 0 | R64: =P64/C64 -> 0.6 | S64: =_xlfn.XLOOKUP(A:A,'[4]TD90D PZAS'!$A:$A,'[4]TD90D PZAS'!$CW:$CW,"",0,1) -> 28 | T64: =_xlfn.XLOOKUP(A:A,'[4]TD90D PZAS'!$A:$A,'[4]TD90D PZAS'!$CX:$CX,"",0,1) -> 3 | U64: =_xlfn.XLOOKUP(A:A,'[4]TD90D PZAS'!$A:$A,'[4]TD90D PZAS'!$DA:$DA,"",0,1) -> 0
A65: 28104 | B65: =_xlfn.XLOOKUP(A:A,[1]Hoja1!$C:$C,[1]Hoja1!$D:$D,"",0,1) -> BRILLON ALUMINIO | C65: 5 | D65: =_xlfn.XLOOKUP(A:A,[2]Hoja1!$C:$C,[2]Hoja1!$H:$H,"",0,1) -> 150.86 | E65: =_xlfn.XLOOKUP(A:A,[1]Hoja1!$C:$C,[1]Hoja1!$H:$H,"",0,1) -> 112.93 | F65: =_xlfn.XLOOKUP(A:A,TD!A:A,TD!EC:EC,"",0,1) -> 2.4 | G65: =INT(F65) -> 2 | H65: =D65*$G$5 -> 452.58 | I65: =E65*$G$5 -> 338.79 | J65: 28104 | K65: =_xlfn.XLOOKUP(J:J,'[3]FILTROS 2'!$A:$A,'[3]FILTROS 2'!$E:$E,"",0,1) -> ESMALTE - BRILLON | O65: =_xlfn.XLOOKUP(A:A,[4]TD90D!$A:$A,[4]TD90D!$CW:$CW,"",0,1) -> 4 | P65: =_xlfn.XLOOKUP(A:A,[4]TD90D!$A:$A,[4]TD90D!$CX:$CX,"",0,1) -> 1 | Q65: =_xlfn.XLOOKUP(A:A,[4]TD90D!$A:$A,[4]TD90D!$DA:$DA,"",0,1) -> 0 | R65: =P65/C65 -> 0.2 | S65: =_xlfn.XLOOKUP(A:A,'[4]TD90D PZAS'!$A:$A,'[4]TD90D PZAS'!$CW:$CW,"",0,1) -> 12 | T65: =_xlfn.XLOOKUP(A:A,'[4]TD90D PZAS'!$A:$A,'[4]TD90D PZAS'!$CX:$CX,"",0,1) -> 1 | U65: =_xlfn.XLOOKUP(A:A,'[4]TD90D PZAS'!$A:$A,'[4]TD90D PZAS'!$DA:$DA,"",0,1) -> 0
A66: 2463 | B66: =_xlfn.XLOOKUP(A:A,[1]Hoja1!$C:$C,[1]Hoja1!$D:$D,"",0,1) -> AEROSOL AZUL METALICO | C66: 5 | D66: =_xlfn.XLOOKUP(A:A,[2]Hoja1!$C:$C,[2]Hoja1!$H:$H,"",0,1) -> 71.55 | E66: =_xlfn.XLOOKUP(A:A,[1]Hoja1!$C:$C,[1]Hoja1!$H:$H,"",0,1) -> 53.45 | F66: =_xlfn.XLOOKUP(A:A,TD!A:A,TD!EC:EC,"",0,1) -> 4.6 | G66: =INT(F66) -> 4 | H66: =D66*$G$5 -> 214.65 | I66: =E66*$G$5 -> 160.35 | J66: 2463 | K66: =_xlfn.XLOOKUP(J:J,'[3]FILTROS 2'!$A:$A,'[3]FILTROS 2'!$E:$E,"",0,1) -> AEROSOLES PRISA | O66: =_xlfn.XLOOKUP(A:A,[4]TD90D!$A:$A,[4]TD90D!$CW:$CW,"",0,1) -> 2 | P66: =_xlfn.XLOOKUP(A:A,[4]TD90D!$A:$A,[4]TD90D!$CX:$CX,"",0,1) -> 1 | Q66: =_xlfn.XLOOKUP(A:A,[4]TD90D!$A:$A,[4]TD90D!$DA:$DA,"",0,1) -> 0 | R66: =P66/C66 -> 0.2 | S66: =_xlfn.XLOOKUP(A:A,'[4]TD90D PZAS'!$A:$A,'[4]TD90D PZAS'!$CW:$CW,"",0,1) -> 12 | T66: =_xlfn.XLOOKUP(A:A,'[4]TD90D PZAS'!$A:$A,'[4]TD90D PZAS'!$CX:$CX,"",0,1) -> 1 | U66: =_xlfn.XLOOKUP(A:A,'[4]TD90D PZAS'!$A:$A,'[4]TD90D PZAS'!$DA:$DA,"",0,1) -> 0
A67: 28105 | B67: =_xlfn.XLOOKUP(A:A,[1]Hoja1!$C:$C,[1]Hoja1!$D:$D,"",0,1) -> BRILLON ALUMINIO | C67: 5 | D67: =_xlfn.XLOOKUP(A:A,[2]Hoja1!$C:$C,[2]Hoja1!$H:$H,"",0,1) -> 90.52 | E67: =_xlfn.XLOOKUP(A:A,[1]Hoja1!$C:$C,[1]Hoja1!$H:$H,"",0,1) -> 67.24 | F67: =_xlfn.XLOOKUP(A:A,TD!A:A,TD!EC:EC,"",0,1) -> 1.8 | G67: =INT(F67) -> 1 | H67: =D67*$G$5 -> 271.56 | I67: =E67*$G$5 -> 201.72 | J67: 28105 | K67: =_xlfn.XLOOKUP(J:J,'[3]FILTROS 2'!$A:$A,'[3]FILTROS 2'!$E:$E,"",0,1) -> ESMALTE - BRILLON | O67: =_xlfn.XLOOKUP(A:A,[4]TD90D!$A:$A,[4]TD90D!$CW:$CW,"",0,1) -> 3 | P67: =_xlfn.XLOOKUP(A:A,[4]TD90D!$A:$A,[4]TD90D!$CX:$CX,"",0,1) -> 1 | Q67: =_xlfn.XLOOKUP(A:A,[4]TD90D!$A:$A,[4]TD90D!$DA:$DA,"",0,1) -> 0 | R67: =P67/C67 -> 0.2 | S67: =_xlfn.XLOOKUP(A:A,'[4]TD90D PZAS'!$A:$A,'[4]TD90D PZAS'!$CW:$CW,"",0,1) -> 3 | T67: =_xlfn.XLOOKUP(A:A,'[4]TD90D PZAS'!$A:$A,'[4]TD90D PZAS'!$CX:$CX,"",0,1) -> 1 | U67: =_xlfn.XLOOKUP(A:A,'[4]TD90D PZAS'!$A:$A,'[4]TD90D PZAS'!$DA:$DA,"",0,1) -> 0
A68: PRG-10931 | B68: =_xlfn.XLOOKUP(A:A,[1]Hoja1!$C:$C,[1]Hoja1!$D:$D,"",0,1) -> PRIMARIO GLOSI ESTRUCTURAS GRIS | C68: 5 | D68: =_xlfn.XLOOKUP(A:A,[2]Hoja1!$C:$C,[2]Hoja1!$H:$H,"",0,1) -> 2001.72 | E68: =_xlfn.XLOOKUP(A:A,[1]Hoja1!$C:$C,[1]Hoja1!$H:$H,"",0,1) -> 1500.86 | F68: =_xlfn.XLOOKUP(A:A,TD!A:A,TD!EC:EC,"",0,1) -> -0.2 | G68: =INT(F68) -> -1 | H68: =D68*$G$5 -> 6005.16 | I68: =E68*$G$5 -> 4502.58 | J68: PRG-10931 | K68: =_xlfn.XLOOKUP(J:J,'[3]FILTROS 2'!$A:$A,'[3]FILTROS 2'!$E:$E,"",0,1) -> ESMALTE - ESTRUCTURAS GLOSI | O68: =_xlfn.XLOOKUP(A:A,[4]TD90D!$A:$A,[4]TD90D!$CW:$CW,"",0,1) -> 4 | P68: =_xlfn.XLOOKUP(A:A,[4]TD90D!$A:$A,[4]TD90D!$CX:$CX,"",0,1) -> 1 | Q68: =_xlfn.XLOOKUP(A:A,[4]TD90D!$A:$A,[4]TD90D!$DA:$DA,"",0,1) -> 0 | R68: =P68/C68 -> 0.2 | S68: =_xlfn.XLOOKUP(A:A,'[4]TD90D PZAS'!$A:$A,'[4]TD90D PZAS'!$CW:$CW,"",0,1) -> 0 | T68: =_xlfn.XLOOKUP(A:A,'[4]TD90D PZAS'!$A:$A,'[4]TD90D PZAS'!$CX:$CX,"",0,1) -> 0 | U68: =_xlfn.XLOOKUP(A:A,'[4]TD90D PZAS'!$A:$A,'[4]TD90D PZAS'!$DA:$DA,"",0,1) -> 0
A69: IG-40001 | B69: =_xlfn.XLOOKUP(A:A,[1]Hoja1!$C:$C,[1]Hoja1!$D:$D,"",0,1) -> AGUACERO 4A BLANCO FIBRATADO | C69: 5 | D69: =_xlfn.XLOOKUP(A:A,[2]Hoja1!$C:$C,[2]Hoja1!$H:$H,"",0,1) -> 1019.83 | E69: =_xlfn.XLOOKUP(A:A,[1]Hoja1!$C:$C,[1]Hoja1!$H:$H,"",0,1) -> 816.38 | F69: =_xlfn.XLOOKUP(A:A,TD!A:A,TD!EC:EC,"",0,1) -> 5.2 | G69: =INT(F69) -> 5 | H69: =D69*$G$5 -> 3059.49 | I69: =E69*$G$5 -> 2449.14 | J69: IG-40001 | K69: =_xlfn.XLOOKUP(J:J,'[3]FILTROS 2'!$A:$A,'[3]FILTROS 2'!$E:$E,"",0,1) -> IMPERGLOSI AGUACERO FIBRA 4 A | O69: =_xlfn.XLOOKUP(A:A,[4]TD90D!$A:$A,[4]TD90D!$CW:$CW,"",0,1) -> 9 | P69: =_xlfn.XLOOKUP(A:A,[4]TD90D!$A:$A,[4]TD90D!$CX:$CX,"",0,1) -> 4 | Q69: =_xlfn.XLOOKUP(A:A,[4]TD90D!$A:$A,[4]TD90D!$DA:$DA,"",0,1) -> 0 | R69: =P69/C69 -> 0.8 | S69: =_xlfn.XLOOKUP(A:A,'[4]TD90D PZAS'!$A:$A,'[4]TD90D PZAS'!$CW:$CW,"",0,1) -> 23 | T69: =_xlfn.XLOOKUP(A:A,'[4]TD90D PZAS'!$A:$A,'[4]TD90D PZAS'!$CX:$CX,"",0,1) -> 4 | U69: =_xlfn.XLOOKUP(A:A,'[4]TD90D PZAS'!$A:$A,'[4]TD90D PZAS'!$DA:$DA,"",0,1) -> 0
A70: E-90191 | B70: =_xlfn.XLOOKUP(A:A,[1]Hoja1!$C:$C,[1]Hoja1!$D:$D,"",0,1) -> PRIMARIO ESTRUCTURAS BLANCO | C70: 5 | D70: =_xlfn.XLOOKUP(A:A,[2]Hoja1!$C:$C,[2]Hoja1!$H:$H,"",0,1) -> 3537.93 | E70: =_xlfn.XLOOKUP(A:A,[1]Hoja1!$C:$C,[1]Hoja1!$H:$H,"",0,1) -> 3037.93 | F70: =_xlfn.XLOOKUP(A:A,TD!A:A,TD!EC:EC,"",0,1) -> -0.2 | G70: =INT(F70) -> -1 | H70: =D70*$G$5 -> 10613.79 | I70: =E70*$G$5 -> 9113.79 | J70: E-90191 | K70: =_xlfn.XLOOKUP(J:J,'[3]FILTROS 2'!$A:$A,'[3]FILTROS 2'!$E:$E,"",0,1) -> PRIMARIOS ESTRUCTURALES ALQUID | O70: =_xlfn.XLOOKUP(A:A,[4]TD90D!$A:$A,[4]TD90D!$CW:$CW,"",0,1) -> 3 | P70: =_xlfn.XLOOKUP(A:A,[4]TD90D!$A:$A,[4]TD90D!$CX:$CX,"",0,1) -> 1 | Q70: =_xlfn.XLOOKUP(A:A,[4]TD90D!$A:$A,[4]TD90D!$DA:$DA,"",0,1) -> 0 | R70: =P70/C70 -> 0.2 | S70: =_xlfn.XLOOKUP(A:A,'[4]TD90D PZAS'!$A:$A,'[4]TD90D PZAS'!$CW:$CW,"",0,1) -> -1 | T70: =_xlfn.XLOOKUP(A:A,'[4]TD90D PZAS'!$A:$A,'[4]TD90D PZAS'!$CX:$CX,"",0,1) -> 0 | U70: =_xlfn.XLOOKUP(A:A,'[4]TD90D PZAS'!$A:$A,'[4]TD90D PZAS'!$DA:$DA,"",0,1) -> 0
A71: VG-30001 | B71: =_xlfn.XLOOKUP(A:A,[1]Hoja1!$C:$C,[1]Hoja1!$D:$D,"",0,1) -> VINILICA GLOSI BLANCO 3A | C71: 5 | D71: =_xlfn.XLOOKUP(A:A,[2]Hoja1!$C:$C,[2]Hoja1!$H:$H,"",0,1) -> 874.14 | E71: =_xlfn.XLOOKUP(A:A,[1]Hoja1!$C:$C,[1]Hoja1!$H:$H,"",0,1) -> 656.9 | F71: =_xlfn.XLOOKUP(A:A,TD!A:A,TD!EC:EC,"",0,1) -> 2 | G71: =INT(F71) -> 2 | H71: =D71*$G$5 -> 2622.42 | I71: =E71*$G$5 -> 1970.7 | J71: VG-30001 | K71: =_xlfn.XLOOKUP(J:J,'[3]FILTROS 2'!$A:$A,'[3]FILTROS 2'!$E:$E,"",0,1) -> VINILICA - GLOSI 3 AÑOS | O71: =_xlfn.XLOOKUP(A:A,[4]TD90D!$A:$A,[4]TD90D!$CW:$CW,"",0,1) -> 8 | P71: =_xlfn.XLOOKUP(A:A,[4]TD90D!$A:$A,[4]TD90D!$CX:$CX,"",0,1) -> 3 | Q71: =_xlfn.XLOOKUP(A:A,[4]TD90D!$A:$A,[4]TD90D!$DA:$DA,"",0,1) -> 0 | R71: =P71/C71 -> 0.6 | S71: =_xlfn.XLOOKUP(A:A,'[4]TD90D PZAS'!$A:$A,'[4]TD90D PZAS'!$CW:$CW,"",0,1) -> 13 | T71: =_xlfn.XLOOKUP(A:A,'[4]TD90D PZAS'!$A:$A,'[4]TD90D PZAS'!$CX:$CX,"",0,1) -> 3 | U71: =_xlfn.XLOOKUP(A:A,'[4]TD90D PZAS'!$A:$A,'[4]TD90D PZAS'!$DA:$DA,"",0,1) -> 0
A72: SRG-10005 | B72: =_xlfn.XLOOKUP(A:A,[1]Hoja1!$C:$C,[1]Hoja1!$D:$D,"",0,1) -> ESMALTE GLOSI SR BLANCO | C72: 5 | D72: =_xlfn.XLOOKUP(A:A,[2]Hoja1!$C:$C,[2]Hoja1!$H:$H,"",0,1) -> 121.55 | E72: =_xlfn.XLOOKUP(A:A,[1]Hoja1!$C:$C,[1]Hoja1!$H:$H,"",0,1) -> 100 | F72: =_xlfn.XLOOKUP(A:A,TD!A:A,TD!EC:EC,"",0,1) -> 4.2 | G72: =INT(F72) -> 4 | H72: =D72*$G$5 -> 364.65 | I72: =E72*$G$5 -> 300 | J72: SRG-10005 | K72: =_xlfn.XLOOKUP(J:J,'[3]FILTROS 2'!$A:$A,'[3]FILTROS 2'!$E:$E,"",0,1) -> ESMALTE - GLOSI SECADO RAPIDO | O72: =_xlfn.XLOOKUP(A:A,[4]TD90D!$A:$A,[4]TD90D!$CW:$CW,"",0,1) -> 3 | P72: =_xlfn.XLOOKUP(A:A,[4]TD90D!$A:$A,[4]TD90D!$CX:$CX,"",0,1) -> 1 | Q72: =_xlfn.XLOOKUP(A:A,[4]TD90D!$A:$A,[4]TD90D!$DA:$DA,"",0,1) -> 0 | R72: =P72/C72 -> 0.2 | S72: =_xlfn.XLOOKUP(A:A,'[4]TD90D PZAS'!$A:$A,'[4]TD90D PZAS'!$CW:$CW,"",0,1) -> 13 | T72: =_xlfn.XLOOKUP(A:A,'[4]TD90D PZAS'!$A:$A,'[4]TD90D PZAS'!$CX:$CX,"",0,1) -> 1 | U72: =_xlfn.XLOOKUP(A:A,'[4]TD90D PZAS'!$A:$A,'[4]TD90D PZAS'!$DA:$DA,"",0,1) -> 0
A73: IG-40561 | B73: =_xlfn.XLOOKUP(A:A,[1]Hoja1!$C:$C,[1]Hoja1!$D:$D,"",0,1) -> AGUACERO 4A TERRACOTA FIBRATADO | C73: 5 | D73: =_xlfn.XLOOKUP(A:A,[2]Hoja1!$C:$C,[2]Hoja1!$H:$H,"",0,1) -> 1019.83 | E73: =_xlfn.XLOOKUP(A:A,[1]Hoja1!$C:$C,[1]Hoja1!$H:$H,"",0,1) -> 816.38 | F73: =_xlfn.XLOOKUP(A:A,TD!A:A,TD!EC:EC,"",0,1) -> 7.4 | G73: =INT(F73) -> 7 | H73: =D73*$G$5 -> 3059.49 | I73: =E73*$G$5 -> 2449.14 | J73: IG-40561 | K73: =_xlfn.XLOOKUP(J:J,'[3]FILTROS 2'!$A:$A,'[3]FILTROS 2'!$E:$E,"",0,1) -> IMPERGLOSI AGUACERO FIBRA 4 A | O73: =_xlfn.XLOOKUP(A:A,[4]TD90D!$A:$A,[4]TD90D!$CW:$CW,"",0,1) -> 2 | P73: =_xlfn.XLOOKUP(A:A,[4]TD90D!$A:$A,[4]TD90D!$CX:$CX,"",0,1) -> 1 | Q73: =_xlfn.XLOOKUP(A:A,[4]TD90D!$A:$A,[4]TD90D!$DA:$DA,"",0,1) -> 0 | R73: =P73/C73 -> 0.2 | S73: =_xlfn.XLOOKUP(A:A,'[4]TD90D PZAS'!$A:$A,'[4]TD90D PZAS'!$CW:$CW,"",0,1) -> 4 | T73: =_xlfn.XLOOKUP(A:A,'[4]TD90D PZAS'!$A:$A,'[4]TD90D PZAS'!$CX:$CX,"",0,1) -> 1 | U73: =_xlfn.XLOOKUP(A:A,'[4]TD90D PZAS'!$A:$A,'[4]TD90D PZAS'!$DA:$DA,"",0,1) -> 0
A74: 76004 | B74: =_xlfn.XLOOKUP(A:A,[1]Hoja1!$C:$C,[1]Hoja1!$D:$D,"",0,1) -> ACEITE DE LINAZA PROTECTOR DE MADERA | C74: 5 | D74: =_xlfn.XLOOKUP(A:A,[2]Hoja1!$C:$C,[2]Hoja1!$H:$H,"",0,1) -> 268.97 | E74: =_xlfn.XLOOKUP(A:A,[1]Hoja1!$C:$C,[1]Hoja1!$H:$H,"",0,1) -> 268.97 | F74: =_xlfn.XLOOKUP(A:A,TD!A:A,TD!EC:EC,"",0,1) -> 0.4 | G74: =INT(F74) -> 0 | H74: =D74*$G$5 -> 806.91 | I74: =E74*$G$5 -> 806.91 | J74: 76004 | K74: =_xlfn.XLOOKUP(J:J,'[3]FILTROS 2'!$A:$A,'[3]FILTROS 2'!$E:$E,"",0,1) -> ACEITE DE LINAZA | O74: =_xlfn.XLOOKUP(A:A,[4]TD90D!$A:$A,[4]TD90D!$CW:$CW,"",0,1) | P74: =_xlfn.XLOOKUP(A:A,[4]TD90D!$A:$A,[4]TD90D!$CX:$CX,"",0,1) | Q74: =_xlfn.XLOOKUP(A:A,[4]TD90D!$A:$A,[4]TD90D!$DA:$DA,"",0,1) | R74: =P74/C74 -> #VALUE! | S74: =_xlfn.XLOOKUP(A:A,'[4]TD90D PZAS'!$A:$A,'[4]TD90D PZAS'!$CW:$CW,"",0,1) | T74: =_xlfn.XLOOKUP(A:A,'[4]TD90D PZAS'!$A:$A,'[4]TD90D PZAS'!$CX:$CX,"",0,1) | U74: =_xlfn.XLOOKUP(A:A,'[4]TD90D PZAS'!$A:$A,'[4]TD90D PZAS'!$DA:$DA,"",0,1)
A75: 29024 | B75: =_xlfn.XLOOKUP(A:A,[1]Hoja1!$C:$C,[1]Hoja1!$D:$D,"",0,1) -> PELO DE GATO | C75: 5 | D75: =_xlfn.XLOOKUP(A:A,[2]Hoja1!$C:$C,[2]Hoja1!$H:$H,"",0,1) -> 309.48 | E75: =_xlfn.XLOOKUP(A:A,[1]Hoja1!$C:$C,[1]Hoja1!$H:$H,"",0,1) -> 237.93 | F75: =_xlfn.XLOOKUP(A:A,TD!A:A,TD!EC:EC,"",0,1) -> 1.6 | G75: =INT(F75) -> 1 | H75: =D75*$G$5 -> 928.44 | I75: =E75*$G$5 -> 713.79 | J75: 29024 | K75: =_xlfn.XLOOKUP(J:J,'[3]FILTROS 2'!$A:$A,'[3]FILTROS 2'!$E:$E,"",0,1) -> PASTA RELLENADORA | O75: =_xlfn.XLOOKUP(A:A,[4]TD90D!$A:$A,[4]TD90D!$CW:$CW,"",0,1) -> 4 | P75: =_xlfn.XLOOKUP(A:A,[4]TD90D!$A:$A,[4]TD90D!$CX:$CX,"",0,1) -> 1 | Q75: =_xlfn.XLOOKUP(A:A,[4]TD90D!$A:$A,[4]TD90D!$DA:$DA,"",0,1) -> 0 | R75: =P75/C75 -> 0.2 | S75: =_xlfn.XLOOKUP(A:A,'[4]TD90D PZAS'!$A:$A,'[4]TD90D PZAS'!$CW:$CW,"",0,1) -> 2 | T75: =_xlfn.XLOOKUP(A:A,'[4]TD90D PZAS'!$A:$A,'[4]TD90D PZAS'!$CX:$CX,"",0,1) -> 1 | U75: =_xlfn.XLOOKUP(A:A,'[4]TD90D PZAS'!$A:$A,'[4]TD90D PZAS'!$DA:$DA,"",0,1) -> 0
A76: BAG-10885 | B76: =_xlfn.XLOOKUP(A:A,[1]Hoja1!$C:$C,[1]Hoja1!$D:$D,"",0,1) -> BARNIZ GLOSI ALQUI CAOBA | C76: 4 | D76: =_xlfn.XLOOKUP(A:A,[2]Hoja1!$C:$C,[2]Hoja1!$H:$H,"",0,1) -> 106.03 | E76: =_xlfn.XLOOKUP(A:A,[1]Hoja1!$C:$C,[1]Hoja1!$H:$H,"",0,1) -> 83.62 | F76: =_xlfn.XLOOKUP(A:A,TD!A:A,TD!EC:EC,"",0,1) -> 2.25 | G76: =INT(F76) -> 2 | H76: =D76*$G$5 -> 318.09 | I76: =E76*$G$5 -> 250.86 | J76: BAG-10885 | K76: =_xlfn.XLOOKUP(J:J,'[3]FILTROS 2'!$A:$A,'[3]FILTROS 2'!$E:$E,"",0,1) -> BARNIZ ALQUIDALICO GLOSI 3-1 | O76: =_xlfn.XLOOKUP(A:A,[4]TD90D!$A:$A,[4]TD90D!$CW:$CW,"",0,1) -> 5 | P76: =_xlfn.XLOOKUP(A:A,[4]TD90D!$A:$A,[4]TD90D!$CX:$CX,"",0,1) -> 2 | Q76: =_xlfn.XLOOKUP(A:A,[4]TD90D!$A:$A,[4]TD90D!$DA:$DA,"",0,1) -> 0 | R76: =P76/C76 -> 0.5 | S76: =_xlfn.XLOOKUP(A:A,'[4]TD90D PZAS'!$A:$A,'[4]TD90D PZAS'!$CW:$CW,"",0,1) -> 12 | T76: =_xlfn.XLOOKUP(A:A,'[4]TD90D PZAS'!$A:$A,'[4]TD90D PZAS'!$CX:$CX,"",0,1) -> 2 | U76: =_xlfn.XLOOKUP(A:A,'[4]TD90D PZAS'!$A:$A,'[4]TD90D PZAS'!$DA:$DA,"",0,1) -> 0
A77: 28016 | B77: =_xlfn.XLOOKUP(A:A,[1]Hoja1!$C:$C,[1]Hoja1!$D:$D,"",0,1) -> BRILLON BLANCO MATE | C77: 4 | D77: =_xlfn.XLOOKUP(A:A,[2]Hoja1!$C:$C,[2]Hoja1!$H:$H,"",0,1) -> 58.62 | E77: =_xlfn.XLOOKUP(A:A,[1]Hoja1!$C:$C,[1]Hoja1!$H:$H,"",0,1) -> 43.97 | F77: =_xlfn.XLOOKUP(A:A,TD!A:A,TD!EC:EC,"",0,1) -> 4 | G77: =INT(F77) -> 4 | H77: =D77*$G$5 -> 175.86 | I77: =E77*$G$5 -> 131.91 | J77: 28016 | K77: =_xlfn.XLOOKUP(J:J,'[3]FILTROS 2'!$A:$A,'[3]FILTROS 2'!$E:$E,"",0,1) -> ESMALTE - BRILLON | O77: =_xlfn.XLOOKUP(A:A,[4]TD90D!$A:$A,[4]TD90D!$CW:$CW,"",0,1) -> 4 | P77: =_xlfn.XLOOKUP(A:A,[4]TD90D!$A:$A,[4]TD90D!$CX:$CX,"",0,1) -> 2 | Q77: =_xlfn.XLOOKUP(A:A,[4]TD90D!$A:$A,[4]TD90D!$DA:$DA,"",0,1) -> 0 | R77: =P77/C77 -> 0.5 | S77: =_xlfn.XLOOKUP(A:A,'[4]TD90D PZAS'!$A:$A,'[4]TD90D PZAS'!$CW:$CW,"",0,1) -> 6 | T77: =_xlfn.XLOOKUP(A:A,'[4]TD90D PZAS'!$A:$A,'[4]TD90D PZAS'!$CX:$CX,"",0,1) -> 2 | U77: =_xlfn.XLOOKUP(A:A,'[4]TD90D PZAS'!$A:$A,'[4]TD90D PZAS'!$DA:$DA,"",0,1) -> 0
A78: SRG-10006 | B78: =_xlfn.XLOOKUP(A:A,[1]Hoja1!$C:$C,[1]Hoja1!$D:$D,"",0,1) -> ESMALTE GLOSI SR BLANCO | C78: 4 | D78: =_xlfn.XLOOKUP(A:A,[2]Hoja1!$C:$C,[2]Hoja1!$H:$H,"",0,1) -> 81.03 | E78: =_xlfn.XLOOKUP(A:A,[1]Hoja1!$C:$C,[1]Hoja1!$H:$H,"",0,1) -> 66.38 | F78: =_xlfn.XLOOKUP(A:A,TD!A:A,TD!EC:EC,"",0,1) -> 7.5 | G78: =INT(F78) -> 7 | H78: =D78*$G$5 -> 243.09 | I78: =E78*$G$5 -> 199.14 | J78: SRG-10006 | K78: =_xlfn.XLOOKUP(J:J,'[3]FILTROS 2'!$A:$A,'[3]FILTROS 2'!$E:$E,"",0,1) -> ESMALTE - GLOSI SECADO RAPIDO | O78: =_xlfn.XLOOKUP(A:A,[4]TD90D!$A:$A,[4]TD90D!$CW:$CW,"",0,1) -> 2 | P78: =_xlfn.XLOOKUP(A:A,[4]TD90D!$A:$A,[4]TD90D!$CX:$CX,"",0,1) -> 1 | Q78: =_xlfn.XLOOKUP(A:A,[4]TD90D!$A:$A,[4]TD90D!$DA:$DA,"",0,1) -> 0 | R78: =P78/C78 -> 0.25 | S78: =_xlfn.XLOOKUP(A:A,'[4]TD90D PZAS'!$A:$A,'[4]TD90D PZAS'!$CW:$CW,"",0,1) -> 24 | T78: =_xlfn.XLOOKUP(A:A,'[4]TD90D PZAS'!$A:$A,'[4]TD90D PZAS'!$CX:$CX,"",0,1) -> 1 | U78: =_xlfn.XLOOKUP(A:A,'[4]TD90D PZAS'!$A:$A,'[4]TD90D PZAS'!$DA:$DA,"",0,1) -> 0
A79: 28646 | B79: =_xlfn.XLOOKUP(A:A,[1]Hoja1!$C:$C,[1]Hoja1!$D:$D,"",0,1) -> BRILLON AZUL AGUA | C79: 4 | D79: =_xlfn.XLOOKUP(A:A,[2]Hoja1!$C:$C,[2]Hoja1!$H:$H,"",0,1) -> 58.62 | E79: =_xlfn.XLOOKUP(A:A,[1]Hoja1!$C:$C,[1]Hoja1!$H:$H,"",0,1) -> 43.97 | F79: =_xlfn.XLOOKUP(A:A,TD!A:A,TD!EC:EC,"",0,1) -> 10.5 | G79: =INT(F79) -> 10 | H79: =D79*$G$5 -> 175.86 | I79: =E79*$G$5 -> 131.91 | J79: 28646 | K79: =_xlfn.XLOOKUP(J:J,'[3]FILTROS 2'!$A:$A,'[3]FILTROS 2'!$E:$E,"",0,1) -> ESMALTE - BRILLON | O79: =_xlfn.XLOOKUP(A:A,[4]TD90D!$A:$A,[4]TD90D!$CW:$CW,"",0,1) | P79: =_xlfn.XLOOKUP(A:A,[4]TD90D!$A:$A,[4]TD90D!$CX:$CX,"",0,1) | Q79: =_xlfn.XLOOKUP(A:A,[4]TD90D!$A:$A,[4]TD90D!$DA:$DA,"",0,1) | R79: =P79/C79 -> #VALUE! | S79: =_xlfn.XLOOKUP(A:A,'[4]TD90D PZAS'!$A:$A,'[4]TD90D PZAS'!$CW:$CW,"",0,1) | T79: =_xlfn.XLOOKUP(A:A,'[4]TD90D PZAS'!$A:$A,'[4]TD90D PZAS'!$CX:$CX,"",0,1) | U79: =_xlfn.XLOOKUP(A:A,'[4]TD90D PZAS'!$A:$A,'[4]TD90D PZAS'!$DA:$DA,"",0,1)
A80: 2358 | B80: =_xlfn.XLOOKUP(A:A,[1]Hoja1!$C:$C,[1]Hoja1!$D:$D,"",0,1) -> AEROSOL CAFE CHOCOLATE | C80: 4 | D80: =_xlfn.XLOOKUP(A:A,[2]Hoja1!$C:$C,[2]Hoja1!$H:$H,"",0,1) -> 55.17 | E80: =_xlfn.XLOOKUP(A:A,[1]Hoja1!$C:$C,[1]Hoja1!$H:$H,"",0,1) -> 41.38 | F80: =_xlfn.XLOOKUP(A:A,TD!A:A,TD!EC:EC,"",0,1) -> 6 | G80: =INT(F80) -> 6 | H80: =D80*$G$5 -> 165.51 | I80: =E80*$G$5 -> 124.14 | J80: 2358 | K80: =_xlfn.XLOOKUP(J:J,'[3]FILTROS 2'!$A:$A,'[3]FILTROS 2'!$E:$E,"",0,1) -> AEROSOLES PRISA | O80: =_xlfn.XLOOKUP(A:A,[4]TD90D!$A:$A,[4]TD90D!$CW:$CW,"",0,1) -> 5 | P80: =_xlfn.XLOOKUP(A:A,[4]TD90D!$A:$A,[4]TD90D!$CX:$CX,"",0,1) -> 2 | Q80: =_xlfn.XLOOKUP(A:A,[4]TD90D!$A:$A,[4]TD90D!$DA:$DA,"",0,1) -> 0 | R80: =P80/C80 -> 0.5 | S80: =_xlfn.XLOOKUP(A:A,'[4]TD90D PZAS'!$A:$A,'[4]TD90D PZAS'!$CW:$CW,"",0,1) -> 18 | T80: =_xlfn.XLOOKUP(A:A,'[4]TD90D PZAS'!$A:$A,'[4]TD90D PZAS'!$CX:$CX,"",0,1) -> 2 | U80: =_xlfn.XLOOKUP(A:A,'[4]TD90D PZAS'!$A:$A,'[4]TD90D PZAS'!$DA:$DA,"",0,1) -> 0
A81: 28914 | B81: =_xlfn.XLOOKUP(A:A,[1]Hoja1!$C:$C,[1]Hoja1!$D:$D,"",0,1) -> BRILLON DORADO | C81: 4 | D81: =_xlfn.XLOOKUP(A:A,[2]Hoja1!$C:$C,[2]Hoja1!$H:$H,"",0,1) -> 150.86 | E81: =_xlfn.XLOOKUP(A:A,[1]Hoja1!$C:$C,[1]Hoja1!$H:$H,"",0,1) -> 112.93 | F81: =_xlfn.XLOOKUP(A:A,TD!A:A,TD!EC:EC,"",0,1) -> 3.25 | G81: =INT(F81) -> 3 | H81: =D81*$G$5 -> 452.58 | I81: =E81*$G$5 -> 338.79 | J81: 28914 | K81: =_xlfn.XLOOKUP(J:J,'[3]FILTROS 2'!$A:$A,'[3]FILTROS 2'!$E:$E,"",0,1) -> ESMALTE - BRILLON | O81: =_xlfn.XLOOKUP(A:A,[4]TD90D!$A:$A,[4]TD90D!$CW:$CW,"",0,1) | P81: =_xlfn.XLOOKUP(A:A,[4]TD90D!$A:$A,[4]TD90D!$CX:$CX,"",0,1) | Q81: =_xlfn.XLOOKUP(A:A,[4]TD90D!$A:$A,[4]TD90D!$DA:$DA,"",0,1) | R81: =P81/C81 -> #VALUE! | S81: =_xlfn.XLOOKUP(A:A,'[4]TD90D PZAS'!$A:$A,'[4]TD90D PZAS'!$CW:$CW,"",0,1) | T81: =_xlfn.XLOOKUP(A:A,'[4]TD90D PZAS'!$A:$A,'[4]TD90D PZAS'!$CX:$CX,"",0,1) | U81: =_xlfn.XLOOKUP(A:A,'[4]TD90D PZAS'!$A:$A,'[4]TD90D PZAS'!$DA:$DA,"",0,1)
A82: BAG-10895 | B82: =_xlfn.XLOOKUP(A:A,[1]Hoja1!$C:$C,[1]Hoja1!$D:$D,"",0,1) -> BARNIZ GLOSI ALQUI NOGAL | C82: 4 | D82: =_xlfn.XLOOKUP(A:A,[2]Hoja1!$C:$C,[2]Hoja1!$H:$H,"",0,1) -> 106.03 | E82: =_xlfn.XLOOKUP(A:A,[1]Hoja1!$C:$C,[1]Hoja1!$H:$H,"",0,1) -> 83.62 | F82: =_xlfn.XLOOKUP(A:A,TD!A:A,TD!EC:EC,"",0,1) -> 2.25 | G82: =INT(F82) -> 2 | H82: =D82*$G$5 -> 318.09 | I82: =E82*$G$5 -> 250.86 | J82: BAG-10895 | K82: =_xlfn.XLOOKUP(J:J,'[3]FILTROS 2'!$A:$A,'[3]FILTROS 2'!$E:$E,"",0,1) -> BARNIZ ALQUIDALICO GLOSI 3-1 | O82: =_xlfn.XLOOKUP(A:A,[4]TD90D!$A:$A,[4]TD90D!$CW:$CW,"",0,1) -> 2 | P82: =_xlfn.XLOOKUP(A:A,[4]TD90D!$A:$A,[4]TD90D!$CX:$CX,"",0,1) -> 1 | Q82: =_xlfn.XLOOKUP(A:A,[4]TD90D!$A:$A,[4]TD90D!$DA:$DA,"",0,1) -> 0 | R82: =P82/C82 -> 0.25 | S82: =_xlfn.XLOOKUP(A:A,'[4]TD90D PZAS'!$A:$A,'[4]TD90D PZAS'!$CW:$CW,"",0,1) -> 3 | T82: =_xlfn.XLOOKUP(A:A,'[4]TD90D PZAS'!$A:$A,'[4]TD90D PZAS'!$CX:$CX,"",0,1) -> 1 | U82: =_xlfn.XLOOKUP(A:A,'[4]TD90D PZAS'!$A:$A,'[4]TD90D PZAS'!$DA:$DA,"",0,1) -> 0
A83: 28965 | B83: =_xlfn.XLOOKUP(A:A,[1]Hoja1!$C:$C,[1]Hoja1!$D:$D,"",0,1) -> BRILLON NEGRO MATE | C83: 4 | D83: =_xlfn.XLOOKUP(A:A,[2]Hoja1!$C:$C,[2]Hoja1!$H:$H,"",0,1) -> 90.52 | E83: =_xlfn.XLOOKUP(A:A,[1]Hoja1!$C:$C,[1]Hoja1!$H:$H,"",0,1) -> 67.24 | F83: =_xlfn.XLOOKUP(A:A,TD!A:A,TD!EC:EC,"",0,1) -> 4.5 | G83: =INT(F83) -> 4 | H83: =D83*$G$5 -> 271.56 | I83: =E83*$G$5 -> 201.72 | J83: 28965 | K83: =_xlfn.XLOOKUP(J:J,'[3]FILTROS 2'!$A:$A,'[3]FILTROS 2'!$E:$E,"",0,1) -> ESMALTE - BRILLON | O83: =_xlfn.XLOOKUP(A:A,[4]TD90D!$A:$A,[4]TD90D!$CW:$CW,"",0,1) -> 3 | P83: =_xlfn.XLOOKUP(A:A,[4]TD90D!$A:$A,[4]TD90D!$CX:$CX,"",0,1) -> 1 | Q83: =_xlfn.XLOOKUP(A:A,[4]TD90D!$A:$A,[4]TD90D!$DA:$DA,"",0,1) -> 0 | R83: =P83/C83 -> 0.25 | S83: =_xlfn.XLOOKUP(A:A,'[4]TD90D PZAS'!$A:$A,'[4]TD90D PZAS'!$CW:$CW,"",0,1) -> 12 | T83: =_xlfn.XLOOKUP(A:A,'[4]TD90D PZAS'!$A:$A,'[4]TD90D PZAS'!$CX:$CX,"",0,1) -> 1 | U83: =_xlfn.XLOOKUP(A:A,'[4]TD90D PZAS'!$A:$A,'[4]TD90D PZAS'!$DA:$DA,"",0,1) -> 0
A84: SRG-10996 | B84: =_xlfn.XLOOKUP(A:A,[1]Hoja1!$C:$C,[1]Hoja1!$D:$D,"",0,1) -> ESMALTE GLOSI SR NEGRO BRILLANTE | C84: 4 | D84: =_xlfn.XLOOKUP(A:A,[2]Hoja1!$C:$C,[2]Hoja1!$H:$H,"",0,1) -> 81.03 | E84: =_xlfn.XLOOKUP(A:A,[1]Hoja1!$C:$C,[1]Hoja1!$H:$H,"",0,1) -> 66.38 | F84: =_xlfn.XLOOKUP(A:A,TD!A:A,TD!EC:EC,"",0,1) -> 7.5 | G84: =INT(F84) -> 7 | H84: =D84*$G$5 -> 243.09 | I84: =E84*$G$5 -> 199.14 | J84: SRG-10996 | K84: =_xlfn.XLOOKUP(J:J,'[3]FILTROS 2'!$A:$A,'[3]FILTROS 2'!$E:$E,"",0,1) -> ESMALTE - GLOSI SECADO RAPIDO | O84: =_xlfn.XLOOKUP(A:A,[4]TD90D!$A:$A,[4]TD90D!$CW:$CW,"",0,1) -> 2 | P84: =_xlfn.XLOOKUP(A:A,[4]TD90D!$A:$A,[4]TD90D!$CX:$CX,"",0,1) -> 1 | Q84: =_xlfn.XLOOKUP(A:A,[4]TD90D!$A:$A,[4]TD90D!$DA:$DA,"",0,1) -> 0 | R84: =P84/C84 -> 0.25 | S84: =_xlfn.XLOOKUP(A:A,'[4]TD90D PZAS'!$A:$A,'[4]TD90D PZAS'!$CW:$CW,"",0,1) -> 24 | T84: =_xlfn.XLOOKUP(A:A,'[4]TD90D PZAS'!$A:$A,'[4]TD90D PZAS'!$CX:$CX,"",0,1) -> 1 | U84: =_xlfn.XLOOKUP(A:A,'[4]TD90D PZAS'!$A:$A,'[4]TD90D PZAS'!$DA:$DA,"",0,1) -> 0
A85: 28983 | B85: =_xlfn.XLOOKUP(A:A,[1]Hoja1!$C:$C,[1]Hoja1!$D:$D,"",0,1) -> BRILLON NEGRO | C85: 4 | D85: =_xlfn.XLOOKUP(A:A,[2]Hoja1!$C:$C,[2]Hoja1!$H:$H,"",0,1) -> 533.62 | E85: =_xlfn.XLOOKUP(A:A,[1]Hoja1!$C:$C,[1]Hoja1!$H:$H,"",0,1) -> 401.72 | F85: =_xlfn.XLOOKUP(A:A,TD!A:A,TD!EC:EC,"",0,1) -> 2.25 | G85: =INT(F85) -> 2 | H85: =D85*$G$5 -> 1600.86 | I85: =E85*$G$5 -> 1205.16 | J85: 28983 | K85: =_xlfn.XLOOKUP(J:J,'[3]FILTROS 2'!$A:$A,'[3]FILTROS 2'!$E:$E,"",0,1) -> ESMALTE - BRILLON | O85: =_xlfn.XLOOKUP(A:A,[4]TD90D!$A:$A,[4]TD90D!$CW:$CW,"",0,1) -> 6 | P85: =_xlfn.XLOOKUP(A:A,[4]TD90D!$A:$A,[4]TD90D!$CX:$CX,"",0,1) -> 2 | Q85: =_xlfn.XLOOKUP(A:A,[4]TD90D!$A:$A,[4]TD90D!$DA:$DA,"",0,1) -> 0 | R85: =P85/C85 -> 0.5 | S85: =_xlfn.XLOOKUP(A:A,'[4]TD90D PZAS'!$A:$A,'[4]TD90D PZAS'!$CW:$CW,"",0,1) -> 14 | T85: =_xlfn.XLOOKUP(A:A,'[4]TD90D PZAS'!$A:$A,'[4]TD90D PZAS'!$CX:$CX,"",0,1) -> 2 | U85: =_xlfn.XLOOKUP(A:A,'[4]TD90D PZAS'!$A:$A,'[4]TD90D PZAS'!$DA:$DA,"",0,1) -> 0
A86: 29484 | B86: =_xlfn.XLOOKUP(A:A,[1]Hoja1!$C:$C,[1]Hoja1!$D:$D,"",0,1) -> PLASTE GRIS CLARO | C86: 4 | D86: =_xlfn.XLOOKUP(A:A,[2]Hoja1!$C:$C,[2]Hoja1!$H:$H,"",0,1) -> 268.97 | E86: =_xlfn.XLOOKUP(A:A,[1]Hoja1!$C:$C,[1]Hoja1!$H:$H,"",0,1) -> 200 | F86: =_xlfn.XLOOKUP(A:A,TD!A:A,TD!EC:EC,"",0,1) -> -1.5 | G86: =INT(F86) -> -2 | H86: =D86*$G$5 -> 806.91 | I86: =E86*$G$5 -> 600 | J86: 29484 | K86: =_xlfn.XLOOKUP(J:J,'[3]FILTROS 2'!$A:$A,'[3]FILTROS 2'!$E:$E,"",0,1) -> PLASTE | O86: =_xlfn.XLOOKUP(A:A,[4]TD90D!$A:$A,[4]TD90D!$CW:$CW,"",0,1) -> 3 | P86: =_xlfn.XLOOKUP(A:A,[4]TD90D!$A:$A,[4]TD90D!$CX:$CX,"",0,1) -> 1 | Q86: =_xlfn.XLOOKUP(A:A,[4]TD90D!$A:$A,[4]TD90D!$DA:$DA,"",0,1) -> 0 | R86: =P86/C86 -> 0.25 | S86: =_xlfn.XLOOKUP(A:A,'[4]TD90D PZAS'!$A:$A,'[4]TD90D PZAS'!$CW:$CW,"",0,1) -> -2 | T86: =_xlfn.XLOOKUP(A:A,'[4]TD90D PZAS'!$A:$A,'[4]TD90D PZAS'!$CX:$CX,"",0,1) -> 0 | U86: =_xlfn.XLOOKUP(A:A,'[4]TD90D PZAS'!$A:$A,'[4]TD90D PZAS'!$DA:$DA,"",0,1) -> 0
A87: 29501 | B87: =_xlfn.XLOOKUP(A:A,[1]Hoja1!$C:$C,[1]Hoja1!$D:$D,"",0,1) -> PULIMENTO BLANCO 1968 | C87: 4 | D87: =_xlfn.XLOOKUP(A:A,[2]Hoja1!$C:$C,[2]Hoja1!$H:$H,"",0,1) -> 3031.03 | E87: =_xlfn.XLOOKUP(A:A,[1]Hoja1!$C:$C,[1]Hoja1!$H:$H,"",0,1) -> 2368.1 | F87: =_xlfn.XLOOKUP(A:A,TD!A:A,TD!EC:EC,"",0,1) -> 1.5 | G87: =INT(F87) -> 1 | H87: =D87*$G$5 -> 9093.09 | I87: =E87*$G$5 -> 7104.3 | J87: 29501 | K87: =_xlfn.XLOOKUP(J:J,'[3]FILTROS 2'!$A:$A,'[3]FILTROS 2'!$E:$E,"",0,1) -> PULIMENTO | O87: =_xlfn.XLOOKUP(A:A,[4]TD90D!$A:$A,[4]TD90D!$CW:$CW,"",0,1) -> 2 | P87: =_xlfn.XLOOKUP(A:A,[4]TD90D!$A:$A,[4]TD90D!$CX:$CX,"",0,1) -> 1 | Q87: =_xlfn.XLOOKUP(A:A,[4]TD90D!$A:$A,[4]TD90D!$DA:$DA,"",0,1) -> 0 | R87: =P87/C87 -> 0.25 | S87: =_xlfn.XLOOKUP(A:A,'[4]TD90D PZAS'!$A:$A,'[4]TD90D PZAS'!$CW:$CW,"",0,1) -> 3 | T87: =_xlfn.XLOOKUP(A:A,'[4]TD90D PZAS'!$A:$A,'[4]TD90D PZAS'!$CX:$CX,"",0,1) -> 1 | U87: =_xlfn.XLOOKUP(A:A,'[4]TD90D PZAS'!$A:$A,'[4]TD90D PZAS'!$DA:$DA,"",0,1) -> 0
A88: 28644 | B88: =_xlfn.XLOOKUP(A:A,[1]Hoja1!$C:$C,[1]Hoja1!$D:$D,"",0,1) -> BRILLON AZUL AGUA | C88: 3 | D88: =_xlfn.XLOOKUP(A:A,[2]Hoja1!$C:$C,[2]Hoja1!$H:$H,"",0,1) -> 150.86 | E88: =_xlfn.XLOOKUP(A:A,[1]Hoja1!$C:$C,[1]Hoja1!$H:$H,"",0,1) -> 112.93 | F88: =_xlfn.XLOOKUP(A:A,TD!A:A,TD!EC:EC,"",0,1) -> 3 | G88: =INT(F88) -> 3 | H88: =D88*$G$5 -> 452.58 | I88: =E88*$G$5 -> 338.79 | J88: 28644 | K88: =_xlfn.XLOOKUP(J:J,'[3]FILTROS 2'!$A:$A,'[3]FILTROS 2'!$E:$E,"",0,1) -> ESMALTE - BRILLON | O88: =_xlfn.XLOOKUP(A:A,[4]TD90D!$A:$A,[4]TD90D!$CW:$CW,"",0,1) | P88: =_xlfn.XLOOKUP(A:A,[4]TD90D!$A:$A,[4]TD90D!$CX:$CX,"",0,1) | Q88: =_xlfn.XLOOKUP(A:A,[4]TD90D!$A:$A,[4]TD90D!$DA:$DA,"",0,1) | R88: =P88/C88 -> #VALUE! | S88: =_xlfn.XLOOKUP(A:A,'[4]TD90D PZAS'!$A:$A,'[4]TD90D PZAS'!$CW:$CW,"",0,1) | T88: =_xlfn.XLOOKUP(A:A,'[4]TD90D PZAS'!$A:$A,'[4]TD90D PZAS'!$CX:$CX,"",0,1) | U88: =_xlfn.XLOOKUP(A:A,'[4]TD90D PZAS'!$A:$A,'[4]TD90D PZAS'!$DA:$DA,"",0,1)
A89: ES-47024 | B89: =_xlfn.XLOOKUP(A:A,[1]Hoja1!$C:$C,[1]Hoja1!$D:$D,"",0,1) -> RESANADOR PINO BA H11 | C89: 3 | D89: =_xlfn.XLOOKUP(A:A,[2]Hoja1!$C:$C,[2]Hoja1!$H:$H,"",0,1) -> 177.59 | E89: =_xlfn.XLOOKUP(A:A,[1]Hoja1!$C:$C,[1]Hoja1!$H:$H,"",0,1) -> 163.79 | F89: =_xlfn.XLOOKUP(A:A,TD!A:A,TD!EC:EC,"",0,1) -> 0.66666667 | G89: =INT(F89) -> 0 | H89: =D89*$G$5 -> 532.77 | I89: =E89*$G$5 -> 491.37 | J89: ES-47024 | K89: =_xlfn.XLOOKUP(J:J,'[3]FILTROS 2'!$A:$A,'[3]FILTROS 2'!$E:$E,"",0,1) -> TAPAPOROS Y RESANES PARA MADER | O89: =_xlfn.XLOOKUP(A:A,[4]TD90D!$A:$A,[4]TD90D!$CW:$CW,"",0,1) -> 3 | P89: =_xlfn.XLOOKUP(A:A,[4]TD90D!$A:$A,[4]TD90D!$CX:$CX,"",0,1) -> 1 | Q89: =_xlfn.XLOOKUP(A:A,[4]TD90D!$A:$A,[4]TD90D!$DA:$DA,"",0,1) -> 0 | R89: =P89/C89 -> 0.33333333 | S89: =_xlfn.XLOOKUP(A:A,'[4]TD90D PZAS'!$A:$A,'[4]TD90D PZAS'!$CW:$CW,"",0,1) -> 2 | T89: =_xlfn.XLOOKUP(A:A,'[4]TD90D PZAS'!$A:$A,'[4]TD90D PZAS'!$CX:$CX,"",0,1) -> 1 | U89: =_xlfn.XLOOKUP(A:A,'[4]TD90D PZAS'!$A:$A,'[4]TD90D PZAS'!$DA:$DA,"",0,1) -> 0
A90: 28935 | B90: =_xlfn.XLOOKUP(A:A,[1]Hoja1!$C:$C,[1]Hoja1!$D:$D,"",0,1) -> BRILLON GRIS | C90: 3 | D90: =_xlfn.XLOOKUP(A:A,[2]Hoja1!$C:$C,[2]Hoja1!$H:$H,"",0,1) -> 90.52 | E90: =_xlfn.XLOOKUP(A:A,[1]Hoja1!$C:$C,[1]Hoja1!$H:$H,"",0,1) -> 67.24 | F90: =_xlfn.XLOOKUP(A:A,TD!A:A,TD!EC:EC,"",0,1) -> 4 | G90: =INT(F90) -> 4 | H90: =D90*$G$5 -> 271.56 | I90: =E90*$G$5 -> 201.72 | J90: 28935 | K90: =_xlfn.XLOOKUP(J:J,'[3]FILTROS 2'!$A:$A,'[3]FILTROS 2'!$E:$E,"",0,1) -> ESMALTE - BRILLON | O90: =_xlfn.XLOOKUP(A:A,[4]TD90D!$A:$A,[4]TD90D!$CW:$CW,"",0,1) | P90: =_xlfn.XLOOKUP(A:A,[4]TD90D!$A:$A,[4]TD90D!$CX:$CX,"",0,1) | Q90: =_xlfn.XLOOKUP(A:A,[4]TD90D!$A:$A,[4]TD90D!$DA:$DA,"",0,1) | R90: =P90/C90 -> #VALUE! | S90: =_xlfn.XLOOKUP(A:A,'[4]TD90D PZAS'!$A:$A,'[4]TD90D PZAS'!$CW:$CW,"",0,1) | T90: =_xlfn.XLOOKUP(A:A,'[4]TD90D PZAS'!$A:$A,'[4]TD90D PZAS'!$CX:$CX,"",0,1) | U90: =_xlfn.XLOOKUP(A:A,'[4]TD90D PZAS'!$A:$A,'[4]TD90D PZAS'!$DA:$DA,"",0,1)
A91: 28654 | B91: =_xlfn.XLOOKUP(A:A,[1]Hoja1!$C:$C,[1]Hoja1!$D:$D,"",0,1) -> BRILLON AZUL IRIS | C91: 3 | D91: =_xlfn.XLOOKUP(A:A,[2]Hoja1!$C:$C,[2]Hoja1!$H:$H,"",0,1) -> 150.86 | E91: =_xlfn.XLOOKUP(A:A,[1]Hoja1!$C:$C,[1]Hoja1!$H:$H,"",0,1) -> 112.93 | F91: =_xlfn.XLOOKUP(A:A,TD!A:A,TD!EC:EC,"",0,1) -> 1 | G91: =INT(F91) -> 1 | H91: =D91*$G$5 -> 452.58 | I91: =E91*$G$5 -> 338.79 | J91: 28654 | K91: =_xlfn.XLOOKUP(J:J,'[3]FILTROS 2'!$A:$A,'[3]FILTROS 2'!$E:$E,"",0,1) -> ESMALTE - BRILLON | O91: =_xlfn.XLOOKUP(A:A,[4]TD90D!$A:$A,[4]TD90D!$CW:$CW,"",0,1) -> 2 | P91: =_xlfn.XLOOKUP(A:A,[4]TD90D!$A:$A,[4]TD90D!$CX:$CX,"",0,1) -> 1 | Q91: =_xlfn.XLOOKUP(A:A,[4]TD90D!$A:$A,[4]TD90D!$DA:$DA,"",0,1) -> 0 | R91: =P91/C91 -> 0.33333333 | S91: =_xlfn.XLOOKUP(A:A,'[4]TD90D PZAS'!$A:$A,'[4]TD90D PZAS'!$CW:$CW,"",0,1) -> 0 | T91: =_xlfn.XLOOKUP(A:A,'[4]TD90D PZAS'!$A:$A,'[4]TD90D PZAS'!$CX:$CX,"",0,1) -> 0 | U91: =_xlfn.XLOOKUP(A:A,'[4]TD90D PZAS'!$A:$A,'[4]TD90D PZAS'!$DA:$DA,"",0,1) -> 0
A92: 25003 | B92: =_xlfn.XLOOKUP(A:A,[1]Hoja1!$C:$C,[1]Hoja1!$D:$D,"",0,1) -> ESM. ACRILICO BLANCO 501 | C92: 3 | D92: =_xlfn.XLOOKUP(A:A,[2]Hoja1!$C:$C,[2]Hoja1!$H:$H,"",0,1) -> 1149.14 | E92: =_xlfn.XLOOKUP(A:A,[1]Hoja1!$C:$C,[1]Hoja1!$H:$H,"",0,1) -> 821.55 | F92: =_xlfn.XLOOKUP(A:A,TD!A:A,TD!EC:EC,"",0,1) -> 0.33333333 | G92: =INT(F92) -> 0 | H92: =D92*$G$5 -> 3447.42 | I92: =E92*$G$5 -> 2464.65 | J92: 25003 | K92: =_xlfn.XLOOKUP(J:J,'[3]FILTROS 2'!$A:$A,'[3]FILTROS 2'!$E:$E,"",0,1) -> ESMALTE ACRILICO | O92: =_xlfn.XLOOKUP(A:A,[4]TD90D!$A:$A,[4]TD90D!$CW:$CW,"",0,1) -> 3 | P92: =_xlfn.XLOOKUP(A:A,[4]TD90D!$A:$A,[4]TD90D!$CX:$CX,"",0,1) -> 1 | Q92: =_xlfn.XLOOKUP(A:A,[4]TD90D!$A:$A,[4]TD90D!$DA:$DA,"",0,1) -> 0 | R92: =P92/C92 -> 0.33333333 | S92: =_xlfn.XLOOKUP(A:A,'[4]TD90D PZAS'!$A:$A,'[4]TD90D PZAS'!$CW:$CW,"",0,1) -> 1 | T92: =_xlfn.XLOOKUP(A:A,'[4]TD90D PZAS'!$A:$A,'[4]TD90D PZAS'!$CX:$CX,"",0,1) -> 1 | U92: =_xlfn.XLOOKUP(A:A,'[4]TD90D PZAS'!$A:$A,'[4]TD90D PZAS'!$DA:$DA,"",0,1) -> 0
A93: VG-30211 | B93: =_xlfn.XLOOKUP(A:A,[1]Hoja1!$C:$C,[1]Hoja1!$D:$D,"",0,1) -> VINILICA GLOSI MARFIL 3A | C93: 3 | D93: =_xlfn.XLOOKUP(A:A,[2]Hoja1!$C:$C,[2]Hoja1!$H:$H,"",0,1) -> 874.14 | E93: =_xlfn.XLOOKUP(A:A,[1]Hoja1!$C:$C,[1]Hoja1!$H:$H,"",0,1) -> 656.9 | F93: =_xlfn.XLOOKUP(A:A,TD!A:A,TD!EC:EC,"",0,1) -> 0.66666667 | G93: =INT(F93) -> 0 | H93: =D93*$G$5 -> 2622.42 | I93: =E93*$G$5 -> 1970.7 | J93: VG-30211 | K93: =_xlfn.XLOOKUP(J:J,'[3]FILTROS 2'!$A:$A,'[3]FILTROS 2'!$E:$E,"",0,1) -> VINILICA - GLOSI 3 AÑOS | O93: =_xlfn.XLOOKUP(A:A,[4]TD90D!$A:$A,[4]TD90D!$CW:$CW,"",0,1) -> 2 | P93: =_xlfn.XLOOKUP(A:A,[4]TD90D!$A:$A,[4]TD90D!$CX:$CX,"",0,1) -> 1 | Q93: =_xlfn.XLOOKUP(A:A,[4]TD90D!$A:$A,[4]TD90D!$DA:$DA,"",0,1) -> 0 | R93: =P93/C93 -> 0.33333333 | S93: =_xlfn.XLOOKUP(A:A,'[4]TD90D PZAS'!$A:$A,'[4]TD90D PZAS'!$CW:$CW,"",0,1) -> 0 | T93: =_xlfn.XLOOKUP(A:A,'[4]TD90D PZAS'!$A:$A,'[4]TD90D PZAS'!$CX:$CX,"",0,1) -> 0 | U93: =_xlfn.XLOOKUP(A:A,'[4]TD90D PZAS'!$A:$A,'[4]TD90D PZAS'!$DA:$DA,"",0,1) -> 0
A94: 28966 | B94: =_xlfn.XLOOKUP(A:A,[1]Hoja1!$C:$C,[1]Hoja1!$D:$D,"",0,1) -> BRILLON NEGRO MATE | C94: 3 | D94: =_xlfn.XLOOKUP(A:A,[2]Hoja1!$C:$C,[2]Hoja1!$H:$H,"",0,1) -> 58.62 | E94: =_xlfn.XLOOKUP(A:A,[1]Hoja1!$C:$C,[1]Hoja1!$H:$H,"",0,1) -> 43.97 | F94: =_xlfn.XLOOKUP(A:A,TD!A:A,TD!EC:EC,"",0,1) -> 5.3333333 | G94: =INT(F94) -> 5 | H94: =D94*$G$5 -> 175.86 | I94: =E94*$G$5 -> 131.91 | J94: 28966 | K94: =_xlfn.XLOOKUP(J:J,'[3]FILTROS 2'!$A:$A,'[3]FILTROS 2'!$E:$E,"",0,1) -> ESMALTE - BRILLON | O94: =_xlfn.XLOOKUP(A:A,[4]TD90D!$A:$A,[4]TD90D!$CW:$CW,"",0,1) -> 4 | P94: =_xlfn.XLOOKUP(A:A,[4]TD90D!$A:$A,[4]TD90D!$CX:$CX,"",0,1) -> 2 | Q94: =_xlfn.XLOOKUP(A:A,[4]TD90D!$A:$A,[4]TD90D!$DA:$DA,"",0,1) -> 0 | R94: =P94/C94 -> 0.66666667 | S94: =_xlfn.XLOOKUP(A:A,'[4]TD90D PZAS'!$A:$A,'[4]TD90D PZAS'!$CW:$CW,"",0,1) -> 16 | T94: =_xlfn.XLOOKUP(A:A,'[4]TD90D PZAS'!$A:$A,'[4]TD90D PZAS'!$CX:$CX,"",0,1) -> 2 | U94: =_xlfn.XLOOKUP(A:A,'[4]TD90D PZAS'!$A:$A,'[4]TD90D PZAS'!$DA:$DA,"",0,1) -> 0
A95: VG-50214 | B95: =_xlfn.XLOOKUP(A:A,[1]Hoja1!$C:$C,[1]Hoja1!$D:$D,"",0,1) -> VINILICA GLOSI MARFIL 5A | C95: 3 | D95: =_xlfn.XLOOKUP(A:A,[2]Hoja1!$C:$C,[2]Hoja1!$H:$H,"",0,1) -> 107.76 | E95: =_xlfn.XLOOKUP(A:A,[1]Hoja1!$C:$C,[1]Hoja1!$H:$H,"",0,1) -> 78.45 | F95: =_xlfn.XLOOKUP(A:A,TD!A:A,TD!EC:EC,"",0,1) -> 3.3333333 | G95: =INT(F95) -> 3 | H95: =D95*$G$5 -> 323.28 | I95: =E95*$G$5 -> 235.35 | J95: VG-50214 | K95: =_xlfn.XLOOKUP(J:J,'[3]FILTROS 2'!$A:$A,'[3]FILTROS 2'!$E:$E,"",0,1) -> VINILICA - GLOSI 5 AÑOS | O95: =_xlfn.XLOOKUP(A:A,[4]TD90D!$A:$A,[4]TD90D!$CW:$CW,"",0,1) | P95: =_xlfn.XLOOKUP(A:A,[4]TD90D!$A:$A,[4]TD90D!$CX:$CX,"",0,1) | Q95: =_xlfn.XLOOKUP(A:A,[4]TD90D!$A:$A,[4]TD90D!$DA:$DA,"",0,1) | R95: =P95/C95 -> #VALUE! | S95: =_xlfn.XLOOKUP(A:A,'[4]TD90D PZAS'!$A:$A,'[4]TD90D PZAS'!$CW:$CW,"",0,1) | T95: =_xlfn.XLOOKUP(A:A,'[4]TD90D PZAS'!$A:$A,'[4]TD90D PZAS'!$CX:$CX,"",0,1) | U95: =_xlfn.XLOOKUP(A:A,'[4]TD90D PZAS'!$A:$A,'[4]TD90D PZAS'!$DA:$DA,"",0,1)
A96: 2380 | B96: =_xlfn.XLOOKUP(A:A,[1]Hoja1!$C:$C,[1]Hoja1!$D:$D,"",0,1) -> AEROSOL ACRILICO TRANSPARENTE | C96: 3 | D96: =_xlfn.XLOOKUP(A:A,[2]Hoja1!$C:$C,[2]Hoja1!$H:$H,"",0,1) -> 71.55 | E96: =_xlfn.XLOOKUP(A:A,[1]Hoja1!$C:$C,[1]Hoja1!$H:$H,"",0,1) -> 53.45 | F96: =_xlfn.XLOOKUP(A:A,TD!A:A,TD!EC:EC,"",0,1) -> 6 | G96: =INT(F96) -> 6 | H96: =D96*$G$5 -> 214.65 | I96: =E96*$G$5 -> 160.35 | J96: 2380 | K96: =_xlfn.XLOOKUP(J:J,'[3]FILTROS 2'!$A:$A,'[3]FILTROS 2'!$E:$E,"",0,1) -> AEROSOLES PRISA | O96: =_xlfn.XLOOKUP(A:A,[4]TD90D!$A:$A,[4]TD90D!$CW:$CW,"",0,1) -> 2 | P96: =_xlfn.XLOOKUP(A:A,[4]TD90D!$A:$A,[4]TD90D!$CX:$CX,"",0,1) -> 1 | Q96: =_xlfn.XLOOKUP(A:A,[4]TD90D!$A:$A,[4]TD90D!$DA:$DA,"",0,1) -> 0 | R96: =P96/C96 -> 0.33333333 | S96: =_xlfn.XLOOKUP(A:A,'[4]TD90D PZAS'!$A:$A,'[4]TD90D PZAS'!$CW:$CW,"",0,1) -> 12 | T96: =_xlfn.XLOOKUP(A:A,'[4]TD90D PZAS'!$A:$A,'[4]TD90D PZAS'!$CX:$CX,"",0,1) -> 1 | U96: =_xlfn.XLOOKUP(A:A,'[4]TD90D PZAS'!$A:$A,'[4]TD90D PZAS'!$DA:$DA,"",0,1) -> 0
A97: 36093 | B97: =_xlfn.XLOOKUP(A:A,[1]Hoja1!$C:$C,[1]Hoja1!$D:$D,"",0,1) -> PEGAMENTO / SELLADOR | C97: 3 | D97: =_xlfn.XLOOKUP(A:A,[2]Hoja1!$C:$C,[2]Hoja1!$H:$H,"",0,1) -> 250.86 | E97: =_xlfn.XLOOKUP(A:A,[1]Hoja1!$C:$C,[1]Hoja1!$H:$H,"",0,1) -> 197.41 | F97: =_xlfn.XLOOKUP(A:A,TD!A:A,TD!EC:EC,"",0,1) -> 4 | G97: =INT(F97) -> 4 | H97: =D97*$G$5 -> 752.58 | I97: =E97*$G$5 -> 592.23 | J97: 36093 | K97: =_xlfn.XLOOKUP(J:J,'[3]FILTROS 2'!$A:$A,'[3]FILTROS 2'!$E:$E,"",0,1) -> SELLADOR - VINILICO GLOSI | O97: =_xlfn.XLOOKUP(A:A,[4]TD90D!$A:$A,[4]TD90D!$CW:$CW,"",0,1) -> 2 | P97: =_xlfn.XLOOKUP(A:A,[4]TD90D!$A:$A,[4]TD90D!$CX:$CX,"",0,1) -> 1 | Q97: =_xlfn.XLOOKUP(A:A,[4]TD90D!$A:$A,[4]TD90D!$DA:$DA,"",0,1) -> 0 | R97: =P97/C97 -> 0.33333333 | S97: =_xlfn.XLOOKUP(A:A,'[4]TD90D PZAS'!$A:$A,'[4]TD90D PZAS'!$CW:$CW,"",0,1) -> 14 | T97: =_xlfn.XLOOKUP(A:A,'[4]TD90D PZAS'!$A:$A,'[4]TD90D PZAS'!$CX:$CX,"",0,1) -> 1 | U97: =_xlfn.XLOOKUP(A:A,'[4]TD90D PZAS'!$A:$A,'[4]TD90D PZAS'!$DA:$DA,"",0,1) -> 0
A98: 19BYC | B98: =_xlfn.XLOOKUP(A:A,[1]Hoja1!$C:$C,[1]Hoja1!$D:$D,"",0,1) | C98: 3 | D98: =_xlfn.XLOOKUP(A:A,[2]Hoja1!$C:$C,[2]Hoja1!$H:$H,"",0,1) -> 29999.14 | E98: =_xlfn.XLOOKUP(A:A,[1]Hoja1!$C:$C,[1]Hoja1!$H:$H,"",0,1) | F98: =_xlfn.XLOOKUP(A:A,TD!A:A,TD!EC:EC,"",0,1) -> -1 | G98: =INT(F98) -> -1 | H98: =D98*$G$5 -> 89997.42 | I98: =E98*$G$5 -> #VALUE! | J98: 19BYC | K98: =_xlfn.XLOOKUP(J:J,'[3]FILTROS 2'!$A:$A,'[3]FILTROS 2'!$E:$E,"",0,1) | O98: =_xlfn.XLOOKUP(A:A,[4]TD90D!$A:$A,[4]TD90D!$CW:$CW,"",0,1) -> 5 | P98: =_xlfn.XLOOKUP(A:A,[4]TD90D!$A:$A,[4]TD90D!$CX:$CX,"",0,1) -> 2 | Q98: =_xlfn.XLOOKUP(A:A,[4]TD90D!$A:$A,[4]TD90D!$DA:$DA,"",0,1) -> 0 | R98: =P98/C98 -> 0.66666667 | S98: =_xlfn.XLOOKUP(A:A,'[4]TD90D PZAS'!$A:$A,'[4]TD90D PZAS'!$CW:$CW,"",0,1) -> -5 | T98: =_xlfn.XLOOKUP(A:A,'[4]TD90D PZAS'!$A:$A,'[4]TD90D PZAS'!$CX:$CX,"",0,1) -> 0 | U98: =_xlfn.XLOOKUP(A:A,'[4]TD90D PZAS'!$A:$A,'[4]TD90D PZAS'!$DA:$DA,"",0,1) -> 0
A99: 61200 | B99: =_xlfn.XLOOKUP(A:A,[1]Hoja1!$C:$C,[1]Hoja1!$D:$D,"",0,1) -> MEMBRANA DE REFUERZO P/IMPER 17/105 20 G | C99: 3 | D99: =_xlfn.XLOOKUP(A:A,[2]Hoja1!$C:$C,[2]Hoja1!$H:$H,"",0,1) -> 452.59 | E99: =_xlfn.XLOOKUP(A:A,[1]Hoja1!$C:$C,[1]Hoja1!$H:$H,"",0,1) -> 339.66 | F99: =_xlfn.XLOOKUP(A:A,TD!A:A,TD!EC:EC,"",0,1) -> 1 | G99: =INT(F99) -> 1 | H99: =D99*$G$5 -> 1357.77 | I99: =E99*$G$5 -> 1018.98 | J99: 61200 | K99: =_xlfn.XLOOKUP(J:J,'[3]FILTROS 2'!$A:$A,'[3]FILTROS 2'!$E:$E,"",0,1) -> HERRAMIENTAS EN GENERAL | O99: =_xlfn.XLOOKUP(A:A,[4]TD90D!$A:$A,[4]TD90D!$CW:$CW,"",0,1) -> 4 | P99: =_xlfn.XLOOKUP(A:A,[4]TD90D!$A:$A,[4]TD90D!$CX:$CX,"",0,1) -> 2 | Q99: =_xlfn.XLOOKUP(A:A,[4]TD90D!$A:$A,[4]TD90D!$DA:$DA,"",0,1) -> 0 | R99: =P99/C99 -> 0.66666667 | S99: =_xlfn.XLOOKUP(A:A,'[4]TD90D PZAS'!$A:$A,'[4]TD90D PZAS'!$CW:$CW,"",0,1) -> 4 | T99: =_xlfn.XLOOKUP(A:A,'[4]TD90D PZAS'!$A:$A,'[4]TD90D PZAS'!$CX:$CX,"",0,1) -> 2 | U99: =_xlfn.XLOOKUP(A:A,'[4]TD90D PZAS'!$A:$A,'[4]TD90D PZAS'!$DA:$DA,"",0,1) -> 0
A100: 28936 | B100: =_xlfn.XLOOKUP(A:A,[1]Hoja1!$C:$C,[1]Hoja1!$D:$D,"",0,1) -> BRILLON GRIS | C100: 3 | D100: =_xlfn.XLOOKUP(A:A,[2]Hoja1!$C:$C,[2]Hoja1!$H:$H,"",0,1) -> 58.62 | E100: =_xlfn.XLOOKUP(A:A,[1]Hoja1!$C:$C,[1]Hoja1!$H:$H,"",0,1) -> 43.97 | F100: =_xlfn.XLOOKUP(A:A,TD!A:A,TD!EC:EC,"",0,1) -> 8 | G100: =INT(F100) -> 8 | H100: =D100*$G$5 -> 175.86 | I100: =E100*$G$5 -> 131.91 | J100: 28936 | K100: =_xlfn.XLOOKUP(J:J,'[3]FILTROS 2'!$A:$A,'[3]FILTROS 2'!$E:$E,"",0,1) -> ESMALTE - BRILLON | O100: =_xlfn.XLOOKUP(A:A,[4]TD90D!$A:$A,[4]TD90D!$CW:$CW,"",0,1) | P100: =_xlfn.XLOOKUP(A:A,[4]TD90D!$A:$A,[4]TD90D!$CX:$CX,"",0,1) | Q100: =_xlfn.XLOOKUP(A:A,[4]TD90D!$A:$A,[4]TD90D!$DA:$DA,"",0,1) | R100: =P100/C100 -> #VALUE! | S100: =_xlfn.XLOOKUP(A:A,'[4]TD90D PZAS'!$A:$A,'[4]TD90D PZAS'!$CW:$CW,"",0,1) | T100: =_xlfn.XLOOKUP(A:A,'[4]TD90D PZAS'!$A:$A,'[4]TD90D PZAS'!$CX:$CX,"",0,1) | U100: =_xlfn.XLOOKUP(A:A,'[4]TD90D PZAS'!$A:$A,'[4]TD90D PZAS'!$DA:$DA,"",0,1)
A101: 28774 | B101: =_xlfn.XLOOKUP(A:A,[1]Hoja1!$C:$C,[1]Hoja1!$D:$D,"",0,1) -> BRILLON VERDE SELVA | C101: 3 | D101: =_xlfn.XLOOKUP(A:A,[2]Hoja1!$C:$C,[2]Hoja1!$H:$H,"",0,1) -> 150.86 | E101: =_xlfn.XLOOKUP(A:A,[1]Hoja1!$C:$C,[1]Hoja1!$H:$H,"",0,1) -> 112.93 | F101: =_xlfn.XLOOKUP(A:A,TD!A:A,TD!EC:EC,"",0,1) -> 6 | G101: =INT(F101) -> 6 | H101: =D101*$G$5 -> 452.58 | I101: =E101*$G$5 -> 338.79 | J101: 28774 | K101: =_xlfn.XLOOKUP(J:J,'[3]FILTROS 2'!$A:$A,'[3]FILTROS 2'!$E:$E,"",0,1) -> ESMALTE - BRILLON | O101: =_xlfn.XLOOKUP(A:A,[4]TD90D!$A:$A,[4]TD90D!$CW:$CW,"",0,1) -> 4 | P101: =_xlfn.XLOOKUP(A:A,[4]TD90D!$A:$A,[4]TD90D!$CX:$CX,"",0,1) -> 2 | Q101: =_xlfn.XLOOKUP(A:A,[4]TD90D!$A:$A,[4]TD90D!$DA:$DA,"",0,1) -> 0 | R101: =P101/C101 -> 0.66666667 | S101: =_xlfn.XLOOKUP(A:A,'[4]TD90D PZAS'!$A:$A,'[4]TD90D PZAS'!$CW:$CW,"",0,1) -> 24 | T101: =_xlfn.XLOOKUP(A:A,'[4]TD90D PZAS'!$A:$A,'[4]TD90D PZAS'!$CX:$CX,"",0,1) -> 2 | U101: =_xlfn.XLOOKUP(A:A,'[4]TD90D PZAS'!$A:$A,'[4]TD90D PZAS'!$DA:$DA,"",0,1) -> 0
...

Sheet SUGERIDO FINAL
A1: SKU | B1: PRODUCTO | C1: MARCA | D1: PROPUESTA
A2: 28984 | B2: =_xlfn.XLOOKUP(A:A,[1]Hoja1!$C:$C,[1]Hoja1!$D:$D,"",0,1) -> BRILLON NEGRO | C2: ESMALTE - BRILLON | D2: ='POR PRODUCTO MAS COM'!L7 -> 4
A3: 28004 | B3: =_xlfn.XLOOKUP(A:A,[1]Hoja1!$C:$C,[1]Hoja1!$D:$D,"",0,1) -> ESMALTE BRILLON BLANCO | C3: ESMALTE - BRILLON | D3: ='POR PRODUCTO MAS COM'!L8 -> 4
A4: 28005 | B4: =_xlfn.XLOOKUP(A:A,[1]Hoja1!$C:$C,[1]Hoja1!$D:$D,"",0,1) -> BRILLON BLANCO | C4: ESMALTE - BRILLON | D4: ='POR PRODUCTO MAS COM'!L9 -> 3
A5: 28985 | B5: =_xlfn.XLOOKUP(A:A,[1]Hoja1!$C:$C,[1]Hoja1!$D:$D,"",0,1) -> BRILLON NEGRO | C5: ESMALTE - BRILLON | D5: ='POR PRODUCTO MAS COM'!L10 -> 4
A6: 28986 | B6: =_xlfn.XLOOKUP(A:A,[1]Hoja1!$C:$C,[1]Hoja1!$D:$D,"",0,1) -> BRILLON NEGRO | C6: ESMALTE - BRILLON | D6: ='POR PRODUCTO MAS COM'!L11 -> 4
A7: 28006 | B7: =_xlfn.XLOOKUP(A:A,[1]Hoja1!$C:$C,[1]Hoja1!$D:$D,"",0,1) -> BRILLON BLANCO | C7: ESMALTE - BRILLON | D7: ='POR PRODUCTO MAS COM'!L12 -> 4
A8: 2399 | B8: =_xlfn.XLOOKUP(A:A,[1]Hoja1!$C:$C,[1]Hoja1!$D:$D,"",0,1) -> AEROSOL NEGRO BRILLANTE | C8: AEROSOLES PRISA | D8: ='POR PRODUCTO MAS COM'!L13 -> 6
A9: 2300 | B9: =_xlfn.XLOOKUP(A:A,[1]Hoja1!$C:$C,[1]Hoja1!$D:$D,"",0,1) -> AEROSOL BLANCO BRILLANTE | C9: AEROSOLES PRISA | D9: ='POR PRODUCTO MAS COM'!L14 -> 6
A10: 29014 | B10: =_xlfn.XLOOKUP(A:A,[1]Hoja1!$C:$C,[1]Hoja1!$D:$D,"",0,1) -> RELLENADOR AUTOMOTRIZ C/CATAL. ROJO | C10: PASTA RELLENADORA | D10: ='POR PRODUCTO MAS COM'!L15 -> 3
A11: 79234 | B11: =_xlfn.XLOOKUP(A:A,[1]Hoja1!$C:$C,[1]Hoja1!$D:$D,"",0,1) -> SIAMIL ECONOMICO MI FL 20 KG | C11: SIAMIL | D11: ='POR PRODUCTO MAS COM'!L16 -> 4
A12: 2398 | B12: =_xlfn.XLOOKUP(A:A,[1]Hoja1!$C:$C,[1]Hoja1!$D:$D,"",0,1) -> AEROSOL NEGRO MATE | C12: AEROSOLES PRISA | D12: ='POR PRODUCTO MAS COM'!L18 -> 5
A13: 2390 | B13: =_xlfn.XLOOKUP(A:A,[1]Hoja1!$C:$C,[1]Hoja1!$D:$D,"",0,1) -> AEROSOL ALUMINIO | C13: AEROSOLES PRISA | D13: ='POR PRODUCTO MAS COM'!L20 -> 3
A14: VG-50013 | B14: =_xlfn.XLOOKUP(A:A,[1]Hoja1!$C:$C,[1]Hoja1!$D:$D,"",0,1) -> VINILICA GLOSI BLANCO ULTRA | C14: VINILICA - GLOSI 3 AÑOS | D14: ='POR PRODUCTO MAS COM'!L22 -> 8
